Workbook
Name Ampliación_de_capital_1: 'ANALISIS '!$L$8
Name año_fin_fianza: 'HIPOTESIS '!$F$40
Name años_amortiz_activ1: 'HIPOTESIS '!$F$52
Name años_amortiz_activ2: 'HIPOTESIS '!$F$55
Name años_amortiz_inv1: 'HIPOTESIS '!$F$44
Name años_amortiz_inv2: 'HIPOTESIS '!$F$47
Name años_subv_activ1: 'HIPOTESIS '!$F$53
Name años_subv_activ2: 'HIPOTESIS '!$F$56
Name años_subvencion1: 'HIPOTESIS '!$F$45
Name años_subvencion2: 'HIPOTESIS '!$F$48
Name carencia_p1: 'HIPOTESIS '!$E$66
Name carencia_p2: 'HIPOTESIS '!$E$67
Name carencia_prest_participa: 'ANALISIS '!$M$11
Name existencias_A: 'HIPOTESIS '!$P$131
Name existencias_B: 'HIPOTESIS '!$P$132
Name existencias_C: 'HIPOTESIS '!$P$133
Name final_amortiz_activ1: 'HIPOTESIS '!$K$52
Name final_amortiz_activ2: 'HIPOTESIS '!$K$55
Name final_inv1: 'HIPOTESIS '!$H$44
Name final_inv2: 'HIPOTESIS '!$H$47
Name final_p1: 'HIPOTESIS '!$G$66
Name final_p2: 'HIPOTESIS '!$G$67
Name final_prest_participa: 'ANALISIS '!$O$11
Name final_subv_activ1: 'HIPOTESIS '!$K$53
Name final_subv_activ2: 'HIPOTESIS '!$K$56
Name final_subv_inv1: 'HIPOTESIS '!$H$45
Name final_subv_inv2: 'HIPOTESIS '!$H$48
Name final_trabaj_activacion1: 'HIPOTESIS '!$H$52
Name final_trabaj_activacion2: 'HIPOTESIS '!$H$55
Name imp_activacion1: 'HIPOTESIS '!$C$52
Name imp_activacion2: 'HIPOTESIS '!$C$55
Name imp_inv1: 'HIPOTESIS '!$C$44
Name imp_inv2: 'HIPOTESIS '!$C$47
Name imp_mensual_trabajo_activ1: 'HIPOTESIS '!$I$52
Name imp_mensual_trabajo_activ2: 'HIPOTESIS '!$I$55
Name imp_p1: 'HIPOTESIS '!$D$66
Name imp_p2: 'HIPOTESIS '!$D$67
Name imp_subv_activ1: 'HIPOTESIS '!$C$53
Name imp_subv_activ2: 'HIPOTESIS '!$C$56
Name imp_subv_inv1: 'HIPOTESIS '!$C$45
Name imp_subv_inv2: 'HIPOTESIS '!$C$48
Name importe_fianza: 'HIPOTESIS '!$C$40
Name importe_prest_participa: 'ANALISIS '!$L$11
Name inicio_amortiz_activ1: 'HIPOTESIS '!$J$52
Name inicio_amortiz_activ2: 'HIPOTESIS '!$J$55
Name inicio_inv1: 'HIPOTESIS '!$G$44
Name inicio_inv2: 'HIPOTESIS '!$G$47
Name inicio_p1: 'HIPOTESIS '!$C$66
Name inicio_p2: 'HIPOTESIS '!$C$67
Name inicio_prest_participa: 'ANALISIS '!$K$11
Name inicio_subv_activ1: 'HIPOTESIS '!$J$53
Name inicio_subv_activ2: 'HIPOTESIS '!$J$56
Name inicio_subv_inv1: 'HIPOTESIS '!$G$45
Name inicio_subv_inv2: 'HIPOTESIS '!$G$48
Name inicio_trabaj_activacion1: 'HIPOTESIS '!$G$52
Name inicio_trabaj_activacion2: 'HIPOTESIS '!$G$55
Name interes_inicio_prest_participa: 'ANALISIS '!$P$11
Name interes_p1: 'HIPOTESIS '!$H$66
Name interes_p2: 'HIPOTESIS '!$H$67
Name interes_participativo_prest_participa: 'ANALISIS '!$Q$11

Sheet IDEA
A4: HOJA DE RUTA DEL PLAN ECONÓMICO FINANCIERO (PEF) CON TOOLBOARD CANVAS
B6: http://toolboardcanvas.com/ | K6: METODOLOGÍA TOOLBOARD CANVAS DE EMPRENDIMIENTO Y INNOVACIÓN Esta hoja de cálculo desarrollada mediante excel es la herramienta 8 de TOOLBOARD . Forma parte del libro "El Viaje del emprendedor: generación de iniciativas de emprendimiento y innovación con ToolBoard Canvas". Accede gratuitamente y si quieres saber más visita: http://toolboardcanvas.com/ o escribe al autor: jaumeteodoro@gmail.com Las hojas están inicialmente completadas con un ejemplo anónimo a sobrescribir.
B8: jaumeteodoro@gmail.com
B10: IDENTIFICACIÓN DEL PROYECTO
B11: Nombre del proyecto: | C11: Nombre_Proyecto | H11: Link: | I11: www.proyecto.com
B12: Integrantes del equipo: | C12: Nombre_apellido1; Nombre_Apellido2 | H12: Contacto: | I12: a@gmail.com
B13: Fecha: | C13: 1/1/00 | H13: Versión: | I13: 1.0
A16: Parte I: DESCRIPCIÓN DEL NEGOCIO
B20: A- PROBLEMA-SOLUCIÓN (problem -solution fit)
B64: B- MODELO DE NEGOCIO (Business Model)
B66: Parte derecha del Canvas (Cliente y estrategias de márquetin para capturar y retener los clientes)
B89: Parte izquierda del Canvas (organización y operaciones de explotación de la organización)
B117: C- PLANIFICACIÓN (Milestones)
B119: Los hitos de negocio son todos aquellas circunstancias esperadas que son relevantes cara a la elaboración del Plan Económico Financiero (PEF). Se trata de grandes objetivos que el equipo emprendedor asume en su lógica para progresar de la idea inicial a un proyecto empresarial real. Se situan en el eje temporal en un diagrama como el adjunto, a título de ejemplo, a partir de un nombre/ descriptor del hito, una fecha estimada, una métrica y un importe asociado a la consecución del hito.
B122: HITO | C122: DESCRIPTOR | D122: FECHA | F122: RECURSOS | H122: IMPORTE | J122: OBSERVACIONES
B123: 1 | C123: EQUIPO: Constitución del equipo de fundadores | D123: Año 0 /I | F123: Team Manifesto | H123: 1000 | J123: Fondos iniciales tipo FFF para empezar , pendientes de formalizar en el momento de la constitución de la empresa.
B124: 2 | C124: IDEA Y PROTOTIPO: Planteamiento, esbozo y primera validación de la idea con su modelo de negocio. | D124: Año 0 /I | F124: Prototipo conceptual | H124: -500 | J124: Desarrollo de la idea y inversión en la prototipo conceptual
B125: 3 | C125: PITCH DE LA IDEA: Cierre de una primera versión del Pitch a efectos de equipo y otros stakeholders. | D125: Año 0/ I | F125: Eventos de Pitch | H125: -500 | J125: Desarrollo del ToolBoard Canvas de inicio que muestra la idea y el modelo de negocio de partida. Orientado a equipo y programas de soporte a emprendedores. Canvas con acceso desde : www.Miro.com /proyecto
B126: 4 | C126: SOCIEDAD: Constitución de la Sociedad y primeras inversiones operativas en año 0. | D126: Año 0 / II | F126: Acto de constitución. Capital social | H126: 25000 | J126: Primeros fondos FFF aportados por los fundadores (se considera todo el año 0 como mes 0 del proyecto) y fondos seed capital (pequeños inversores, subvenciones y premios). Se llevan a cabo las primeras inversiones. Se incurre en los primeros gastos fijos y de personal (salarios de los fundadores y de otros integrantes del equipo). Es común que parte de los costes de personal relativos a los fundadores no se desembolsen hasta que exista actividad económica.
B127: 5 | C127: MVP: Validación en mercado real en una incubadora o aceleradora. Primeras ventas usuarios tempranos. | D127: Año 0 / II | F127: Realización y usuarios tempranos | H127: -10000 | J127: Validación con clientes en mercado real. Inversión en el MVP. Identificación de los early adopters.
B128: 6 | C128: PLAN ECONÓMICO FINANCIERO (PEF). A partir de los primeros resultados en mercado real se desarrolla un primer PEF | D128: Año 0 / II | F128: Personal propio y asesores | H128: 0 | J128: Realización del primer borrador del PEF a partir del modelo de negocio y las conclusiones del proceso de validación. Se trabaja con escenarios a fin de gestionar el dilema de la prudencia. En este momento es posible que la iniciativa ingrese en una incubadora o en un programa de aceleración
B129: 7 | C129: INVERSIONES INICIALES: Inversiones y trabajos para el propio activo indispensables para inicio de las operaciones | D129: Año 1 / I | F129: Personal propio y alianzas | H129: (mmmm) | J129: Actividad de inversiones de partida a la que se suma la investigación, desarrollo y innovación (I+D+i) que lleva a la creación de activos intangibles con recursos propios (trabajos para el propio activo en el PEF). Puede ser el caso de una patente industrial, un proceso de fabricación de un producto, un software y en general cualquier activo elaborado con recursos propios (desembolsados o pendientes de desembolsar) que la Startup va a rentabilizar a lo largo del tiempo.
B130: 8 | C130: INICIO OPERATIVO: Empieza el ciclo de ventas y la acción de márquetin con las primeras inversiones. | D130: Año I/I | F130: Clientes reales | H130: >0 | J130: Foco en ventas reales que validen y muestren la creación de valor. Uso de la métrica de negocio identificada en el PEF para medir objetivos, según tipo de industria: leads, usuarios, ventas, descargas, … En este momento se produce la incorporación de nuevo personal en nómina.
B131: 9 | C131: PITCH DE LA STARTUP: Nuevo Pitch con ToolBoard Canvas orientado a inversionistas de capital (angel capital) | D131: Año 1 /II | F131: Foros de inversión | H131: 0 | J131: Desarrollo completo con ToolBoard Canvas, incluyendo los resultados del MVP y el primer borrador del PEF.
B132: 10 | C132: AMPLIACIÓN DE CAPITAL : Momento en que se espera la entrada de inversores (Angel Capital) | D132: Año 2 y en adelante | F132: Según valoración de empresa y % de la propiedad a cambio | H132: 20% -30% de la propiedad | J132: Para la entrada de socios inversores de capital va ser necesario mostrar métricas de negocio con las que poder hacer una valoración de la startup. El emprendedor hace frente al dilema de la dilución buscando el mejor momento para dar entrada a inversores
B133: 11 | C133: ESCALABILIDAD: Nuevas inversiones a medida que se consiguen objetivos de ventas. Adaptación de la estructura (gastos fijos) según métricas de crecimiento y disponible. | D133: Año 2 y en adelante | F133: Proyectos de inversión | H133: n x 1.000 | J133: Incremento de la capacidad productiva, comercial y de gestión a partir de nuevos proyectos de inversión y ampliaciones de la estructura de la empresa. Puede tratarse de nuevos productos, servicios, funcionalidades o expansión en un nuevo mercado.
B134: 12 | C134: PUNTO MUERTO: Momento en que se provee alcanzar el punto de equilibrio | D134: Año 1 o 2 o en adelante | F134: EBT | H134: >0 | J134: El punto de equilibrio (Ingresos Totales = Gastos Totales) se calcula con la hoja de cálculo a partir de la proyección de la cuenta de resultados. El proyecto va a requerir un tiempo para alcanzar este umbral de rentabilidad. Durante este tiempo las métricas de crecimiento (ventas) son la referencia valorar el desarrollo del proyecto. A partir del umbral la métrica básica para medir el proyecto será la rentabilidad en EBT.
B135: 13 | C135: APALANCAMIENTO / CAPITAL INSTITUCIONAL: Captación de recursos financieros externos a partir de préstamos | D135: Año 3 y en adelante | F135: Préstamos bancarios | H135: (mmmm) | J135: Momento en que los datos de la empresa permiten su valoración y con ello obtener financiación externa. El objetivo es obtener la máxima eficiencia en cuanto a fondos propios buscando el máximo apalancamiento posible si la solvencia de la empresa y el tipo de interés del dinero lo permite.
B139: Diagrama de hitos:

Sheet HIPOTESIS 
B2: www.toolboardcanvas.com
A4: Parte II: HIPÓTESIS DE NEGOCIO
B6: FISCALIDAD (Taxes)
B8: FISCALIDAD | C8: #1 | D8: #2 | E8: # 3 | F8: OBSERVACIONES
B9: Impuesto de sociedades (IS) | C9: 0.25 | F9: Cada país tiene un tipo medio estimado. En este caso se estima un tipo medio del 25% para España.
B10: Impuesto del Valor Añadido (IVA) de las compras | C10: 0.21 | F10: Los tipos de IVA se pueden cambiar según normativa del impuesto en cada país. Por este motivo se puede modificar el dato de esta tabla, que por defecto es del 21%. La liquidación de IVA en esta hoja de cálculo se hace por meses. Todos los importes a entrar en hipótesis iniciales en adelante se entran sin IVA.
B11: Impuesto del Valor Añadido (IVA) de las ventas | C11: 0.21
B12: Impuesto del Valor Añadido (IVA) de las inversiones | C12: 0.21
B13: Seguro social régimen especial de autónomos | C13: 0.15 | D13: 0 | E13: 56640 | F13: El primer dato corresponde a lo que paga la empresa y el segundo a lo que paga el trabajador. El tercer dato corresponde al tope máximo a partir del cual ya no se paga más.
B14: Seguro social régimen general | C14: 0.33 | D14: 0.0647 | E14: 56640
B15: Retención RENTA a los trabajadores (IRPF) | C15: 0 | D15: 0.2 | E15: 0.4 | F15: Se hace un cálculo abreviado muy simple, solamente en 3 tramos (#1, #2 y #3) de forma que en cada tramo se indica un porcentaje de retención según sueldo bruto: . #1 en 0% para salario bruto menor a 15.000,#2 en 20% entre 15.000 y 90.000 y #3 en 40% por encima de 90.000). Si se desea se puede hacer el cálculo precisa accediendo a la web de hacienda una vez conocidos los trabajadores y sus características personales.
B19: º
A21: A. HIPÓTESIS SOBRE INVERSIONES (CAPEX)
B24: INVERSIONES DE INICIO (Año 0) | C24: IMPORTE | D24: %IVA | E24: IVA | F24: AÑOS AMORTIZA. | G24: MES ADQUISICIÓN | H24: MES FIN AMORTIZA. | I24: OBSERVACIONES
B25: Inmovilizado intangible
B26: Investigación y desarrollo | C26: 0 | D26: =IVA_inversiones -> 0.21 | E26: =C26*D26 -> 0 | F26: 5 | G26: 0 | H26: =F26*12+G26 -> 60
B27: Patentes y marcas | C27: 0 | D27: =IVA_inversiones -> 0.21 | E27: =C27*D27 -> 0 | F27: 10 | G27: 0 | H27: =F27*12+G27 -> 120
B28: Aplicaciones informáticas | C28: 0 | D28: =IVA_inversiones -> 0.21 | E28: =C28*D28 -> 0 | F28: 5 | G28: 0 | H28: =F28*12+G28 -> 60
B29: Otros inmovilizados intangibles | C29: 0 | D29: =IVA_inversiones -> 0.21 | E29: =C29*D29 -> 0 | F29: 5 | G29: 0 | H29: =F29*12+G29 -> 60
B30: Inmovilizado material
B31: Terrenos y construcciones | C31: 0 | D31: 0 | E31: =C31*D31 -> 0 | F31: 50 | G31: 0 | H31: =F31*12+G31 -> 600
B32: Instalaciones | C32: 0 | D32: =IVA_inversiones -> 0.21 | E32: =C32*D32 -> 0 | F32: 10 | G32: 0 | H32: =F32*12+G32 -> 120
B33: Maquinaria | C33: 0 | D33: =IVA_inversiones -> 0.21 | E33: =C33*D33 -> 0 | F33: 10 | G33: 0 | H33: =F33*12+G33 -> 120
B34: Equipos para procesos de información( EPIs) | C34: 0 | D34: =IVA_inversiones -> 0.21 | E34: =C34*D34 -> 0 | F34: 5 | G34: 0 | H34: =F34*12+G34 -> 60
B35: Mobiliario | C35: 0 | D35: =IVA_inversiones -> 0.21 | E35: =C35*D35 -> 0 | F35: 10 | G35: 0 | H35: =F35*12+G35 -> 120
B36: Vehículos | C36: 0 | D36: =IVA_inversiones -> 0.21 | E36: =C36*D36 -> 0 | F36: 10 | G36: 0 | H36: =F36*12+G36 -> 120
B37: Otros inmovilizados materiales | C37: 0 | D37: =IVA_inversiones -> 0.21 | E37: =C37*D37 -> 0 | F37: 5 | G37: 0 | H37: =F37*12+G37 -> 60
B38: Total inversiones al inicio | C38: =C26+C27+C28+C29+C31+C32+C33+C34+C35+C36+C37 -> 0 | E38: =SUM(E26:E37) -> 0
B39: Fianzas y depósitos | I39: Indicar aquí las inversiones de tipo finazas y depósitos necesarias para arrancar el proyecto (mes 0).
B40: Fianzas y depósitos a largo plazo | C40: 0 | F40: 5 | G40: 1
B42: PROYECTOS DE INVERSIÓN EN AÑOS POSTERIORES | C42: IMPORTE | D42: %IVA | E42: IVA | F42: AÑOS AMORTIZA. | G42: MES ADQUISICIÓN | H42: MES FIN AMORTIZA. | I42: OBSERVACIONES
B43: Detalle de la nueva inversión (1) | I43: Explicar aquí en que consiste el proyecto 1 y si existe una subención de capital
B44: Nuevo proyecto de inversión 1 | C44: 0 | D44: =IVA_inversiones -> 0.21 | E44: =imp_inv1*D44 -> 0 | F44: 1 | G44: 1 | H44: =inicio_inv1+años_amortiz_inv1*12 -> 13
B45: Subvención de capital por inversión (1) | C45: 0 | D45: 0 | F45: 1 | G45: 1 | H45: =H44 -> 13
B46: Detalle de la nueva inversión (2) | I46: Explicar aquí en que consiste el proyecto 2 y si existe una subvención de capital
B47: Nuevo proyecto de inversión 2 | C47: 0 | D47: =IVA_inversiones -> 0.21 | E47: =imp_inv2*D47 -> 0 | F47: 1 | G47: 1 | H47: =inicio_inv2+años_amortiz_inv2*12 -> 13
B48: Subvención de capital por inversión (2) | C48: 0 | D48: 0 | F48: =años_amortiz_inv2 -> 1 | G48: =inicio_inv2 -> 1 | H48: =H47 -> 13
B50: PROYECTOS DE TRABAJO PARA EL PROPIO ACTIVO / INMOVILIZADO INTANGIBLE | C50: IMPORTE | D50: %IVA | E50: IVA | F50: AÑOS AMORTIZA. | G50: MES INICIO PROYECTO | H50: MES FIN PROYECTO | I50: IMPORTE MEDIO MENSUAL | J50: MES INICIO AMORTIZA. | K50: MES FINAL AMORTIZA. | L50: OBSERVACIONES
B51: Detalle del proyecto de activación I+D+i (1) | L51: Explica aquí en que consiste el proyecto I+D+i de trabajo para el propio activo.
B52: Proyecto de trabajo para el propio activo 1 | C52: 0 | D52: 0 | E52: 0 | F52: 1 | G52: 1 | H52: 1 | I52: =imp_activacion1/(final_trabaj_activacion1-inicio_trabaj_activacion1+1) -> 0 | J52: =final_trabaj_activacion1+1 -> 2 | K52: =inicio_amortiz_activ1+años_amortiz_activ1*12 -> 14
B53: Subvención de capital activación 1 | C53: 0 | D53: 0 | F53: =años_amortiz_activ1 -> 1 | I53: 0 | J53: =J52 -> 2 | K53: =K52 -> 14
B54: Detalle del proyecto de activación I+D+i (2)
B55: Proyecto de trabajo para el propio activo 2 | C55: 0 | D55: 0 | E55: 0 | F55: 1 | G55: 1 | H55: 1 | I55: =imp_activacion2/(final_trabaj_activacion2-inicio_trabaj_activacion2+1) -> 0 | J55: =final_trabaj_activacion2+1 -> 2 | K55: =inicio_amortiz_activ2+años_amortiz_activ2*12 -> 14
B56: Subvención de capital activación 2 | C56: 0 | D56: 0 | F56: =años_amortiz_activ2 -> 1 | I56: 0 | J56: =J55 -> 2 | K56: =K55 -> 14
A59: B. HIPÓTESIS SOBRE FINANCIACIÓN (FUNDING)
B62: FINANCIACIÓN INTERNA | C62: MES ENTRADA | D62: IMPORTE | E62: VALORACIÓN EMPRESA (PRE-MONEY) | F62: ACCIONES TOTALES EN CIRCULACIÓN | G62: VALOR MONETARIO POR ACCIÓN | H62: OBSERVACIONES
B63: Capital inicial desembolsado por los fundadores (mes 0) | C63: 0 | D63: 1000 | E63: =D63 -> 1000 | F63: 1000 | G63: =D63/F63 -> 1 | H63: Indicar importe del capital inicial y número de acciones en que se decide dividir la sociedad.
B65: FINANCIACIÓN EXTERNA | C65: MES INICIO | D65: IMPORTE | E65: MESES CARENCIA | F65: MESES AMORTIZA. | G65: MES FINAL | H65: % INTERÉS ANUAL | I65: OBSERVACIONES
B66: Préstamo 1 | C66: 1 | D66: 0 | E66: 0 | F66: 1 | G66: =inicio_p1+carencia_p1+meses_amortiz_p1 -> 2 | H66: 0.01 | I66: Explicar aquí la financiación
B67: Préstamo 2 | C67: 1 | D67: 0 | E67: 0 | F67: 1 | G67: =inicio_p2+carencia_p2+meses_amortiz_p2 -> 2 | H67: 0 | I67: Explicar aquí la financiación
B69: FINANCIACIÓN EXTERNA CON PÓLIZA DE CRÉDITO (=NECESIDAD DE REFINANCIACIÓN) | C69: IMPORTE | D69: INTERÉS | E69: OBSERVACIONES
C70: (ilimitado) | D70: 0.03 | E70: Indicar el tipo de interés de la póliza de crédito. No obstante se debe tener presente que en primeras iteraciones la cantidad sea muy alta y se deba refinanciar primero teniendo en consideración que la póliza de crédito no esta pensada para financiar la empresa sino únicamente el capital ciriculante.
A73: C. HIPÓTESIS SOBRE GASTOS OPERATIVOS DE LA EMPRESA (OPEX)
B76: GASTO FIJO ANUAL POR SERVICIOS EXTERIORES | C76: IMPORTE AÑO 1 | D76: IVA AÑO 1 | E76: % INC. AÑO 2 | F76: IMPORTE AÑO 2 | G76: IVA AÑO 2 | H76: % INC. AÑO 3 | I76: IMPORTE AÑO 3 | J76: IVA AÑO 3 | K76: % INC. AÑO 4 | L76: IMPORTE AÑO 4 | M76: IVA AÑO 4 | N76: % INC. AÑO 5 | O76: IMPORTE AÑO 5 | P76: IVA AÑO 5
B77: Alquileres | C77: 0 | D77: =C77*IVA_compras -> 0 | E77: 0 | F77: =C77*(1+E77) -> 0 | G77: =F77*IVA_compras -> 0 | H77: =E77 -> 0 | I77: =F77*(1+H77) -> 0 | J77: =I77*IVA_compras -> 0 | K77: =H77 -> 0 | L77: =I77*(1+K77) -> 0 | M77: =L77*IVA_compras -> 0 | N77: 0.03 | O77: =L77*(1+N77) -> 0 | P77: =O77*IVA_compras -> 0
B78: Suministros | C78: 0 | D78: =C78*IVA_compras -> 0 | E78: 0 | F78: =C78*(1+E78) -> 0 | G78: =F78*IVA_compras -> 0 | H78: =E78 -> 0 | I78: =F78*(1+H78) -> 0 | J78: =I78*IVA_compras -> 0 | K78: =H78 -> 0 | L78: =I78*(1+K78) -> 0 | M78: =L78*IVA_compras -> 0 | N78: =K78 -> 0 | O78: =L78*(1+N78) -> 0 | P78: =O78*IVA_compras -> 0
B79: Rentings | C79: 0 | D79: =C79*IVA_compras -> 0 | E79: 0 | F79: =C79*(1+E79) -> 0 | G79: =F79*IVA_compras -> 0 | H79: =E79 -> 0 | I79: =F79*(1+H79) -> 0 | J79: =I79*IVA_compras -> 0 | K79: =H79 -> 0 | L79: =I79*(1+K79) -> 0 | M79: =L79*IVA_compras -> 0 | N79: =K79 -> 0 | O79: =L79*(1+N79) -> 0 | P79: =O79*IVA_compras -> 0
B80: Reparaciones | C80: 0 | D80: =C80*IVA_compras -> 0 | E80: 0 | F80: =C80*(1+E80) -> 0 | G80: =F80*IVA_compras -> 0 | H80: =E80 -> 0 | I80: =F80*(1+H80) -> 0 | J80: =I80*IVA_compras -> 0 | K80: =H80 -> 0 | L80: =I80*(1+K80) -> 0 | M80: =L80*IVA_compras -> 0 | N80: =K80 -> 0 | O80: =L80*(1+N80) -> 0 | P80: =O80*IVA_compras -> 0
B81: Servicios profesionales independientes | C81: 0 | D81: =C81*IVA_compras -> 0 | E81: 0 | F81: =C81*(1+E81) -> 0 | G81: =F81*IVA_compras -> 0 | H81: =E81 -> 0 | I81: =F81*(1+H81) -> 0 | J81: =I81*IVA_compras -> 0 | K81: =H81 -> 0 | L81: =I81*(1+K81) -> 0 | M81: =L81*IVA_compras -> 0 | N81: =K81 -> 0 | O81: =L81*(1+N81) -> 0 | P81: =O81*IVA_compras -> 0
B82: Gastos de transportes | C82: 0 | D82: =C82*IVA_compras -> 0 | E82: 0 | F82: =C82*(1+E82) -> 0 | G82: =F82*IVA_compras -> 0 | H82: =E82 -> 0 | I82: =F82*(1+H82) -> 0 | J82: =I82*IVA_compras -> 0 | K82: =H82 -> 0 | L82: =I82*(1+K82) -> 0 | M82: =L82*IVA_compras -> 0 | N82: =K82 -> 0 | O82: =L82*(1+N82) -> 0 | P82: =O82*IVA_compras -> 0
B83: Gastos bancarios y de seguros | C83: 0 | D83: =C83*IVA_compras -> 0 | E83: 0 | F83: =C83*(1+E83) -> 0 | G83: =F83*IVA_compras -> 0 | H83: =E83 -> 0 | I83: =F83*(1+H83) -> 0 | J83: =I83*IVA_compras -> 0 | K83: =H83 -> 0 | L83: =I83*(1+K83) -> 0 | M83: =L83*IVA_compras -> 0 | N83: =K83 -> 0 | O83: =L83*(1+N83) -> 0 | P83: =O83*IVA_compras -> 0
B84: Gastos de márquetin | C84: 0 | D84: =C84*IVA_compras -> 0 | E84: 0 | F84: =C84*(1+E84) -> 0 | G84: =F84*IVA_compras -> 0 | H84: =E84 -> 0 | I84: =F84*(1+H84) -> 0 | J84: =I84*IVA_compras -> 0 | K84: =H84 -> 0 | L84: =I84*(1+K84) -> 0 | M84: =L84*IVA_compras -> 0 | N84: =K84 -> 0 | O84: =L84*(1+N84) -> 0 | P84: =O84*IVA_compras -> 0
B85: Tributos municipales | C85: 0 | D85: =C85*IVA_compras -> 0 | E85: 0 | F85: =C85*(1+E85) -> 0 | G85: =F85*IVA_compras -> 0 | H85: =E85 -> 0 | I85: =F85*(1+H85) -> 0 | J85: =I85*IVA_compras -> 0 | K85: =H85 -> 0 | L85: =I85*(1+K85) -> 0 | M85: =L85*IVA_compras -> 0 | N85: =K85 -> 0 | O85: =L85*(1+N85) -> 0 | P85: =O85*IVA_compras -> 0
B86: TOTAL ANUAL | C86: =SUM(C77:C85) -> 0 | D86: =SUM(D77:D85) -> 0 | F86: =SUM(F77:F85) -> 0 | G86: =SUM(G77:G85) -> 0 | I86: =SUM(I77:I85) -> 0 | J86: =SUM(J77:J85) -> 0 | L86: =SUM(L77:L85) -> 0 | M86: =SUM(M77:M85) -> 0 | O86: =SUM(O77:O85) -> 0 | P86: =SUM(P77:P85) -> 0
B89: GASTO FIJO ANUAL POR NÓMINA | C89: ETAPA | D89: # TRABAJADORES | E89: MES ALTA | F89: MES BAJA | G89: SUELDO BRUTO ANUAL | H89: SEGURO SOCIAL PARTE EMPRESA | I89: SEGURO SOCIAL PARTE TRABAJADOR | J89: TOTAL DE SEGURO SOCIAL | K89: RETENCIÓN RENTA IRPF AL TRABAJADOR (Aprox.) | L89: COSTE EMPRESA ANUAL | M89: SUELDO NETO ANUAL (APROX.) | N89: % INC. ANUAL SALARIO | O89: OBSERVACIONES
A90: 1 | B90: Socios fundadores trabajadores (etapa 1) | C90: 1 | D90: 0 | E90: 1 | F90: 60 | G90: 0 | H90: =IF(G90<seg_social_topeespecial,G90*seg_social_retencion_reg_especial,seg_social_topeespecial*seg_social_retencion_reg_especial) -> 0 | I90: 0 | J90: =H90+I90 -> 0 | K90: =IF(G90<15000,G90*IRPF_BAJO,0)+IF(AND(G90<90000,G90>=15000),G90*IRPF_MEDIO,0)+IF(G90>=90000,G90*IRPF_ALTO,0) -> 0 | L90: =G90+H90 -> 0 | M90: =G90-I90-K90 -> 0 | N90: 0.02 | O90: Porcentaje de incremento de salario bruto el año 2
B91: Personal perfil tipo A (etapa 1) | D91: 0 | E91: 1 | F91: 60 | G91: 0 | H91: =IF(G91<seg_social_topegeneral,G91*seg_social_retencion_reg_general,seg_social_topegeneral*seg_social_retencion_reg_general) -> 0 | I91: =IF(G91<seg_social_topegeneral,G91*seg_social_parte_trabajador,seg_social_topegeneral*seg_social_parte_trabajador) -> 0 | J91: =H91+I91 -> 0 | K91: =IF(G91<15000,G91*IRPF_BAJO,0)+IF(AND(G91<90000,G91>=15000),G91*IRPF_MEDIO,0)+IF(G91>=90000,G91*IRPF_ALTO,0) -> 0 | L91: =G91+H91 -> 0 | M91: =G91-I91-K91 -> 0
B92: Personal perfil tipo B (etapa 1) | D92: 0 | E92: 1 | F92: 60 | G92: 0 | H92: =IF(G92<seg_social_topegeneral,G92*seg_social_retencion_reg_general,seg_social_topegeneral*seg_social_retencion_reg_general) -> 0 | I92: =IF(G92<seg_social_topegeneral,G92*seg_social_parte_trabajador,seg_social_topegeneral*seg_social_parte_trabajador) -> 0 | J92: =H92+I92 -> 0 | K92: =IF(G92<15000,G92*IRPF_BAJO,0)+IF(AND(G92<90000,G92>=15000),G92*IRPF_MEDIO,0)+IF(G92>=90000,G92*IRPF_ALTO,0) -> 0 | L92: =G92+H92 -> 0 | M92: =G92-I92-K92 -> 0
B93: Personal perfil tipo C (etapa 1) | D93: 0 | E93: 1 | F93: 60 | G93: 0 | H93: =IF(G93<seg_social_topegeneral,G93*seg_social_retencion_reg_general,seg_social_topegeneral*seg_social_retencion_reg_general) -> 0 | I93: =IF(G93<seg_social_topegeneral,G93*seg_social_parte_trabajador,seg_social_topegeneral*seg_social_parte_trabajador) -> 0 | J93: =H93+I93 -> 0 | K93: =IF(G93<15000,G93*IRPF_BAJO,0)+IF(AND(G93<90000,G93>=15000),G93*IRPF_MEDIO,0)+IF(G93>=90000,G93*IRPF_ALTO,0) -> 0 | L93: =G93+H93 -> 0 | M93: =G93-I93-K93 -> 0
B94: Personal perfil tipo D (etapa 1) | D94: 0 | E94: 1 | F94: 60 | G94: 0 | H94: =IF(G94<seg_social_topegeneral,G94*seg_social_retencion_reg_general,seg_social_topegeneral*seg_social_retencion_reg_general) -> 0 | I94: =IF(G94<seg_social_topegeneral,G94*seg_social_parte_trabajador,seg_social_topegeneral*seg_social_parte_trabajador) -> 0 | J94: =H94+I94 -> 0 | K94: =IF(G94<15000,G94*IRPF_BAJO,0)+IF(AND(G94<90000,G94>=15000),G94*IRPF_MEDIO,0)+IF(G94>=90000,G94*IRPF_ALTO,0) -> 0 | L94: =G94+H94 -> 0 | M94: =G94-I94-K94 -> 0
A95: 2 | B95: Más socios fundadores trabajadores (etapa 2) | C95: 2 | D95: 0 | E95: 1 | F95: 60 | G95: =G90 -> 0 | H95: =IF(G95<seg_social_topeespecial,G95*seg_social_retencion_reg_especial,seg_social_topeespecial*seg_social_retencion_reg_especial) -> 0 | I95: 0 | J95: =H95+I95 -> 0 | K95: =IF(G95<15000,G95*IRPF_BAJO,0)+IF(AND(G95<90000,G95>=15000),G95*IRPF_MEDIO,0)+IF(G95>=90000,G95*IRPF_ALTO,0) -> 0 | L95: =G95+H95 -> 0 | M95: =G95-I95-K95 -> 0 | N95: 0.02 | O95: Porcentaje de incremento de salario bruto el año 3, respecto al anterior (año 2)
B96: Más personal perfil tipo A (etapa 2) | D96: 0 | E96: 1 | F96: 60 | G96: =G91 -> 0 | H96: =IF(G96<seg_social_topegeneral,G96*seg_social_retencion_reg_general,seg_social_topegeneral*seg_social_retencion_reg_general) -> 0 | I96: =IF(G96<seg_social_topegeneral,G96*seg_social_parte_trabajador,seg_social_topegeneral*seg_social_parte_trabajador) -> 0 | J96: =H96+I96 -> 0 | K96: =IF(G96<15000,G96*IRPF_BAJO,0)+IF(AND(G96<90000,G96>=15000),G96*IRPF_MEDIO,0)+IF(G96>=90000,G96*IRPF_ALTO,0) -> 0 | L96: =G96+H96 -> 0 | M96: =G96-I96-K96 -> 0
B97: Más personal perfil tipo B (etapa 2) | D97: 0 | E97: 1 | F97: 60 | G97: =G92 -> 0 | H97: =IF(G97<seg_social_topegeneral,G97*seg_social_retencion_reg_general,seg_social_topegeneral*seg_social_retencion_reg_general) -> 0 | I97: =IF(G97<seg_social_topegeneral,G97*seg_social_parte_trabajador,seg_social_topegeneral*seg_social_parte_trabajador) -> 0 | J97: =H97+I97 -> 0 | K97: =IF(G97<15000,G97*IRPF_BAJO,0)+IF(AND(G97<90000,G97>=15000),G97*IRPF_MEDIO,0)+IF(G97>=90000,G97*IRPF_ALTO,0) -> 0 | L97: =G97+H97 -> 0 | M97: =G97-I97-K97 -> 0
B98: Más personal perfil tipo C (etapa 2) | D98: 0 | E98: 1 | F98: 60 | G98: =G93 -> 0 | H98: =IF(G98<seg_social_topegeneral,G98*seg_social_retencion_reg_general,seg_social_topegeneral*seg_social_retencion_reg_general) -> 0 | I98: =IF(G98<seg_social_topegeneral,G98*seg_social_parte_trabajador,seg_social_topegeneral*seg_social_parte_trabajador) -> 0 | J98: =H98+I98 -> 0 | K98: =IF(G98<15000,G98*IRPF_BAJO,0)+IF(AND(G98<90000,G98>=15000),G98*IRPF_MEDIO,0)+IF(G98>=90000,G98*IRPF_ALTO,0) -> 0 | L98: =G98+H98 -> 0 | M98: =G98-I98-K98 -> 0
B99: Más personal perfil tipo D (etapa 2) | D99: 0 | E99: 1 | F99: 60 | G99: =G94 -> 0 | H99: =IF(G99<seg_social_topegeneral,G99*seg_social_retencion_reg_general,seg_social_topegeneral*seg_social_retencion_reg_general) -> 0 | I99: =IF(G99<seg_social_topegeneral,G99*seg_social_parte_trabajador,seg_social_topegeneral*seg_social_parte_trabajador) -> 0 | J99: =H99+I99 -> 0 | K99: =IF(G99<15000,G99*IRPF_BAJO,0)+IF(AND(G99<90000,G99>=15000),G99*IRPF_MEDIO,0)+IF(G99>=90000,G99*IRPF_ALTO,0) -> 0 | L99: =G99+H99 -> 0 | M99: =G99-I99-K99 -> 0
A100: 3 | B100: Más socios fundadores trabajadores (etapa 3) | C100: 3 | D100: 0 | E100: 1 | F100: 60 | G100: =G90 -> 0 | H100: =IF(G100<seg_social_topeespecial,G100*seg_social_retencion_reg_especial,seg_social_topeespecial*seg_social_retencion_reg_especial) -> 0 | I100: 0 | J100: =H100+I100 -> 0 | K100: =IF(G100<15000,G100*IRPF_BAJO,0)+IF(AND(G100<90000,G100>=15000),G100*IRPF_MEDIO,0)+IF(G100>=90000,G100*IRPF_ALTO,0) -> 0 | L100: =G100+H100 -> 0 | M100: =G100-I100-K100 -> 0 | N100: 0.03 | O100: Porcentaje de incremento de salario bruto el año 4 y sucesivos.
B101: Más personal perfil tipo A (etapa 3) | D101: 0 | E101: 1 | F101: 60 | G101: =G91 -> 0 | H101: =IF(G101<seg_social_topegeneral,G101*seg_social_retencion_reg_general,seg_social_topegeneral*seg_social_retencion_reg_general) -> 0 | I101: =IF(G101<seg_social_topegeneral,G101*seg_social_parte_trabajador,seg_social_topegeneral*seg_social_parte_trabajador) -> 0 | J101: =H101+I101 -> 0 | K101: =IF(G101<15000,G101*IRPF_BAJO,0)+IF(AND(G101<90000,G101>=15000),G101*IRPF_MEDIO,0)+IF(G101>=90000,G101*IRPF_ALTO,0) -> 0 | L101: =G101+H101 -> 0 | M101: =G101-I101-K101 -> 0
B102: Más personal perfil tipo B (etapa 3) | D102: 0 | E102: 1 | F102: 60 | G102: =G92 -> 0 | H102: =IF(G102<seg_social_topegeneral,G102*seg_social_retencion_reg_general,seg_social_topegeneral*seg_social_retencion_reg_general) -> 0 | I102: =IF(G102<seg_social_topegeneral,G102*seg_social_parte_trabajador,seg_social_topegeneral*seg_social_parte_trabajador) -> 0 | J102: =H102+I102 -> 0 | K102: =IF(G102<15000,G102*IRPF_BAJO,0)+IF(AND(G102<90000,G102>=15000),G102*IRPF_MEDIO,0)+IF(G102>=90000,G102*IRPF_ALTO,0) -> 0 | L102: =G102+H102 -> 0 | M102: =G102-I102-K102 -> 0
B103: Más personal perfil tipo C (etapa 3) | D103: 0 | E103: 1 | F103: 60 | G103: =G93 -> 0 | H103: =IF(G103<seg_social_topegeneral,G103*seg_social_retencion_reg_general,seg_social_topegeneral*seg_social_retencion_reg_general) -> 0 | I103: =IF(G103<seg_social_topegeneral,G103*seg_social_parte_trabajador,seg_social_topegeneral*seg_social_parte_trabajador) -> 0 | J103: =H103+I103 -> 0 | K103: =IF(G103<15000,G103*IRPF_BAJO,0)+IF(AND(G103<90000,G103>=15000),G103*IRPF_MEDIO,0)+IF(G103>=90000,G103*IRPF_ALTO,0) -> 0 | L103: =G103+H103 -> 0 | M103: =G103-I103-K103 -> 0
B104: Más personal perfil tipo D (etapa 3) | D104: 0 | E104: 1 | F104: 60 | G104: =G94 -> 0 | H104: =IF(G104<seg_social_topegeneral,G104*seg_social_retencion_reg_general,seg_social_topegeneral*seg_social_retencion_reg_general) -> 0 | I104: =IF(G104<seg_social_topegeneral,G104*seg_social_parte_trabajador,seg_social_topegeneral*seg_social_parte_trabajador) -> 0 | J104: =H104+I104 -> 0 | K104: =IF(G104<15000,G104*IRPF_BAJO,0)+IF(AND(G104<90000,G104>=15000),G104*IRPF_MEDIO,0)+IF(G104>=90000,G104*IRPF_ALTO,0) -> 0 | L104: =G104+H104 -> 0 | M104: =G104-I104-K104 -> 0
A106: D. HIPÓTESIS COMERCIALES (SALES)
B109: UNIDADES VENDIDAS / CLIENTES SERVIDOS | C109: Año 1 | D109: Año 2 | E109: Año 3 | F109: Año 4 | G109: Año 5 | H109: Observaciones
A110: A | B110: SAM (A). | C110: 0 | H110: Explicar en que consistem el tipo de producto o servicio A
B111: SOM OBJETIVO A (%) | C111: 0 | D111: 0 | E111: 0 | F111: 0 | G111: 0
B112: Objetivo de ventas totales anuales de A (# unidades o clientes servidos) | C112: =INT($C$110*C111) -> 0 | D112: =INT($C$110*D111) -> 0 | E112: =INT($C$110*E111) -> 0 | F112: =INT($C$110*F111) -> 0 | G112: =INT($C$110*G111) -> 0
B113: SAM (B). | C113: 0 | H113: Explicar en que consistem el tipo de producto o servicio B
B114: SOM OBJETIVO B(%) | C114: 0.01 | D114: 0.05 | E114: 0.2 | F114: 0.1 | G114: 1
A115: B | B115: Objetivo de ventas totales anuales de B (# unidades o clientes servidos) | C115: =INT($C$113*C114) -> 0 | D115: =INT($C$113*D114) -> 0 | E115: =INT($C$113*E114) -> 0 | F115: =INT($C$113*F114) -> 0 | G115: =INT($C$113*G114) -> 0
B116: SAM (C). | C116: 0 | H116: Explicar en que consistem el tipo de producto o servicio C
B117: SOM OBJETIVO C (%) | C117: 0.01 | D117: 0.01 | E117: 0.01 | F117: 0.01 | G117: 0.01
A118: C | B118: Objetivo de ventas totales anuales de C (# unidades o clientes servidos) | C118: =INT($C$116*C117) -> 0 | D118: =INT($C$116*D117) -> 0 | E118: =INT($C$116*E117) -> 0 | F118: =INT($C$116*F117) -> 0 | G118: =INT($C$116*G117) -> 0
B121: PRECIOS DE VENTA | C121: Año 1 | D121: Año 2 | E121: Año 3 | F121: Año 4 | G121: Año 5 | K121: CONDICIONES DE PAGO Y COBRO DE LAS OPERACIONES COMERCIALES | P121: # meses
A122: A | B122: Precio unitario tipo A | C122: 1 | D122: =C122*(1+$D125) -> 1.04 | E122: =D122*(1+$E125) -> 1.0608 | F122: =E122*(1+$F125) -> 1.092624 | G122: =F122*(1+$G125) -> 1.1254027 | J122: A | K122: Plazo de cobro tipo A (en meses desde la factura de la venta a cliente a su cobro) | P122: 0
A123: B | B123: Precio unitario tipo B | C123: 0 | D123: =C123*(1+$D125) -> 0 | E123: =D123*(1+$E125) -> 0 | F123: =E123*(1+$F125) -> 0 | G123: =F123*(1+$G125) -> 0 | K123: Plazo de pago tipo A (en meses desde la factura del coste del proveedor a su pago) | P123: 0
A124: C | B124: Precio unitario tipo C | C124: 0 | D124: =C124*(1+$D125) -> 0 | E124: =D124*(1+$E125) -> 0 | F124: =E124*(1+$F125) -> 0 | G124: =F124*(1+$G125) -> 0 | J124: B | K124: Plazo de cobro tipo B (en meses desde la factura de la venta a cliente a su cobro) | P124: 0
B125: Incremento anual de precios | C125: 0 | D125: 0.04 | E125: 0.02 | F125: 0.03 | G125: 0.03 | K125: Plazo de pago tipo B (en meses desde la factura del coste del proveedor a su pago) | P125: 0
J126: C | K126: Plazo de cobro tipo C (en meses desde la factura de la venta a cliente a su cobro) | P126: 0
B127: MÁRGENES COMERCIALES | C127: Año 1 | D127: Año 2 | E127: Año 3 | F127: Año 4 | G127: Año 5 | K127: Plazo de pago tipo C (en meses desde la factura del coste del proveedor a su pago) | P127: 0
A128: A | B128: Coste variable de producción A (%) | C128: 0 | D128: =C128 -> 0 | E128: =D128 -> 0 | F128: =E128 -> 0 | G128: =F128 -> 0
B129: Coste variable de adquisición de A (%) | C129: 0 | D129: =C129 -> 0 | E129: =D129 -> 0 | F129: =E129 -> 0 | G129: =F129 -> 0
...

Sheet C
A1: DETALLE DE CÁLCULOS A PARTIR DE LAS HIPÓTESIS
BN2: listas desplegables
B3: CUADRO DE AMORTIZACIONES MENSUALES DE LAS INVERSIONES EN ACTIVOS | C3: MESES
C4: 0 | D4: 1 | E4: 2 | F4: 3 | G4: 4 | H4: 5 | I4: 6 | J4: 7 | K4: 8 | L4: 9 | M4: 10 | N4: 11 | O4: 12 | P4: 13 | Q4: 14 | R4: 15 | S4: 16 | T4: 17 | U4: 18 | V4: 19 | W4: 20 | X4: 21 | Y4: 22 | Z4: 23 | AA4: 24 | AB4: 25 | AC4: 26 | AD4: 27 | AE4: 28 | AF4: 29 | AG4: 30 | AH4: 31 | AI4: 32 | AJ4: 33 | AK4: 34 | AL4: 35 | AM4: 36 | AN4: 37 | AO4: 38 | AP4: 39 | AQ4: 40 | AR4: 41 | AS4: 42 | AT4: 43 | AU4: 44 | AV4: 45 | AW4: 46 | AX4: 47 | AY4: 48 | AZ4: 49 | BA4: 50 | BB4: 51 | BC4: 52 | BD4: 53 | BE4: 54 | BF4: 55 | BG4: 56 | BH4: 57 | BI4: 58 | BJ4: 59 | BK4: 60 | BO4: 0 | BP4: 0
B5: Amortización inmobilizado intangible inicial | BO5: 1 | BP5: 1
B6: Investigación y desarrollo | C6: 0 | D6: =IF(D$4<=('HIPOTESIS '!$F26*12),'HIPOTESIS '!$C$26/('HIPOTESIS '!$F$26*12),0) -> 0 | E6: =IF(E$4<=('HIPOTESIS '!$F26*12),'HIPOTESIS '!$C$26/('HIPOTESIS '!$F$26*12),0) -> 0 | F6: =IF(F$4<=('HIPOTESIS '!$F26*12),'HIPOTESIS '!$C$26/('HIPOTESIS '!$F$26*12),0) -> 0 | G6: =IF(G$4<=('HIPOTESIS '!$F26*12),'HIPOTESIS '!$C$26/('HIPOTESIS '!$F$26*12),0) -> 0 | H6: =IF(H$4<=('HIPOTESIS '!$F26*12),'HIPOTESIS '!$C$26/('HIPOTESIS '!$F$26*12),0) -> 0 | I6: =IF(I$4<=('HIPOTESIS '!$F26*12),'HIPOTESIS '!$C$26/('HIPOTESIS '!$F$26*12),0) -> 0 | J6: =IF(J$4<=('HIPOTESIS '!$F26*12),'HIPOTESIS '!$C$26/('HIPOTESIS '!$F$26*12),0) -> 0 | K6: =IF(K$4<=('HIPOTESIS '!$F26*12),'HIPOTESIS '!$C$26/('HIPOTESIS '!$F$26*12),0) -> 0 | ... BK6: =IF(BK$4<=('HIPOTESIS '!$F26*12),'HIPOTESIS '!$C$26/('HIPOTESIS '!$F$26*12),0) -> 0 | BO6: 2 | BP6: 2
B7: Patentes y marcas | C7: 0 | D7: =IF(D$4<='HIPOTESIS '!$F27*12,'HIPOTESIS '!$C27/('HIPOTESIS '!$F27*12),0) -> 0 | E7: =IF(E$4<='HIPOTESIS '!$F27*12,'HIPOTESIS '!$C27/('HIPOTESIS '!$F27*12),0) -> 0 | F7: =IF(F$4<='HIPOTESIS '!$F27*12,'HIPOTESIS '!$C27/('HIPOTESIS '!$F27*12),0) -> 0 | G7: =IF(G$4<='HIPOTESIS '!$F27*12,'HIPOTESIS '!$C27/('HIPOTESIS '!$F27*12),0) -> 0 | H7: =IF(H$4<='HIPOTESIS '!$F27*12,'HIPOTESIS '!$C27/('HIPOTESIS '!$F27*12),0) -> 0 | I7: =IF(I$4<='HIPOTESIS '!$F27*12,'HIPOTESIS '!$C27/('HIPOTESIS '!$F27*12),0) -> 0 | J7: =IF(J$4<='HIPOTESIS '!$F27*12,'HIPOTESIS '!$C27/('HIPOTESIS '!$F27*12),0) -> 0 | K7: =IF(K$4<='HIPOTESIS '!$F27*12,'HIPOTESIS '!$C27/('HIPOTESIS '!$F27*12),0) -> 0 | ... BK7: =IF(BK$4<='HIPOTESIS '!$F27*12,'HIPOTESIS '!$C27/('HIPOTESIS '!$F27*12),0) -> 0 | BO7: 3 | BP7: 3
B8: Aplicaciones informáticas | C8: 0 | D8: =IF(D$4<='HIPOTESIS '!$F28*12,'HIPOTESIS '!$C28/('HIPOTESIS '!$F28*12),0) -> 0 | E8: =IF(E$4<='HIPOTESIS '!$F28*12,'HIPOTESIS '!$C28/('HIPOTESIS '!$F28*12),0) -> 0 | F8: =IF(F$4<='HIPOTESIS '!$F28*12,'HIPOTESIS '!$C28/('HIPOTESIS '!$F28*12),0) -> 0 | G8: =IF(G$4<='HIPOTESIS '!$F28*12,'HIPOTESIS '!$C28/('HIPOTESIS '!$F28*12),0) -> 0 | H8: =IF(H$4<='HIPOTESIS '!$F28*12,'HIPOTESIS '!$C28/('HIPOTESIS '!$F28*12),0) -> 0 | I8: =IF(I$4<='HIPOTESIS '!$F28*12,'HIPOTESIS '!$C28/('HIPOTESIS '!$F28*12),0) -> 0 | J8: =IF(J$4<='HIPOTESIS '!$F28*12,'HIPOTESIS '!$C28/('HIPOTESIS '!$F28*12),0) -> 0 | K8: =IF(K$4<='HIPOTESIS '!$F28*12,'HIPOTESIS '!$C28/('HIPOTESIS '!$F28*12),0) -> 0 | ... BK8: =IF(BK$4<='HIPOTESIS '!$F28*12,'HIPOTESIS '!$C28/('HIPOTESIS '!$F28*12),0) -> 0 | BP8: 4
B9: Otros inmobilizados intangibles | C9: 0 | D9: =IF(D$4<='HIPOTESIS '!$F29*12,'HIPOTESIS '!$C29/('HIPOTESIS '!$F29*12),0) -> 0 | E9: =IF(E$4<='HIPOTESIS '!$F29*12,'HIPOTESIS '!$C29/('HIPOTESIS '!$F29*12),0) -> 0 | F9: =IF(F$4<='HIPOTESIS '!$F29*12,'HIPOTESIS '!$C29/('HIPOTESIS '!$F29*12),0) -> 0 | G9: =IF(G$4<='HIPOTESIS '!$F29*12,'HIPOTESIS '!$C29/('HIPOTESIS '!$F29*12),0) -> 0 | H9: =IF(H$4<='HIPOTESIS '!$F29*12,'HIPOTESIS '!$C29/('HIPOTESIS '!$F29*12),0) -> 0 | I9: =IF(I$4<='HIPOTESIS '!$F29*12,'HIPOTESIS '!$C29/('HIPOTESIS '!$F29*12),0) -> 0 | J9: =IF(J$4<='HIPOTESIS '!$F29*12,'HIPOTESIS '!$C29/('HIPOTESIS '!$F29*12),0) -> 0 | K9: =IF(K$4<='HIPOTESIS '!$F29*12,'HIPOTESIS '!$C29/('HIPOTESIS '!$F29*12),0) -> 0 | ... BK9: =IF(BK$4<='HIPOTESIS '!$F29*12,'HIPOTESIS '!$C29/('HIPOTESIS '!$F29*12),0) -> 0 | BN9: 0 | BP9: 5
B10: Amortización inmobilizado material inicial | BN10: 2 | BP10: 6 | BQ10: -0.2
B11: Terrenos y construcciones | C11: 0 | D11: =IF(D$4<='HIPOTESIS '!$F31*12,'HIPOTESIS '!$C31/('HIPOTESIS '!$F31*12),0) -> 0 | E11: =IF(E$4<='HIPOTESIS '!$F31*12,'HIPOTESIS '!$C31/('HIPOTESIS '!$F31*12),0) -> 0 | F11: =IF(F$4<='HIPOTESIS '!$F31*12,'HIPOTESIS '!$C31/('HIPOTESIS '!$F31*12),0) -> 0 | G11: =IF(G$4<='HIPOTESIS '!$F31*12,'HIPOTESIS '!$C31/('HIPOTESIS '!$F31*12),0) -> 0 | H11: =IF(H$4<='HIPOTESIS '!$F31*12,'HIPOTESIS '!$C31/('HIPOTESIS '!$F31*12),0) -> 0 | I11: =IF(I$4<='HIPOTESIS '!$F31*12,'HIPOTESIS '!$C31/('HIPOTESIS '!$F31*12),0) -> 0 | J11: =IF(J$4<='HIPOTESIS '!$F31*12,'HIPOTESIS '!$C31/('HIPOTESIS '!$F31*12),0) -> 0 | K11: =IF(K$4<='HIPOTESIS '!$F31*12,'HIPOTESIS '!$C31/('HIPOTESIS '!$F31*12),0) -> 0 | ... BK11: =IF(BK$4<='HIPOTESIS '!$F31*12,'HIPOTESIS '!$C31/('HIPOTESIS '!$F31*12),0) -> 0 | BN11: 4 | BP11: 7 | BQ11: -0.1
B12: Instalaciones | C12: 0 | D12: =IF(D$4<='HIPOTESIS '!$F32*12,'HIPOTESIS '!$C32/('HIPOTESIS '!$F32*12),0) -> 0 | E12: =IF(E$4<='HIPOTESIS '!$F32*12,'HIPOTESIS '!$C32/('HIPOTESIS '!$F32*12),0) -> 0 | F12: =IF(F$4<='HIPOTESIS '!$F32*12,'HIPOTESIS '!$C32/('HIPOTESIS '!$F32*12),0) -> 0 | G12: =IF(G$4<='HIPOTESIS '!$F32*12,'HIPOTESIS '!$C32/('HIPOTESIS '!$F32*12),0) -> 0 | H12: =IF(H$4<='HIPOTESIS '!$F32*12,'HIPOTESIS '!$C32/('HIPOTESIS '!$F32*12),0) -> 0 | I12: =IF(I$4<='HIPOTESIS '!$F32*12,'HIPOTESIS '!$C32/('HIPOTESIS '!$F32*12),0) -> 0 | J12: =IF(J$4<='HIPOTESIS '!$F32*12,'HIPOTESIS '!$C32/('HIPOTESIS '!$F32*12),0) -> 0 | K12: =IF(K$4<='HIPOTESIS '!$F32*12,'HIPOTESIS '!$C32/('HIPOTESIS '!$F32*12),0) -> 0 | ... BK12: =IF(BK$4<='HIPOTESIS '!$F32*12,'HIPOTESIS '!$C32/('HIPOTESIS '!$F32*12),0) -> 0 | BN12: 6 | BP12: 8 | BQ12: -0.09
B13: Maquinaria | C13: 0 | D13: =IF(D$4<='HIPOTESIS '!$F33*12,'HIPOTESIS '!$C33/('HIPOTESIS '!$F33*12),0) -> 0 | E13: =IF(E$4<='HIPOTESIS '!$F33*12,'HIPOTESIS '!$C33/('HIPOTESIS '!$F33*12),0) -> 0 | F13: =IF(F$4<='HIPOTESIS '!$F33*12,'HIPOTESIS '!$C33/('HIPOTESIS '!$F33*12),0) -> 0 | G13: =IF(G$4<='HIPOTESIS '!$F33*12,'HIPOTESIS '!$C33/('HIPOTESIS '!$F33*12),0) -> 0 | H13: =IF(H$4<='HIPOTESIS '!$F33*12,'HIPOTESIS '!$C33/('HIPOTESIS '!$F33*12),0) -> 0 | I13: =IF(I$4<='HIPOTESIS '!$F33*12,'HIPOTESIS '!$C33/('HIPOTESIS '!$F33*12),0) -> 0 | J13: =IF(J$4<='HIPOTESIS '!$F33*12,'HIPOTESIS '!$C33/('HIPOTESIS '!$F33*12),0) -> 0 | K13: =IF(K$4<='HIPOTESIS '!$F33*12,'HIPOTESIS '!$C33/('HIPOTESIS '!$F33*12),0) -> 0 | ... BK13: =IF(BK$4<='HIPOTESIS '!$F33*12,'HIPOTESIS '!$C33/('HIPOTESIS '!$F33*12),0) -> 0 | BN13: 8 | BP13: 9 | BQ13: -0.08
B14: Equipos para procesos de información( Ordenadores) | C14: 0 | D14: =IF(D$4<='HIPOTESIS '!$F34*12,'HIPOTESIS '!$C34/('HIPOTESIS '!$F34*12),0) -> 0 | E14: =IF(E$4<='HIPOTESIS '!$F34*12,'HIPOTESIS '!$C34/('HIPOTESIS '!$F34*12),0) -> 0 | F14: =IF(F$4<='HIPOTESIS '!$F34*12,'HIPOTESIS '!$C34/('HIPOTESIS '!$F34*12),0) -> 0 | G14: =IF(G$4<='HIPOTESIS '!$F34*12,'HIPOTESIS '!$C34/('HIPOTESIS '!$F34*12),0) -> 0 | H14: =IF(H$4<='HIPOTESIS '!$F34*12,'HIPOTESIS '!$C34/('HIPOTESIS '!$F34*12),0) -> 0 | I14: =IF(I$4<='HIPOTESIS '!$F34*12,'HIPOTESIS '!$C34/('HIPOTESIS '!$F34*12),0) -> 0 | J14: =IF(J$4<='HIPOTESIS '!$F34*12,'HIPOTESIS '!$C34/('HIPOTESIS '!$F34*12),0) -> 0 | K14: =IF(K$4<='HIPOTESIS '!$F34*12,'HIPOTESIS '!$C34/('HIPOTESIS '!$F34*12),0) -> 0 | ... BK14: =IF(BK$4<='HIPOTESIS '!$F34*12,'HIPOTESIS '!$C34/('HIPOTESIS '!$F34*12),0) -> 0 | BN14: 10 | BP14: 10 | BQ14: -0.07
B15: Mobiliario | C15: 0 | D15: =IF(D$4<='HIPOTESIS '!$F35*12,'HIPOTESIS '!$C35/('HIPOTESIS '!$F35*12),0) -> 0 | E15: =IF(E$4<='HIPOTESIS '!$F35*12,'HIPOTESIS '!$C35/('HIPOTESIS '!$F35*12),0) -> 0 | F15: =IF(F$4<='HIPOTESIS '!$F35*12,'HIPOTESIS '!$C35/('HIPOTESIS '!$F35*12),0) -> 0 | G15: =IF(G$4<='HIPOTESIS '!$F35*12,'HIPOTESIS '!$C35/('HIPOTESIS '!$F35*12),0) -> 0 | H15: =IF(H$4<='HIPOTESIS '!$F35*12,'HIPOTESIS '!$C35/('HIPOTESIS '!$F35*12),0) -> 0 | I15: =IF(I$4<='HIPOTESIS '!$F35*12,'HIPOTESIS '!$C35/('HIPOTESIS '!$F35*12),0) -> 0 | J15: =IF(J$4<='HIPOTESIS '!$F35*12,'HIPOTESIS '!$C35/('HIPOTESIS '!$F35*12),0) -> 0 | K15: =IF(K$4<='HIPOTESIS '!$F35*12,'HIPOTESIS '!$C35/('HIPOTESIS '!$F35*12),0) -> 0 | ... BK15: =IF(BK$4<='HIPOTESIS '!$F35*12,'HIPOTESIS '!$C35/('HIPOTESIS '!$F35*12),0) -> 0 | BN15: 12 | BP15: 11 | BQ15: -0.06
B16: Vehículos | C16: 0 | D16: =IF(D$4<='HIPOTESIS '!$F36*12,'HIPOTESIS '!$C36/('HIPOTESIS '!$F36*12),0) -> 0 | E16: =IF(E$4<='HIPOTESIS '!$F36*12,'HIPOTESIS '!$C36/('HIPOTESIS '!$F36*12),0) -> 0 | F16: =IF(F$4<='HIPOTESIS '!$F36*12,'HIPOTESIS '!$C36/('HIPOTESIS '!$F36*12),0) -> 0 | G16: =IF(G$4<='HIPOTESIS '!$F36*12,'HIPOTESIS '!$C36/('HIPOTESIS '!$F36*12),0) -> 0 | H16: =IF(H$4<='HIPOTESIS '!$F36*12,'HIPOTESIS '!$C36/('HIPOTESIS '!$F36*12),0) -> 0 | I16: =IF(I$4<='HIPOTESIS '!$F36*12,'HIPOTESIS '!$C36/('HIPOTESIS '!$F36*12),0) -> 0 | J16: =IF(J$4<='HIPOTESIS '!$F36*12,'HIPOTESIS '!$C36/('HIPOTESIS '!$F36*12),0) -> 0 | K16: =IF(K$4<='HIPOTESIS '!$F36*12,'HIPOTESIS '!$C36/('HIPOTESIS '!$F36*12),0) -> 0 | ... BK16: =IF(BK$4<='HIPOTESIS '!$F36*12,'HIPOTESIS '!$C36/('HIPOTESIS '!$F36*12),0) -> 0 | BN16: 14 | BP16: 12 | BQ16: -0.05
B17: Otros inmobilizados materiales | C17: 0 | D17: =IF(D$4<='HIPOTESIS '!$F37*12,'HIPOTESIS '!$C37/('HIPOTESIS '!$F37*12),0) -> 0 | E17: =IF(E$4<='HIPOTESIS '!$F37*12,'HIPOTESIS '!$C37/('HIPOTESIS '!$F37*12),0) -> 0 | F17: =IF(F$4<='HIPOTESIS '!$F37*12,'HIPOTESIS '!$C37/('HIPOTESIS '!$F37*12),0) -> 0 | G17: =IF(G$4<='HIPOTESIS '!$F37*12,'HIPOTESIS '!$C37/('HIPOTESIS '!$F37*12),0) -> 0 | H17: =IF(H$4<='HIPOTESIS '!$F37*12,'HIPOTESIS '!$C37/('HIPOTESIS '!$F37*12),0) -> 0 | I17: =IF(I$4<='HIPOTESIS '!$F37*12,'HIPOTESIS '!$C37/('HIPOTESIS '!$F37*12),0) -> 0 | J17: =IF(J$4<='HIPOTESIS '!$F37*12,'HIPOTESIS '!$C37/('HIPOTESIS '!$F37*12),0) -> 0 | K17: =IF(K$4<='HIPOTESIS '!$F37*12,'HIPOTESIS '!$C37/('HIPOTESIS '!$F37*12),0) -> 0 | ... BK17: =IF(BK$4<='HIPOTESIS '!$F37*12,'HIPOTESIS '!$C37/('HIPOTESIS '!$F37*12),0) -> 0 | BN17: 16 | BQ17: -0.04
B18: Amortización nuevas inversiones y activaciones | BN18: 18 | BP18: -0.2 | BQ18: -0.03
B19: Inversión 1 | C19: =IF(AND(C4>inicio_inv1,C4<=(final_inv1)),imp_inv1/(años_amortiz_inv1*12),0) -> 0 | D19: =IF(AND(D4>inicio_inv1,D4<=(final_inv1)),imp_inv1/(años_amortiz_inv1*12),0) -> 0 | E19: =IF(AND(E4>inicio_inv1,E4<=(final_inv1)),imp_inv1/(años_amortiz_inv1*12),0) -> 0 | F19: =IF(AND(F4>inicio_inv1,F4<=(final_inv1)),imp_inv1/(años_amortiz_inv1*12),0) -> 0 | G19: =IF(AND(G4>inicio_inv1,G4<=(final_inv1)),imp_inv1/(años_amortiz_inv1*12),0) -> 0 | H19: =IF(AND(H4>inicio_inv1,H4<=(final_inv1)),imp_inv1/(años_amortiz_inv1*12),0) -> 0 | I19: =IF(AND(I4>inicio_inv1,I4<=(final_inv1)),imp_inv1/(años_amortiz_inv1*12),0) -> 0 | J19: =IF(AND(J4>inicio_inv1,J4<=(final_inv1)),imp_inv1/(años_amortiz_inv1*12),0) -> 0 | ... BK19: =IF(AND(BK4>inicio_inv1,BK4<=(final_inv1)),imp_inv1/(años_amortiz_inv1*12),0) -> 0 | BN19: 20 | BO19: -0.3 | BP19: -0.1 | BQ19: -0.02
B20: Inversión 2 | C20: =IF(AND(C4>inicio_inv2,C4<=(final_inv2)),imp_inv2/(años_amortiz_inv2*12),0) -> 0 | D20: =IF(AND(D4>inicio_inv2,D4<=(final_inv2)),imp_inv2/(años_amortiz_inv2*12),0) -> 0 | E20: =IF(AND(E4>inicio_inv2,E4<=(final_inv2)),imp_inv2/(años_amortiz_inv2*12),0) -> 0 | F20: =IF(AND(F4>inicio_inv2,F4<=(final_inv2)),imp_inv2/(años_amortiz_inv2*12),0) -> 0 | G20: =IF(AND(G4>inicio_inv2,G4<=(final_inv2)),imp_inv2/(años_amortiz_inv2*12),0) -> 0 | H20: =IF(AND(H4>inicio_inv2,H4<=(final_inv2)),imp_inv2/(años_amortiz_inv2*12),0) -> 0 | I20: =IF(AND(I4>inicio_inv2,I4<=(final_inv2)),imp_inv2/(años_amortiz_inv2*12),0) -> 0 | J20: =IF(AND(J4>inicio_inv2,J4<=(final_inv2)),imp_inv2/(años_amortiz_inv2*12),0) -> 0 | ... BK20: =IF(AND(BK4>inicio_inv2,BK4<=(final_inv2)),imp_inv2/(años_amortiz_inv2*12),0) -> 0 | BO20: -0.2 | BP20: -0.08 | BQ20: -0.01
B21: Proyecto activación 1 | C21: =IF(AND(C4>inicio_amortiz_activ1,C4<=(final_amortiz_activ1)),imp_activacion1/(años_amortiz_activ1*12),0) -> 0 | D21: =IF(AND(D4>inicio_amortiz_activ1,D4<=(final_amortiz_activ1)),imp_activacion1/(años_amortiz_activ1*12),0) -> 0 | E21: =IF(AND(E4>inicio_amortiz_activ1,E4<=(final_amortiz_activ1)),imp_activacion1/(años_amortiz_activ1*12),0) -> 0 | F21: =IF(AND(F4>inicio_amortiz_activ1,F4<=(final_amortiz_activ1)),imp_activacion1/(años_amortiz_activ1*12),0) -> 0 | G21: =IF(AND(G4>inicio_amortiz_activ1,G4<=(final_amortiz_activ1)),imp_activacion1/(años_amortiz_activ1*12),0) -> 0 | H21: =IF(AND(H4>inicio_amortiz_activ1,H4<=(final_amortiz_activ1)),imp_activacion1/(años_amortiz_activ1*12),0) -> 0 | I21: =IF(AND(I4>inicio_amortiz_activ1,I4<=(final_amortiz_activ1)),imp_activacion1/(años_amortiz_activ1*12),0) -> 0 | J21: =IF(AND(J4>inicio_amortiz_activ1,J4<=(final_amortiz_activ1)),imp_activacion1/(años_amortiz_activ1*12),0) -> 0 | ... BK21: =IF(AND(BK4>inicio_amortiz_activ1,BK4<=(final_amortiz_activ1)),imp_activacion1/(años_amortiz_activ1*12),0) -> 0 | BO21: -0.15 | BP21: -0.06 | BQ21: 0
B22: Proyecto activación2 | C22: =IF(AND(C4>inicio_amortiz_activ2,C4<=(final_amortiz_activ2)),imp_activacion2/(años_amortiz_activ2*12),0) -> 0 | D22: =IF(AND(D4>inicio_amortiz_activ2,D4<=(final_amortiz_activ2)),imp_activacion2/(años_amortiz_activ2*12),0) -> 0 | E22: =IF(AND(E4>inicio_amortiz_activ2,E4<=(final_amortiz_activ2)),imp_activacion2/(años_amortiz_activ2*12),0) -> 0 | F22: =IF(AND(F4>inicio_amortiz_activ2,F4<=(final_amortiz_activ2)),imp_activacion2/(años_amortiz_activ2*12),0) -> 0 | G22: =IF(AND(G4>inicio_amortiz_activ2,G4<=(final_amortiz_activ2)),imp_activacion2/(años_amortiz_activ2*12),0) -> 0 | H22: =IF(AND(H4>inicio_amortiz_activ2,H4<=(final_amortiz_activ2)),imp_activacion2/(años_amortiz_activ2*12),0) -> 0 | I22: =IF(AND(I4>inicio_amortiz_activ2,I4<=(final_amortiz_activ2)),imp_activacion2/(años_amortiz_activ2*12),0) -> 0 | J22: =IF(AND(J4>inicio_amortiz_activ2,J4<=(final_amortiz_activ2)),imp_activacion2/(años_amortiz_activ2*12),0) -> 0 | ... BK22: =IF(AND(BK4>inicio_amortiz_activ2,BK4<=(final_amortiz_activ2)),imp_activacion2/(años_amortiz_activ2*12),0) -> 0 | BO22: -0.1 | BP22: -0.04 | BQ22: 0.01
B23: TOTAL amortizaciones | C23: =SUM(C6:C22) -> 0 | D23: =SUM(D6:D22) -> 0 | E23: =SUM(E6:E22) -> 0 | F23: =SUM(F6:F22) -> 0 | G23: =SUM(G6:G22) -> 0 | H23: =SUM(H6:H22) -> 0 | I23: =SUM(I6:I22) -> 0 | J23: =SUM(J6:J22) -> 0 | ... BK23: =SUM(BK6:BK22) -> 0 | BO23: -0.05 | BP23: -0.02 | BQ23: 0.02
B24: Amortización de las subvenciones de capital (por inversiones y activaciones) | BO24: 0 | BP24: 0 | BQ24: 0.03
B25: Subvención inversión 1 | C25: =IF(AND(C4>inicio_subv_inv1,C4<=(final_subv_inv1)),imp_subv_inv1/(años_amortiz_inv1*12),0) -> 0 | D25: =IF(AND(D4>inicio_subv_inv1,D4<=(final_subv_inv1)),imp_subv_inv1/(años_amortiz_inv1*12),0) -> 0 | E25: =IF(AND(E4>inicio_subv_inv1,E4<=(final_subv_inv1)),imp_subv_inv1/(años_amortiz_inv1*12),0) -> 0 | F25: =IF(AND(F4>inicio_subv_inv1,F4<=(final_subv_inv1)),imp_subv_inv1/(años_amortiz_inv1*12),0) -> 0 | G25: =IF(AND(G4>inicio_subv_inv1,G4<=(final_subv_inv1)),imp_subv_inv1/(años_amortiz_inv1*12),0) -> 0 | H25: =IF(AND(H4>inicio_subv_inv1,H4<=(final_subv_inv1)),imp_subv_inv1/(años_amortiz_inv1*12),0) -> 0 | I25: =IF(AND(I4>inicio_subv_inv1,I4<=(final_subv_inv1)),imp_subv_inv1/(años_amortiz_inv1*12),0) -> 0 | J25: =IF(AND(J4>inicio_subv_inv1,J4<=(final_subv_inv1)),imp_subv_inv1/(años_amortiz_inv1*12),0) -> 0 | ... BK25: =IF(AND(BK4>inicio_subv_inv1,BK4<=(final_subv_inv1)),imp_subv_inv1/(años_amortiz_inv1*12),0) -> 0 | BO25: 0.05 | BP25: 0.02 | BQ25: 0.04
B26: Subvención inversión 2 | C26: =IF(AND(C4>inicio_subv_inv2,C4<=(final_subv_inv2)),imp_subv_inv2/(años_amortiz_inv2*12),0) -> 0 | D26: =IF(AND(D4>inicio_subv_inv2,D4<=(final_subv_inv2)),imp_subv_inv2/(años_amortiz_inv2*12),0) -> 0 | E26: =IF(AND(E4>inicio_subv_inv2,E4<=(final_subv_inv2)),imp_subv_inv2/(años_amortiz_inv2*12),0) -> 0 | F26: =IF(AND(F4>inicio_subv_inv2,F4<=(final_subv_inv2)),imp_subv_inv2/(años_amortiz_inv2*12),0) -> 0 | G26: =IF(AND(G4>inicio_subv_inv2,G4<=(final_subv_inv2)),imp_subv_inv2/(años_amortiz_inv2*12),0) -> 0 | H26: =IF(AND(H4>inicio_subv_inv2,H4<=(final_subv_inv2)),imp_subv_inv2/(años_amortiz_inv2*12),0) -> 0 | I26: =IF(AND(I4>inicio_subv_inv2,I4<=(final_subv_inv2)),imp_subv_inv2/(años_amortiz_inv2*12),0) -> 0 | J26: =IF(AND(J4>inicio_subv_inv2,J4<=(final_subv_inv2)),imp_subv_inv2/(años_amortiz_inv2*12),0) -> 0 | ... BK26: =IF(AND(BK4>inicio_subv_inv2,BK4<=(final_subv_inv2)),imp_subv_inv2/(años_amortiz_inv2*12),0) -> 0 | BO26: 0.1 | BP26: 0.04 | BQ26: 0.05
B27: Subvención activación 1 | C27: =IF(AND(C4>inicio_amortiz_activ1,C4<=(final_amortiz_activ1)),imp_subv_activ1/(años_amortiz_activ1*12),0) -> 0 | D27: =IF(AND(D4>inicio_amortiz_activ1,D4<=(final_amortiz_activ1)),imp_subv_activ1/(años_amortiz_activ1*12),0) -> 0 | E27: =IF(AND(E4>inicio_amortiz_activ1,E4<=(final_amortiz_activ1)),imp_subv_activ1/(años_amortiz_activ1*12),0) -> 0 | F27: =IF(AND(F4>inicio_amortiz_activ1,F4<=(final_amortiz_activ1)),imp_subv_activ1/(años_amortiz_activ1*12),0) -> 0 | G27: =IF(AND(G4>inicio_amortiz_activ1,G4<=(final_amortiz_activ1)),imp_subv_activ1/(años_amortiz_activ1*12),0) -> 0 | H27: =IF(AND(H4>inicio_amortiz_activ1,H4<=(final_amortiz_activ1)),imp_subv_activ1/(años_amortiz_activ1*12),0) -> 0 | I27: =IF(AND(I4>inicio_amortiz_activ1,I4<=(final_amortiz_activ1)),imp_subv_activ1/(años_amortiz_activ1*12),0) -> 0 | J27: =IF(AND(J4>inicio_amortiz_activ1,J4<=(final_amortiz_activ1)),imp_subv_activ1/(años_amortiz_activ1*12),0) -> 0 | ... BK27: =IF(AND(BK4>inicio_amortiz_activ1,BK4<=(final_amortiz_activ1)),imp_subv_activ1/(años_amortiz_activ1*12),0) -> 0 | BO27: 0.15 | BP27: 0.06 | BQ27: 0.06
B28: Subvención activación 2 | C28: =IF(AND(C4>inicio_amortiz_activ2,C4<=(final_amortiz_activ2)),imp_subv_activ2/(años_amortiz_activ2*12),0) -> 0 | D28: =IF(AND(D4>inicio_amortiz_activ2,D4<=(final_amortiz_activ2)),imp_subv_activ2/(años_amortiz_activ2*12),0) -> 0 | E28: =IF(AND(E4>inicio_amortiz_activ2,E4<=(final_amortiz_activ2)),imp_subv_activ2/(años_amortiz_activ2*12),0) -> 0 | F28: =IF(AND(F4>inicio_amortiz_activ2,F4<=(final_amortiz_activ2)),imp_subv_activ2/(años_amortiz_activ2*12),0) -> 0 | G28: =IF(AND(G4>inicio_amortiz_activ2,G4<=(final_amortiz_activ2)),imp_subv_activ2/(años_amortiz_activ2*12),0) -> 0 | H28: =IF(AND(H4>inicio_amortiz_activ2,H4<=(final_amortiz_activ2)),imp_subv_activ2/(años_amortiz_activ2*12),0) -> 0 | I28: =IF(AND(I4>inicio_amortiz_activ2,I4<=(final_amortiz_activ2)),imp_subv_activ2/(años_amortiz_activ2*12),0) -> 0 | J28: =IF(AND(J4>inicio_amortiz_activ2,J4<=(final_amortiz_activ2)),imp_subv_activ2/(años_amortiz_activ2*12),0) -> 0 | ... BK28: =IF(AND(BK4>inicio_amortiz_activ2,BK4<=(final_amortiz_activ2)),imp_subv_activ2/(años_amortiz_activ2*12),0) -> 0 | BO28: 0.2 | BP28: 0.08 | BQ28: 0.07
B29: TOTAL imputación de subvenciones de capital | C29: =SUM(C25:C28) -> 0 | D29: =SUM(D25:D28) -> 0 | E29: =SUM(E25:E28) -> 0 | F29: =SUM(F25:F28) -> 0 | G29: =SUM(G25:G28) -> 0 | H29: =SUM(H25:H28) -> 0 | I29: =SUM(I25:I28) -> 0 | J29: =SUM(J25:J28) -> 0 | ... BK29: =SUM(BK25:BK28) -> 0 | BO29: 0.3 | BP29: 0.1 | BQ29: 0.08
BP30: 0.2 | BQ30: 0.09
B31: CUADRO DE ACTUALIZACIÓN DEL VALOR CONTABLE DE LOS ACTIVOS Y LAS SUBVENCIONES DE CAPITAL | BQ31: 0.1
C32: 0 | D32: 1 | E32: 2 | F32: 3 | G32: 4 | H32: 5 | I32: 6 | J32: 7 | K32: 8 | L32: 9 | M32: 10 | N32: 11 | O32: 12 | P32: 13 | Q32: 14 | R32: 15 | S32: 16 | T32: 17 | U32: 18 | V32: 19 | W32: 20 | X32: 21 | Y32: 22 | Z32: 23 | AA32: 24 | AB32: 25 | AC32: 26 | AD32: 27 | AE32: 28 | AF32: 29 | AG32: 30 | AH32: 31 | AI32: 32 | AJ32: 33 | AK32: 34 | AL32: 35 | AM32: 36 | AN32: 37 | AO32: 38 | AP32: 39 | AQ32: 40 | AR32: 41 | AS32: 42 | AT32: 43 | AU32: 44 | AV32: 45 | AW32: 46 | AX32: 47 | AY32: 48 | AZ32: 49 | BA32: 50 | BB32: 51 | BC32: 52 | BD32: 53 | BE32: 54 | BF32: 55 | BG32: 56 | BH32: 57 | BI32: 58 | BJ32: 59 | BK32: 60 | BQ32: 0.2
B33: Valor del inmobilizado intangible inicial
B34: Investigación y desarrollo | C34: ='HIPOTESIS '!C26 -> 0 | D34: =C34-D6 -> 0 | E34: =D34-E6 -> 0 | F34: =E34-F6 -> 0 | G34: =F34-G6 -> 0 | H34: =G34-H6 -> 0 | I34: =H34-I6 -> 0 | J34: =I34-J6 -> 0 | K34: =J34-K6 -> 0 | ... BK34: =BJ34-BK6 -> 0
B35: Patentes y marcas | C35: ='HIPOTESIS '!C27 -> 0 | D35: =C35-D7 -> 0 | E35: =D35-E7 -> 0 | F35: =E35-F7 -> 0 | G35: =F35-G7 -> 0 | H35: =G35-H7 -> 0 | I35: =H35-I7 -> 0 | J35: =I35-J7 -> 0 | K35: =J35-K7 -> 0 | ... BK35: =BJ35-BK7 -> 0
B36: Aplicaciones informáticas | C36: ='HIPOTESIS '!C28 -> 0 | D36: =C36-D8 -> 0 | E36: =D36-E8 -> 0 | F36: =E36-F8 -> 0 | G36: =F36-G8 -> 0 | H36: =G36-H8 -> 0 | I36: =H36-I8 -> 0 | J36: =I36-J8 -> 0 | K36: =J36-K8 -> 0 | ... BK36: =BJ36-BK8 -> 0
B37: Otros inmobilizados intangibles | C37: ='HIPOTESIS '!C29 -> 0 | D37: =C37-D9 -> 0 | E37: =D37-E9 -> 0 | F37: =E37-F9 -> 0 | G37: =F37-G9 -> 0 | H37: =G37-H9 -> 0 | I37: =H37-I9 -> 0 | J37: =I37-J9 -> 0 | K37: =J37-K9 -> 0 | ... BK37: =BJ37-BK9 -> 0
B38: Valor del inmobilizado material inicial
B39: Terrenos y construcciones | C39: ='HIPOTESIS '!C31 -> 0 | D39: =C39-D11 -> 0 | E39: =D39-E11 -> 0 | F39: =E39-F11 -> 0 | G39: =F39-G11 -> 0 | H39: =G39-H11 -> 0 | I39: =H39-I11 -> 0 | J39: =I39-J11 -> 0 | K39: =J39-K11 -> 0 | ... BK39: =BJ39-BK11 -> 0
B40: Instalaciones | C40: ='HIPOTESIS '!C32 -> 0 | D40: =C40-D12 -> 0 | E40: =D40-E12 -> 0 | F40: =E40-F12 -> 0 | G40: =F40-G12 -> 0 | H40: =G40-H12 -> 0 | I40: =H40-I12 -> 0 | J40: =I40-J12 -> 0 | K40: =J40-K12 -> 0 | ... BK40: =BJ40-BK12 -> 0
B41: Maquinaria | C41: ='HIPOTESIS '!C33 -> 0 | D41: =C41-D13 -> 0 | E41: =D41-E13 -> 0 | F41: =E41-F13 -> 0 | G41: =F41-G13 -> 0 | H41: =G41-H13 -> 0 | I41: =H41-I13 -> 0 | J41: =I41-J13 -> 0 | K41: =J41-K13 -> 0 | ... BK41: =BJ41-BK13 -> 0
B42: Equipos para procesos de información( Ordenadores) | C42: ='HIPOTESIS '!C34 -> 0 | D42: =C42-D14 -> 0 | E42: =D42-E14 -> 0 | F42: =E42-F14 -> 0 | G42: =F42-G14 -> 0 | H42: =G42-H14 -> 0 | I42: =H42-I14 -> 0 | J42: =I42-J14 -> 0 | K42: =J42-K14 -> 0 | ... BK42: =BJ42-BK14 -> 0
B43: Mobiliario | C43: ='HIPOTESIS '!C35 -> 0 | D43: =C43-D15 -> 0 | E43: =D43-E15 -> 0 | F43: =E43-F15 -> 0 | G43: =F43-G15 -> 0 | H43: =G43-H15 -> 0 | I43: =H43-I15 -> 0 | J43: =I43-J15 -> 0 | K43: =J43-K15 -> 0 | ... BK43: =BJ43-BK15 -> 0
B44: Vehículos | C44: ='HIPOTESIS '!C36 -> 0 | D44: =C44-D16 -> 0 | E44: =D44-E16 -> 0 | F44: =E44-F16 -> 0 | G44: =F44-G16 -> 0 | H44: =G44-H16 -> 0 | I44: =H44-I16 -> 0 | J44: =I44-J16 -> 0 | K44: =J44-K16 -> 0 | ... BK44: =BJ44-BK16 -> 0
B45: Otros inmobilizados materiales | C45: ='HIPOTESIS '!C37 -> 0 | D45: =C45-D17 -> 0 | E45: =D45-E17 -> 0 | F45: =E45-F17 -> 0 | G45: =F45-G17 -> 0 | H45: =G45-H17 -> 0 | I45: =H45-I17 -> 0 | J45: =I45-J17 -> 0 | K45: =J45-K17 -> 0 | ... BK45: =BJ45-BK17 -> 0
B46: Valor del activo de nuevas inversiones y activaciones
B47: Inversión 1 | C47: =IF(AND(C32>=inicio_inv1,C32<final_inv1),imp_inv1-imp_inv1/(años_amortiz_inv1*12)*(C32-inicio_inv1),0) -> 0 | D47: =IF(AND(D32>=inicio_inv1,D32<final_inv1),imp_inv1-imp_inv1/(años_amortiz_inv1*12)*(D32-inicio_inv1),0) -> 0 | E47: =IF(AND(E32>=inicio_inv1,E32<final_inv1),imp_inv1-imp_inv1/(años_amortiz_inv1*12)*(E32-inicio_inv1),0) -> 0 | F47: =IF(AND(F32>=inicio_inv1,F32<final_inv1),imp_inv1-imp_inv1/(años_amortiz_inv1*12)*(F32-inicio_inv1),0) -> 0 | G47: =IF(AND(G32>=inicio_inv1,G32<final_inv1),imp_inv1-imp_inv1/(años_amortiz_inv1*12)*(G32-inicio_inv1),0) -> 0 | H47: =IF(AND(H32>=inicio_inv1,H32<final_inv1),imp_inv1-imp_inv1/(años_amortiz_inv1*12)*(H32-inicio_inv1),0) -> 0 | I47: =IF(AND(I32>=inicio_inv1,I32<final_inv1),imp_inv1-imp_inv1/(años_amortiz_inv1*12)*(I32-inicio_inv1),0) -> 0 | J47: =IF(AND(J32>=inicio_inv1,J32<final_inv1),imp_inv1-imp_inv1/(años_amortiz_inv1*12)*(J32-inicio_inv1),0) -> 0 | ... BK47: =IF(AND(BK32>=inicio_inv1,BK32<final_inv1),imp_inv1-imp_inv1/(años_amortiz_inv1*12)*(BK32-inicio_inv1),0) -> 0
B48: Inversión 2 | C48: =IF(AND(C32>=inicio_inv2,C32<final_inv2),imp_inv2-imp_inv2/(años_amortiz_inv2*12)*(C32-inicio_inv2),0) -> 0 | D48: =IF(AND(D32>=inicio_inv2,D32<final_inv2),imp_inv2-imp_inv2/(años_amortiz_inv2*12)*(D32-inicio_inv2),0) -> 0 | E48: =IF(AND(E32>=inicio_inv2,E32<final_inv2),imp_inv2-imp_inv2/(años_amortiz_inv2*12)*(E32-inicio_inv2),0) -> 0 | F48: =IF(AND(F32>=inicio_inv2,F32<final_inv2),imp_inv2-imp_inv2/(años_amortiz_inv2*12)*(F32-inicio_inv2),0) -> 0 | G48: =IF(AND(G32>=inicio_inv2,G32<final_inv2),imp_inv2-imp_inv2/(años_amortiz_inv2*12)*(G32-inicio_inv2),0) -> 0 | H48: =IF(AND(H32>=inicio_inv2,H32<final_inv2),imp_inv2-imp_inv2/(años_amortiz_inv2*12)*(H32-inicio_inv2),0) -> 0 | I48: =IF(AND(I32>=inicio_inv2,I32<final_inv2),imp_inv2-imp_inv2/(años_amortiz_inv2*12)*(I32-inicio_inv2),0) -> 0 | J48: =IF(AND(J32>=inicio_inv2,J32<final_inv2),imp_inv2-imp_inv2/(años_amortiz_inv2*12)*(J32-inicio_inv2),0) -> 0 | ... BK48: =IF(AND(BK32>=inicio_inv2,BK32<final_inv2),imp_inv2-imp_inv2/(años_amortiz_inv2*12)*(BK32-inicio_inv2),0) -> 0
B49: Proyecto activación 1 | C49: =IF(AND(C32>=inicio_amortiz_activ1,C32<final_amortiz_activ1),imp_activacion1-imp_activacion1/(años_amortiz_activ1*12)*(C32-inicio_amortiz_activ1),0)+IF(AND(C32>=inicio_trabaj_activacion1,C32<=final_trabaj_activacion1),imp_mensual_trabajo_activ1*(C32+1-inicio_trabaj_activacion1),0) -> 0 | D49: =IF(AND(D32>=inicio_amortiz_activ1,D32<final_amortiz_activ1),imp_activacion1-imp_activacion1/(años_amortiz_activ1*12)*(D32-inicio_amortiz_activ1),0)+IF(AND(D32>=inicio_trabaj_activacion1,D32<=final_trabaj_activacion1),imp_mensual_trabajo_activ1*(D32+1-inicio_trabaj_activacion1),0) -> 0 | E49: =IF(AND(E32>=inicio_amortiz_activ1,E32<final_amortiz_activ1),imp_activacion1-imp_activacion1/(años_amortiz_activ1*12)*(E32-inicio_amortiz_activ1),0)+IF(AND(E32>=inicio_trabaj_activacion1,E32<=final_trabaj_activacion1),imp_mensual_trabajo_activ1*(E32+1-inicio_trabaj_activacion1),0) -> 0 | F49: =IF(AND(F32>=inicio_amortiz_activ1,F32<final_amortiz_activ1),imp_activacion1-imp_activacion1/(años_amortiz_activ1*12)*(F32-inicio_amortiz_activ1),0)+IF(AND(F32>=inicio_trabaj_activacion1,F32<=final_trabaj_activacion1),imp_mensual_trabajo_activ1*(F32+1-inicio_trabaj_activacion1),0) -> 0 | G49: =IF(AND(G32>=inicio_amortiz_activ1,G32<final_amortiz_activ1),imp_activacion1-imp_activacion1/(años_amortiz_activ1*12)*(G32-inicio_amortiz_activ1),0)+IF(AND(G32>=inicio_trabaj_activacion1,G32<=final_trabaj_activacion1),imp_mensual_trabajo_activ1*(G32+1-inicio_trabaj_activacion1),0) -> 0 | H49: =IF(AND(H32>=inicio_amortiz_activ1,H32<final_amortiz_activ1),imp_activacion1-imp_activacion1/(años_amortiz_activ1*12)*(H32-inicio_amortiz_activ1),0)+IF(AND(H32>=inicio_trabaj_activacion1,H32<=final_trabaj_activacion1),imp_mensual_trabajo_activ1*(H32+1-inicio_trabaj_activacion1),0) -> 0 | I49: =IF(AND(I32>=inicio_amortiz_activ1,I32<final_amortiz_activ1),imp_activacion1-imp_activacion1/(años_amortiz_activ1*12)*(I32-inicio_amortiz_activ1),0)+IF(AND(I32>=inicio_trabaj_activacion1,I32<=final_trabaj_activacion1),imp_mensual_trabajo_activ1*(I32+1-inicio_trabaj_activacion1),0) -> 0 | J49: =IF(AND(J32>=inicio_amortiz_activ1,J32<final_amortiz_activ1),imp_activacion1-imp_activacion1/(años_amortiz_activ1*12)*(J32-inicio_amortiz_activ1),0)+IF(AND(J32>=inicio_trabaj_activacion1,J32<=final_trabaj_activacion1),imp_mensual_trabajo_activ1*(J32+1-inicio_trabaj_activacion1),0) -> 0 | ... BK49: =IF(AND(BK32>=inicio_amortiz_activ1,BK32<final_amortiz_activ1),imp_activacion1-imp_activacion1/(años_amortiz_activ1*12)*(BK32-inicio_amortiz_activ1),0)+IF(AND(BK32>=inicio_trabaj_activacion1,BK32<=final_trabaj_activacion1),imp_mensual_trabajo_activ1*(BK32+1-inicio_trabaj_activacion1),0) -> 0
B50: Proyecto activación2 | C50: =IF(AND(C32>=inicio_amortiz_activ2,C32<final_amortiz_activ2),imp_activacion2-imp_activacion2/(años_amortiz_activ2*12)*(C32-inicio_amortiz_activ2),0)+IF(AND(C32>=inicio_trabaj_activacion2,C32<=final_trabaj_activacion2),imp_mensual_trabajo_activ2*(C32+1-inicio_trabaj_activacion2),0) -> 0 | D50: =IF(AND(D32>=inicio_amortiz_activ2,D32<final_amortiz_activ2),imp_activacion2-imp_activacion2/(años_amortiz_activ2*12)*(D32-inicio_amortiz_activ2),0)+IF(AND(D32>=inicio_trabaj_activacion2,D32<=final_trabaj_activacion2),imp_mensual_trabajo_activ2*(D32+1-inicio_trabaj_activacion2),0) -> 0 | E50: =IF(AND(E32>=inicio_amortiz_activ2,E32<final_amortiz_activ2),imp_activacion2-imp_activacion2/(años_amortiz_activ2*12)*(E32-inicio_amortiz_activ2),0)+IF(AND(E32>=inicio_trabaj_activacion2,E32<=final_trabaj_activacion2),imp_mensual_trabajo_activ2*(E32+1-inicio_trabaj_activacion2),0) -> 0 | F50: =IF(AND(F32>=inicio_amortiz_activ2,F32<final_amortiz_activ2),imp_activacion2-imp_activacion2/(años_amortiz_activ2*12)*(F32-inicio_amortiz_activ2),0)+IF(AND(F32>=inicio_trabaj_activacion2,F32<=final_trabaj_activacion2),imp_mensual_trabajo_activ2*(F32+1-inicio_trabaj_activacion2),0) -> 0 | G50: =IF(AND(G32>=inicio_amortiz_activ2,G32<final_amortiz_activ2),imp_activacion2-imp_activacion2/(años_amortiz_activ2*12)*(G32-inicio_amortiz_activ2),0)+IF(AND(G32>=inicio_trabaj_activacion2,G32<=final_trabaj_activacion2),imp_mensual_trabajo_activ2*(G32+1-inicio_trabaj_activacion2),0) -> 0 | H50: =IF(AND(H32>=inicio_amortiz_activ2,H32<final_amortiz_activ2),imp_activacion2-imp_activacion2/(años_amortiz_activ2*12)*(H32-inicio_amortiz_activ2),0)+IF(AND(H32>=inicio_trabaj_activacion2,H32<=final_trabaj_activacion2),imp_mensual_trabajo_activ2*(H32+1-inicio_trabaj_activacion2),0) -> 0 | I50: =IF(AND(I32>=inicio_amortiz_activ2,I32<final_amortiz_activ2),imp_activacion2-imp_activacion2/(años_amortiz_activ2*12)*(I32-inicio_amortiz_activ2),0)+IF(AND(I32>=inicio_trabaj_activacion2,I32<=final_trabaj_activacion2),imp_mensual_trabajo_activ2*(I32+1-inicio_trabaj_activacion2),0) -> 0 | J50: =IF(AND(J32>=inicio_amortiz_activ2,J32<final_amortiz_activ2),imp_activacion2-imp_activacion2/(años_amortiz_activ2*12)*(J32-inicio_amortiz_activ2),0)+IF(AND(J32>=inicio_trabaj_activacion2,J32<=final_trabaj_activacion2),imp_mensual_trabajo_activ2*(J32+1-inicio_trabaj_activacion2),0) -> 0 | ... BK50: =IF(AND(BK32>=inicio_amortiz_activ2,BK32<final_amortiz_activ2),imp_activacion2-imp_activacion2/(años_amortiz_activ2*12)*(BK32-inicio_amortiz_activ2),0)+IF(AND(BK32>=inicio_trabaj_activacion2,BK32<=final_trabaj_activacion2),imp_mensual_trabajo_activ2*(BK32+1-inicio_trabaj_activacion2),0) -> 0
B51: Total valor del inmobilizado | C51: =SUM(C34:C50) -> 0 | D51: =SUM(D34:D50) -> 0 | E51: =SUM(E34:E50) -> 0 | F51: =SUM(F34:F50) -> 0 | G51: =SUM(G34:G50) -> 0 | H51: =SUM(H34:H50) -> 0 | I51: =SUM(I34:I50) -> 0 | J51: =SUM(J34:J50) -> 0 | ... BK51: =SUM(BK34:BK50) -> 0
B52: Fianzas y depósitos
B53: Fianzas y depósitos (largo plazo en que estan inmobilizados) | C53: =IF(AND(C32>=mes_fianza,C32<(mes_fianza+año_fin_fianza*12)),importe_fianza,0) -> 0 | D53: =IF(AND(D32>=mes_fianza,D32<(mes_fianza+año_fin_fianza*12)),importe_fianza,0) -> 0 | E53: =IF(AND(E32>=mes_fianza,E32<(mes_fianza+año_fin_fianza*12)),importe_fianza,0) -> 0 | F53: =IF(AND(F32>=mes_fianza,F32<(mes_fianza+año_fin_fianza*12)),importe_fianza,0) -> 0 | G53: =IF(AND(G32>=mes_fianza,G32<(mes_fianza+año_fin_fianza*12)),importe_fianza,0) -> 0 | H53: =IF(AND(H32>=mes_fianza,H32<(mes_fianza+año_fin_fianza*12)),importe_fianza,0) -> 0 | I53: =IF(AND(I32>=mes_fianza,I32<(mes_fianza+año_fin_fianza*12)),importe_fianza,0) -> 0 | J53: =IF(AND(J32>=mes_fianza,J32<(mes_fianza+año_fin_fianza*12)),importe_fianza,0) -> 0 | ... BK53: =IF(AND(BK32>=mes_fianza,BK32<(mes_fianza+año_fin_fianza*12)),importe_fianza,0) -> 0
B54: Valor de las subvenciones de inversiones y activaciones
B55: Subvención inversión 1 | C55: =IF(AND(C32>=inicio_inv1,C32<final_inv1),imp_subv_inv1-imp_subv_inv1/(años_amortiz_inv1*12)*(C32-inicio_inv1),0) -> 0 | D55: =IF(AND(D32>=inicio_inv1,D32<final_inv1),imp_subv_inv1-imp_subv_inv1/(años_amortiz_inv1*12)*(D32-inicio_inv1),0) -> 0 | E55: =IF(AND(E32>=inicio_inv1,E32<final_inv1),imp_subv_inv1-imp_subv_inv1/(años_amortiz_inv1*12)*(E32-inicio_inv1),0) -> 0 | F55: =IF(AND(F32>=inicio_inv1,F32<final_inv1),imp_subv_inv1-imp_subv_inv1/(años_amortiz_inv1*12)*(F32-inicio_inv1),0) -> 0 | G55: =IF(AND(G32>=inicio_inv1,G32<final_inv1),imp_subv_inv1-imp_subv_inv1/(años_amortiz_inv1*12)*(G32-inicio_inv1),0) -> 0 | H55: =IF(AND(H32>=inicio_inv1,H32<final_inv1),imp_subv_inv1-imp_subv_inv1/(años_amortiz_inv1*12)*(H32-inicio_inv1),0) -> 0 | I55: =IF(AND(I32>=inicio_inv1,I32<final_inv1),imp_subv_inv1-imp_subv_inv1/(años_amortiz_inv1*12)*(I32-inicio_inv1),0) -> 0 | J55: =IF(AND(J32>=inicio_inv1,J32<final_inv1),imp_subv_inv1-imp_subv_inv1/(años_amortiz_inv1*12)*(J32-inicio_inv1),0) -> 0 | ... BK55: =IF(AND(BK32>=inicio_inv1,BK32<final_inv1),imp_subv_inv1-imp_subv_inv1/(años_amortiz_inv1*12)*(BK32-inicio_inv1),0) -> 0
B56: Subvención inversión 2 | C56: =IF(AND(C32>=inicio_inv2,C32<final_inv2),imp_subv_inv2-imp_subv_inv2/(años_amortiz_inv2*12)*(C32-inicio_inv2),0) -> 0 | D56: =IF(AND(D32>=inicio_inv2,D32<final_inv2),imp_subv_inv2-imp_subv_inv2/(años_amortiz_inv2*12)*(D32-inicio_inv2),0) -> 0 | E56: =IF(AND(E32>=inicio_inv2,E32<final_inv2),imp_subv_inv2-imp_subv_inv2/(años_amortiz_inv2*12)*(E32-inicio_inv2),0) -> 0 | F56: =IF(AND(F32>=inicio_inv2,F32<final_inv2),imp_subv_inv2-imp_subv_inv2/(años_amortiz_inv2*12)*(F32-inicio_inv2),0) -> 0 | G56: =IF(AND(G32>=inicio_inv2,G32<final_inv2),imp_subv_inv2-imp_subv_inv2/(años_amortiz_inv2*12)*(G32-inicio_inv2),0) -> 0 | H56: =IF(AND(H32>=inicio_inv2,H32<final_inv2),imp_subv_inv2-imp_subv_inv2/(años_amortiz_inv2*12)*(H32-inicio_inv2),0) -> 0 | I56: =IF(AND(I32>=inicio_inv2,I32<final_inv2),imp_subv_inv2-imp_subv_inv2/(años_amortiz_inv2*12)*(I32-inicio_inv2),0) -> 0 | J56: =IF(AND(J32>=inicio_inv2,J32<final_inv2),imp_subv_inv2-imp_subv_inv2/(años_amortiz_inv2*12)*(J32-inicio_inv2),0) -> 0 | ... BK56: =IF(AND(BK32>=inicio_inv2,BK32<final_inv2),imp_subv_inv2-imp_subv_inv2/(años_amortiz_inv2*12)*(BK32-inicio_inv2),0) -> 0
B57: Subvención activación 1 | C57: =IF(AND(C32>=inicio_amortiz_activ1,C32<final_amortiz_activ1),imp_subv_activ1-imp_subv_activ1/(años_amortiz_activ1*12)*(C32-inicio_amortiz_activ1),0) -> 0 | D57: =IF(AND(D32>=inicio_amortiz_activ1,D32<final_amortiz_activ1),imp_subv_activ1-imp_subv_activ1/(años_amortiz_activ1*12)*(D32-inicio_amortiz_activ1),0) -> 0 | E57: =IF(AND(E32>=inicio_amortiz_activ1,E32<final_amortiz_activ1),imp_subv_activ1-imp_subv_activ1/(años_amortiz_activ1*12)*(E32-inicio_amortiz_activ1),0) -> 0 | F57: =IF(AND(F32>=inicio_amortiz_activ1,F32<final_amortiz_activ1),imp_subv_activ1-imp_subv_activ1/(años_amortiz_activ1*12)*(F32-inicio_amortiz_activ1),0) -> 0 | G57: =IF(AND(G32>=inicio_amortiz_activ1,G32<final_amortiz_activ1),imp_subv_activ1-imp_subv_activ1/(años_amortiz_activ1*12)*(G32-inicio_amortiz_activ1),0) -> 0 | H57: =IF(AND(H32>=inicio_amortiz_activ1,H32<final_amortiz_activ1),imp_subv_activ1-imp_subv_activ1/(años_amortiz_activ1*12)*(H32-inicio_amortiz_activ1),0) -> 0 | I57: =IF(AND(I32>=inicio_amortiz_activ1,I32<final_amortiz_activ1),imp_subv_activ1-imp_subv_activ1/(años_amortiz_activ1*12)*(I32-inicio_amortiz_activ1),0) -> 0 | J57: =IF(AND(J32>=inicio_amortiz_activ1,J32<final_amortiz_activ1),imp_subv_activ1-imp_subv_activ1/(años_amortiz_activ1*12)*(J32-inicio_amortiz_activ1),0) -> 0 | ... BK57: =IF(AND(BK32>=inicio_amortiz_activ1,BK32<final_amortiz_activ1),imp_subv_activ1-imp_subv_activ1/(años_amortiz_activ1*12)*(BK32-inicio_amortiz_activ1),0) -> 0
B58: Subvención activación 2 | C58: =IF(AND(C32>=inicio_amortiz_activ2,C32<final_amortiz_activ2),imp_subv_activ2-imp_subv_activ2/(años_amortiz_activ2*12)*(C32-inicio_amortiz_activ2),0) -> 0 | D58: =IF(AND(D32>=inicio_amortiz_activ2,D32<final_amortiz_activ2),imp_subv_activ2-imp_subv_activ2/(años_amortiz_activ2*12)*(D32-inicio_amortiz_activ2),0) -> 0 | E58: =IF(AND(E32>=inicio_amortiz_activ2,E32<final_amortiz_activ2),imp_subv_activ2-imp_subv_activ2/(años_amortiz_activ2*12)*(E32-inicio_amortiz_activ2),0) -> 0 | F58: =IF(AND(F32>=inicio_amortiz_activ2,F32<final_amortiz_activ2),imp_subv_activ2-imp_subv_activ2/(años_amortiz_activ2*12)*(F32-inicio_amortiz_activ2),0) -> 0 | G58: =IF(AND(G32>=inicio_amortiz_activ2,G32<final_amortiz_activ2),imp_subv_activ2-imp_subv_activ2/(años_amortiz_activ2*12)*(G32-inicio_amortiz_activ2),0) -> 0 | H58: =IF(AND(H32>=inicio_amortiz_activ2,H32<final_amortiz_activ2),imp_subv_activ2-imp_subv_activ2/(años_amortiz_activ2*12)*(H32-inicio_amortiz_activ2),0) -> 0 | I58: =IF(AND(I32>=inicio_amortiz_activ2,I32<final_amortiz_activ2),imp_subv_activ2-imp_subv_activ2/(años_amortiz_activ2*12)*(I32-inicio_amortiz_activ2),0) -> 0 | J58: =IF(AND(J32>=inicio_amortiz_activ2,J32<final_amortiz_activ2),imp_subv_activ2-imp_subv_activ2/(años_amortiz_activ2*12)*(J32-inicio_amortiz_activ2),0) -> 0 | ... BK58: =IF(AND(BK32>=inicio_amortiz_activ2,BK32<final_amortiz_activ2),imp_subv_activ2-imp_subv_activ2/(años_amortiz_activ2*12)*(BK32-inicio_amortiz_activ2),0) -> 0
B59: Total valor de las subvenciones de capital | C59: =SUM(C55:C58) -> 0 | D59: =SUM(D55:D58) -> 0 | E59: =SUM(E55:E58) -> 0 | F59: =SUM(F55:F58) -> 0 | G59: =SUM(G55:G58) -> 0 | H59: =SUM(H55:H58) -> 0 | I59: =SUM(I55:I58) -> 0 | J59: =SUM(J55:J58) -> 0 | ... BK59: =SUM(BK55:BK58) -> 0
B61: SALDO DE CAPITAL SOCIAL
C62: 0 | D62: 1 | E62: 2 | F62: 3 | G62: 4 | H62: 5 | I62: 6 | J62: 7 | K62: 8 | L62: 9 | M62: 10 | N62: 11 | O62: 12 | P62: 13 | Q62: 14 | R62: 15 | S62: 16 | T62: 17 | U62: 18 | V62: 19 | W62: 20 | X62: 21 | Y62: 22 | Z62: 23 | AA62: 24 | AB62: 25 | AC62: 26 | AD62: 27 | AE62: 28 | AF62: 29 | AG62: 30 | AH62: 31 | AI62: 32 | AJ62: 33 | AK62: 34 | AL62: 35 | AM62: 36 | AN62: 37 | AO62: 38 | AP62: 39 | AQ62: 40 | AR62: 41 | AS62: 42 | AT62: 43 | AU62: 44 | AV62: 45 | AW62: 46 | AX62: 47 | AY62: 48 | AZ62: 49 | BA62: 50 | BB62: 51 | BC62: 52 | BD62: 53 | BE62: 54 | BF62: 55 | BG62: 56 | BH62: 57 | BI62: 58 | BJ62: 59 | BK62: 60
B63: Capital social y ampliaciones de capital | C63: ='HIPOTESIS '!D63+IF(C62=mes_ampliacion_capital_1,Ampliación_de_capital_1,0) -> 1000 | D63: =IF(D62=mes_ampliacion_capital_1,Ampliación_de_capital_1,0) -> 0 | E63: =IF(E62=mes_ampliacion_capital_1,Ampliación_de_capital_1,0) -> 0 | F63: =IF(F62=mes_ampliacion_capital_1,Ampliación_de_capital_1,0) -> 0 | G63: =IF(G62=mes_ampliacion_capital_1,Ampliación_de_capital_1,0) -> 0 | H63: =IF(H62=mes_ampliacion_capital_1,Ampliación_de_capital_1,0) -> 0 | I63: =IF(I62=mes_ampliacion_capital_1,Ampliación_de_capital_1,0) -> 0 | J63: =IF(J62=mes_ampliacion_capital_1,Ampliación_de_capital_1,0) -> 0 | K63: =IF(K62=mes_ampliacion_capital_1,Ampliación_de_capital_1,0) -> 0 | ... BK63: =IF(BK62=mes_ampliacion_capital_1,Ampliación_de_capital_1,0) -> 0
B64: Total capital social acumulado | C64: =C63 -> 1000 | D64: =C64+D63 -> 1000 | E64: =D64+E63 -> 1000 | F64: =E64+F63 -> 1000 | G64: =F64+G63 -> 1000 | H64: =G64+H63 -> 1000 | I64: =H64+I63 -> 1000 | J64: =I64+J63 -> 1000 | K64: =J64+K63 -> 1000 | ... BK64: =BJ64+BK63 -> 1000
B66: CUADRO FINANCIERO PRÉSTAMO 1 (método francés) | C66: MESES
C67: 0 | D67: 1 | E67: 2 | F67: 3 | G67: 4 | H67: 5 | I67: 6 | J67: 7 | K67: 8 | L67: 9 | M67: 10 | N67: 11 | O67: 12 | P67: 13 | Q67: 14 | R67: 15 | S67: 16 | T67: 17 | U67: 18 | V67: 19 | W67: 20 | X67: 21 | Y67: 22 | Z67: 23 | AA67: 24 | AB67: 25 | AC67: 26 | AD67: 27 | AE67: 28 | AF67: 29 | AG67: 30 | AH67: 31 | AI67: 32 | AJ67: 33 | AK67: 34 | AL67: 35 | AM67: 36 | AN67: 37 | AO67: 38 | AP67: 39 | AQ67: 40 | AR67: 41 | AS67: 42 | AT67: 43 | AU67: 44 | AV67: 45 | AW67: 46 | AX67: 47 | AY67: 48 | AZ67: 49 | BA67: 50 | BB67: 51 | BC67: 52 | BD67: 53 | BE67: 54 | BF67: 55 | BG67: 56 | BH67: 57 | BI67: 58 | BJ67: 59 | BK67: 60
B68: Saldo vivo final periodo (Capital pendiente del préstamo a fin de mes) | C68: =IF(AND(C67>=(inicio_p1),C67<final_p1),IF(AND(C67>=(inicio_p1),C67<=inicio_p1+carencia_p1),imp_p1,B68-C72),0) -> 0 | D68: =IF(AND(D67>=(inicio_p1),D67<final_p1),IF(AND(D67>=(inicio_p1),D67<=inicio_p1+carencia_p1),imp_p1,C68-D72),0) -> 0 | E68: =IF(AND(E67>=(inicio_p1),E67<final_p1),IF(AND(E67>=(inicio_p1),E67<=inicio_p1+carencia_p1),imp_p1,D68-E72),0) -> 0 | F68: =IF(AND(F67>=(inicio_p1),F67<final_p1),IF(AND(F67>=(inicio_p1),F67<=inicio_p1+carencia_p1),imp_p1,E68-F72),0) -> 0 | G68: =IF(AND(G67>=(inicio_p1),G67<final_p1),IF(AND(G67>=(inicio_p1),G67<=inicio_p1+carencia_p1),imp_p1,F68-G72),0) -> 0 | H68: =IF(AND(H67>=(inicio_p1),H67<final_p1),IF(AND(H67>=(inicio_p1),H67<=inicio_p1+carencia_p1),imp_p1,G68-H72),0) -> 0 | I68: =IF(AND(I67>=(inicio_p1),I67<final_p1),IF(AND(I67>=(inicio_p1),I67<=inicio_p1+carencia_p1),imp_p1,H68-I72),0) -> 0 | J68: =IF(AND(J67>=(inicio_p1),J67<final_p1),IF(AND(J67>=(inicio_p1),J67<=inicio_p1+carencia_p1),imp_p1,I68-J72),0) -> 0 | ... BK68: =IF(AND(BK67>=(inicio_p1),BK67<final_p1),IF(AND(BK67>=(inicio_p1),BK67<=inicio_p1+carencia_p1),imp_p1,BJ68-BK72),0) -> 0
B69: Parte del saldo vivo que es a corto plazo (<=12 meses) | C69: =IF(C67>=inicio_p1,SUM(D72:O72),0) -> 0 | D69: =IF(D67>=inicio_p1,SUM(E72:P72),0) -> 0 | E69: =IF(E67>=inicio_p1,SUM(F72:Q72),0) -> 0 | F69: =IF(F67>=inicio_p1,SUM(G72:R72),0) -> 0 | G69: =IF(G67>=inicio_p1,SUM(H72:S72),0) -> 0 | H69: =IF(H67>=inicio_p1,SUM(I72:T72),0) -> 0 | I69: =IF(I67>=inicio_p1,SUM(J72:U72),0) -> 0 | J69: =IF(J67>=inicio_p1,SUM(K72:V72),0) -> 0 | ... BK69: =IF(BK67>=inicio_p1,SUM(BL72:BW72),0) -> 0
B70: Parte del saldo vivo que es a largo plazo (>12 meses) | C70: =C68-C69 -> 0 | D70: =D68-D69 -> 0 | E70: =E68-E69 -> 0 | F70: =F68-F69 -> 0 | G70: =G68-G69 -> 0 | H70: =H68-H69 -> 0 | I70: =I68-I69 -> 0 | J70: =J68-J69 -> 0 | ... BK70: =BK68-BK69 -> 0
B71: Cuota total a abonar a 31/12 (capital + intereses) | C71: =IF(AND(C67>(inicio_p1+carencia_p1),C67<=(final_p1)),PMT(interes_p2/12,meses_amortiz_p1,-imp_p1),0) -> 0 | D71: =IF(AND(D67>(inicio_p1+carencia_p1),D67<=(final_p1)),PMT(interes_p1/12,meses_amortiz_p1,-imp_p1),0) -> 0 | E71: =IF(AND(E67>(inicio_p1+carencia_p1),E67<=(final_p1)),PMT(interes_p1/12,meses_amortiz_p1,-imp_p1),0) -> 0 | F71: =IF(AND(F67>(inicio_p1+carencia_p1),F67<=(final_p1)),PMT(interes_p1/12,meses_amortiz_p1,-imp_p1),0) -> 0 | G71: =IF(AND(G67>(inicio_p1+carencia_p1),G67<=(final_p1)),PMT(interes_p1/12,meses_amortiz_p1,-imp_p1),0) -> 0 | H71: =IF(AND(H67>(inicio_p1+carencia_p1),H67<=(final_p1)),PMT(interes_p1/12,meses_amortiz_p1,-imp_p1),0) -> 0 | I71: =IF(AND(I67>(inicio_p1+carencia_p1),I67<=(final_p1)),PMT(interes_p1/12,meses_amortiz_p1,-imp_p1),0) -> 0 | J71: =IF(AND(J67>(inicio_p1+carencia_p1),J67<=(final_p1)),PMT(interes_p1/12,meses_amortiz_p1,-imp_p1),0) -> 0 | K71: =IF(AND(K67>(inicio_p1+carencia_p1),K67<=(final_p1)),PMT(interes_p1/12,meses_amortiz_p1,-imp_p1),0) -> 0 | ... BK71: =IF(AND(BK67>(inicio_p1+carencia_p1),BK67<=(final_p1)),PMT(interes_p1/12,meses_amortiz_p1,-imp_p1),0) -> 0
B72: Cuota de amortización capital a final de periodo | C72: =IF(C71>0,C71-C73,0) -> 0 | D72: =IF(D71>0,D71-D73,0) -> 0 | E72: =IF(E71>0,E71-E73,0) -> 0 | F72: =IF(F71>0,F71-F73,0) -> 0 | G72: =IF(G71>0,G71-G73,0) -> 0 | H72: =IF(H71>0,H71-H73,0) -> 0 | I72: =IF(I71>0,I71-I73,0) -> 0 | J72: =IF(J71>0,J71-J73,0) -> 0 | ... BK72: =IF(BK71>0,BK71-BK73,0) -> 0
B73: Cuota de intereses a final de periodo | C73: 0 | D73: =C68*interes_p1/12 -> 0 | E73: =D68*interes_p1/12 -> 0 | F73: =E68*interes_p1/12 -> 0 | G73: =F68*interes_p1/12 -> 0 | H73: =G68*interes_p1/12 -> 0 | I73: =H68*interes_p1/12 -> 0 | J73: =I68*interes_p1/12 -> 0 | K73: =J68*interes_p1/12 -> 0 | ... BK73: =BJ68*interes_p1/12 -> 0
B75: CUADRO FINANCIERO PRÉSTAMO 2 (método francés) | C75: MESES
C76: 0 | D76: 1 | E76: 2 | F76: 3 | G76: 4 | H76: 5 | I76: 6 | J76: 7 | K76: 8 | L76: 9 | M76: 10 | N76: 11 | O76: 12 | P76: 13 | Q76: 14 | R76: 15 | S76: 16 | T76: 17 | U76: 18 | V76: 19 | W76: 20 | X76: 21 | Y76: 22 | Z76: 23 | AA76: 24 | AB76: 25 | AC76: 26 | AD76: 27 | AE76: 28 | AF76: 29 | AG76: 30 | AH76: 31 | AI76: 32 | AJ76: 33 | AK76: 34 | AL76: 35 | AM76: 36 | AN76: 37 | AO76: 38 | AP76: 39 | AQ76: 40 | AR76: 41 | AS76: 42 | AT76: 43 | AU76: 44 | AV76: 45 | AW76: 46 | AX76: 47 | AY76: 48 | AZ76: 49 | BA76: 50 | BB76: 51 | BC76: 52 | BD76: 53 | BE76: 54 | BF76: 55 | BG76: 56 | BH76: 57 | BI76: 58 | BJ76: 59 | BK76: 60
B77: Saldo vivo final periodo (Capital pendiente del préstamo a fin de mes) | C77: =IF(AND(C76>=(inicio_p2),C76<final_p2),IF(AND(C76>=(inicio_p2),C76<=inicio_p2+carencia_p2),imp_p2,B77-C81),0) -> 0 | D77: =IF(AND(D76>=(inicio_p2),D76<final_p2),IF(AND(D76>=(inicio_p2),D76<=inicio_p2+carencia_p2),imp_p2,C77-D81),0) -> 0 | E77: =IF(AND(E76>=(inicio_p2),E76<final_p2),IF(AND(E76>=(inicio_p2),E76<=inicio_p2+carencia_p2),imp_p2,D77-E81),0) -> 0 | F77: =IF(AND(F76>=(inicio_p2),F76<final_p2),IF(AND(F76>=(inicio_p2),F76<=inicio_p2+carencia_p2),imp_p2,E77-F81),0) -> 0 | G77: =IF(AND(G76>=(inicio_p2),G76<final_p2),IF(AND(G76>=(inicio_p2),G76<=inicio_p2+carencia_p2),imp_p2,F77-G81),0) -> 0 | H77: =IF(AND(H76>=(inicio_p2),H76<final_p2),IF(AND(H76>=(inicio_p2),H76<=inicio_p2+carencia_p2),imp_p2,G77-H81),0) -> 0 | I77: =IF(AND(I76>=(inicio_p2),I76<final_p2),IF(AND(I76>=(inicio_p2),I76<=inicio_p2+carencia_p2),imp_p2,H77-I81),0) -> 0 | J77: =IF(AND(J76>=(inicio_p2),J76<final_p2),IF(AND(J76>=(inicio_p2),J76<=inicio_p2+carencia_p2),imp_p2,I77-J81),0) -> 0 | ... BK77: =IF(AND(BK76>=(inicio_p2),BK76<final_p2),IF(AND(BK76>=(inicio_p2),BK76<=inicio_p2+carencia_p2),imp_p2,BJ77-BK81),0) -> 0
B78: Parte del saldo vivo que es a corto plazo (<=12 meses) | C78: =IF(C76>=inicio_p2,SUM(D81:O81),0) -> 0 | D78: =IF(D76>=inicio_p2,SUM(E81:P81),0) -> 0 | E78: =IF(E76>=inicio_p2,SUM(F81:Q81),0) -> 0 | F78: =IF(F76>=inicio_p2,SUM(G81:R81),0) -> 0 | G78: =IF(G76>=inicio_p2,SUM(H81:S81),0) -> 0 | H78: =IF(H76>=inicio_p2,SUM(I81:T81),0) -> 0 | I78: =IF(I76>=inicio_p2,SUM(J81:U81),0) -> 0 | J78: =IF(J76>=inicio_p2,SUM(K81:V81),0) -> 0 | ... BK78: =IF(BK76>=inicio_p2,SUM(BL81:BW81),0) -> 0
B79: Parte del saldo vivo que es a largo plazo (>12 meses) | C79: =C77-C78 -> 0 | D79: =D77-D78 -> 0 | E79: =E77-E78 -> 0 | F79: =F77-F78 -> 0 | G79: =G77-G78 -> 0 | H79: =H77-H78 -> 0 | I79: =I77-I78 -> 0 | J79: =J77-J78 -> 0 | ... BK79: =BK77-BK78 -> 0
B80: Cuota total a abonar a 31/12 (capital + intereses) | C80: =IF(AND(C76>(inicio_p2+carencia_p2),C76<=(final_p2)),PMT(interes_p2/12,meses_amortiz_p2,-imp_p2),0) -> 0 | D80: =IF(AND(D76>(inicio_p2+carencia_p2),D76<=(final_p2)),PMT(interes_p2/12,meses_amortiz_p2,-imp_p2),0) -> 0 | E80: =IF(AND(E76>(inicio_p2+carencia_p2),E76<=(final_p2)),PMT(interes_p2/12,meses_amortiz_p2,-imp_p2),0) -> 0 | F80: =IF(AND(F76>(inicio_p2+carencia_p2),F76<=(final_p2)),PMT(interes_p2/12,meses_amortiz_p2,-imp_p2),0) -> 0 | G80: =IF(AND(G76>(inicio_p2+carencia_p2),G76<=(final_p2)),PMT(interes_p2/12,meses_amortiz_p2,-imp_p2),0) -> 0 | H80: =IF(AND(H76>(inicio_p2+carencia_p2),H76<=(final_p2)),PMT(interes_p2/12,meses_amortiz_p2,-imp_p2),0) -> 0 | I80: =IF(AND(I76>(inicio_p2+carencia_p2),I76<=(final_p2)),PMT(interes_p2/12,meses_amortiz_p2,-imp_p2),0) -> 0 | J80: =IF(AND(J76>(inicio_p2+carencia_p2),J76<=(final_p2)),PMT(interes_p2/12,meses_amortiz_p2,-imp_p2),0) -> 0 | ... BK80: =IF(AND(BK76>(inicio_p2+carencia_p2),BK76<=(final_p2)),PMT(interes_p2/12,meses_amortiz_p2,-imp_p2),0) -> 0
B81: Cuota de amortización capital a final de periodo | C81: =IF(C80>0,C80-C82,0) -> 0 | D81: =IF(D80>0,D80-D82,0) -> 0 | E81: =IF(E80>0,E80-E82,0) -> 0 | F81: =IF(F80>0,F80-F82,0) -> 0 | G81: =IF(G80>0,G80-G82,0) -> 0 | H81: =IF(H80>0,H80-H82,0) -> 0 | I81: =IF(I80>0,I80-I82,0) -> 0 | J81: =IF(J80>0,J80-J82,0) -> 0 | ... BK81: =IF(BK80>0,BK80-BK82,0) -> 0
B82: Cuota de intereses a final de periodo | C82: 0 | D82: =C77*interes_p2/12 -> 0 | E82: =D77*interes_p2/12 -> 0 | F82: =E77*interes_p2/12 -> 0 | G82: =F77*interes_p2/12 -> 0 | H82: =G77*interes_p2/12 -> 0 | I82: =H77*interes_p2/12 -> 0 | J82: =I77*interes_p2/12 -> 0 | K82: =J77*interes_p2/12 -> 0 | ... BK82: =BJ77*interes_p2/12 -> 0
B84: CUADRO FINANCIERO PRÉSTAMO PARTICIPATIVO (método aleman) | C84: MESES
C85: 0 | D85: 1 | E85: 2 | F85: 3 | G85: 4 | H85: 5 | I85: 6 | J85: 7 | K85: 8 | L85: 9 | M85: 10 | N85: 11 | O85: 12 | P85: 13 | Q85: 14 | R85: 15 | S85: 16 | T85: 17 | U85: 18 | V85: 19 | W85: 20 | X85: 21 | Y85: 22 | Z85: 23 | AA85: 24 | AB85: 25 | AC85: 26 | AD85: 27 | AE85: 28 | AF85: 29 | AG85: 30 | AH85: 31 | AI85: 32 | AJ85: 33 | AK85: 34 | AL85: 35 | AM85: 36 | AN85: 37 | AO85: 38 | AP85: 39 | AQ85: 40 | AR85: 41 | AS85: 42 | AT85: 43 | AU85: 44 | AV85: 45 | AW85: 46 | AX85: 47 | AY85: 48 | AZ85: 49 | BA85: 50 | BB85: 51 | BC85: 52 | BD85: 53 | BE85: 54 | BF85: 55 | BG85: 56 | BH85: 57 | BI85: 58 | BJ85: 59 | BK85: 60
B86: Saldo vivo final periodo (Capital pendiente del préstamo a fin de mes) | C86: =IF(AND(C85>=(inicio_prest_participa),C85<final_prest_participa),IF(AND(C85>=(inicio_prest_participa),C85<=inicio_prest_participa+carencia_prest_participa),importe_prest_participa,B86-C88),0) -> 0 | D86: =IF(AND(D85>=(inicio_prest_participa),D85<final_prest_participa),IF(AND(D85>=(inicio_prest_participa),D85<=inicio_prest_participa+carencia_prest_participa),importe_prest_participa,C86-D88),0) -> 0 | E86: =IF(AND(E85>=(inicio_prest_participa),E85<final_prest_participa),IF(AND(E85>=(inicio_prest_participa),E85<=inicio_prest_participa+carencia_prest_participa),importe_prest_participa,D86-E88),0) -> 0 | F86: =IF(AND(F85>=(inicio_prest_participa),F85<final_prest_participa),IF(AND(F85>=(inicio_prest_participa),F85<=inicio_prest_participa+carencia_prest_participa),importe_prest_participa,E86-F88),0) -> 0 | G86: =IF(AND(G85>=(inicio_prest_participa),G85<final_prest_participa),IF(AND(G85>=(inicio_prest_participa),G85<=inicio_prest_participa+carencia_prest_participa),importe_prest_participa,F86-G88),0) -> 0 | H86: =IF(AND(H85>=(inicio_prest_participa),H85<final_prest_participa),IF(AND(H85>=(inicio_prest_participa),H85<=inicio_prest_participa+carencia_prest_participa),importe_prest_participa,G86-H88),0) -> 0 | I86: =IF(AND(I85>=(inicio_prest_participa),I85<final_prest_participa),IF(AND(I85>=(inicio_prest_participa),I85<=inicio_prest_participa+carencia_prest_participa),importe_prest_participa,H86-I88),0) -> 0 | J86: =IF(AND(J85>=(inicio_prest_participa),J85<final_prest_participa),IF(AND(J85>=(inicio_prest_participa),J85<=inicio_prest_participa+carencia_prest_participa),importe_prest_participa,I86-J88),0) -> 0 | ... BK86: =IF(AND(BK85>=(inicio_prest_participa),BK85<final_prest_participa),IF(AND(BK85>=(inicio_prest_participa),BK85<=inicio_prest_participa+carencia_prest_participa),importe_prest_participa,BJ86-BK88),0) -> 0
B87: Cuota total a abonar capital a final de periodo | C87: =IF(C88>0,C88-C89,0) -> 0 | D87: =IF(D88>0,D88+D89,0) -> 0 | E87: =IF(E88>0,E88+E89,0) -> 0 | F87: =IF(F88>0,F88+F89,0) -> 0 | G87: =IF(G88>0,G88+G89,0) -> 0 | H87: =IF(H88>0,H88+H89,0) -> 0 | I87: =IF(I88>0,I88+I89,0) -> 0 | J87: =IF(J88>0,J88+J89,0) -> 0 | K87: =IF(K88>0,K88+K89,0) -> 0 | ... BK87: =IF(BK88>0,BK88+BK89,0) -> 0
B88: Cuota de amortización capital a final de periodo | C88: =IF(AND(C85>(inicio_p2+carencia_p2),C85<=(final_p2)),PMT(interes_p2/12,meses_amortiz_p2,-imp_p2),0) -> 0 | D88: =IF(AND(D85>(inicio_prest_participa+carencia_prest_participa),D85<=(final_prest_participa)),importe_prest_participa/meses_amortiz_prest_participa,0) -> 0 | E88: =IF(AND(E85>(inicio_prest_participa+carencia_prest_participa),E85<=(final_prest_participa)),importe_prest_participa/meses_amortiz_prest_participa,0) -> 0 | F88: =IF(AND(F85>(inicio_prest_participa+carencia_prest_participa),F85<=(final_prest_participa)),importe_prest_participa/meses_amortiz_prest_participa,0) -> 0 | G88: =IF(AND(G85>(inicio_prest_participa+carencia_prest_participa),G85<=(final_prest_participa)),importe_prest_participa/meses_amortiz_prest_participa,0) -> 0 | H88: =IF(AND(H85>(inicio_prest_participa+carencia_prest_participa),H85<=(final_prest_participa)),importe_prest_participa/meses_amortiz_prest_participa,0) -> 0 | I88: =IF(AND(I85>(inicio_prest_participa+carencia_prest_participa),I85<=(final_prest_participa)),importe_prest_participa/meses_amortiz_prest_participa,0) -> 0 | J88: =IF(AND(J85>(inicio_prest_participa+carencia_prest_participa),J85<=(final_prest_participa)),importe_prest_participa/meses_amortiz_prest_participa,0) -> 0 | K88: =IF(AND(K85>(inicio_prest_participa+carencia_prest_participa),K85<=(final_prest_participa)),importe_prest_participa/meses_amortiz_prest_participa,0) -> 0 | ... BK88: =IF(AND(BK85>(inicio_prest_participa+carencia_prest_participa),BK85<=(final_prest_participa)),importe_prest_participa/meses_amortiz_prest_participa,0) -> 0
B89: Cuota de intereses a final de periodo (interes participativo) | C89: 0 | D89: =IF(AND(D85>=0,D85<=inicio_prest_participa+carencia_prest_participa),C86*interes_inicio_prest_participa/12,C86*interes_participativo_prest_participa/12) -> 0 | E89: =IF(AND(E85>=0,E85<=inicio_prest_participa+carencia_prest_participa),D86*interes_inicio_prest_participa/12,D86*interes_participativo_prest_participa/12) -> 0 | F89: =IF(AND(F85>=0,F85<=inicio_prest_participa+carencia_prest_participa),E86*interes_inicio_prest_participa/12,E86*interes_participativo_prest_participa/12) -> 0 | G89: =IF(AND(G85>=0,G85<=inicio_prest_participa+carencia_prest_participa),F86*interes_inicio_prest_participa/12,F86*interes_participativo_prest_participa/12) -> 0 | H89: =IF(AND(H85>=0,H85<=inicio_prest_participa+carencia_prest_participa),G86*interes_inicio_prest_participa/12,G86*interes_participativo_prest_participa/12) -> 0 | I89: =IF(AND(I85>=0,I85<=inicio_prest_participa+carencia_prest_participa),H86*interes_inicio_prest_participa/12,H86*interes_participativo_prest_participa/12) -> 0 | J89: =IF(AND(J85>=0,J85<=inicio_prest_participa+carencia_prest_participa),I86*interes_inicio_prest_participa/12,I86*interes_participativo_prest_participa/12) -> 0 | K89: =IF(AND(K85>=0,K85<=inicio_prest_participa+carencia_prest_participa),J86*interes_inicio_prest_participa/12,J86*interes_participativo_prest_participa/12) -> 0 | ... BK89: =IF(AND(BK85>=0,BK85<=inicio_prest_participa+carencia_prest_participa),BJ86*interes_inicio_prest_participa/12,BJ86*interes_participativo_prest_participa/12) -> 0
B91: INGRESOS POR TRABAJOS PARA EL PROPIO ACTIVO | C91: 0 | D91: 1 | E91: 2 | F91: 3 | G91: 4 | H91: 5 | I91: 6 | J91: 7 | K91: 8 | L91: 9 | M91: 10 | N91: 11 | O91: 12 | P91: 13 | Q91: 14 | R91: 15 | S91: 16 | T91: 17 | U91: 18 | V91: 19 | W91: 20 | X91: 21 | Y91: 22 | Z91: 23 | AA91: 24 | AB91: 25 | AC91: 26 | AD91: 27 | AE91: 28 | AF91: 29 | AG91: 30 | AH91: 31 | AI91: 32 | AJ91: 33 | AK91: 34 | AL91: 35 | AM91: 36 | AN91: 37 | AO91: 38 | AP91: 39 | AQ91: 40 | AR91: 41 | AS91: 42 | AT91: 43 | AU91: 44 | AV91: 45 | AW91: 46 | AX91: 47 | AY91: 48 | AZ91: 49 | BA91: 50 | BB91: 51 | BC91: 52 | BD91: 53 | BE91: 54 | BF91: 55 | BG91: 56 | BH91: 57 | BI91: 58 | BJ91: 59 | BK91: 60
B92: Proyecto de activación 1 | C92: =IF(AND(C91>=inicio_trabaj_activacion1,C91<=final_trabaj_activacion1),imp_mensual_trabajo_activ1,0) -> 0 | D92: =IF(AND(D91>=inicio_trabaj_activacion1,D91<=final_trabaj_activacion1),imp_mensual_trabajo_activ1,0) -> 0 | E92: =IF(AND(E91>=inicio_trabaj_activacion1,E91<=final_trabaj_activacion1),imp_mensual_trabajo_activ1,0) -> 0 | F92: =IF(AND(F91>=inicio_trabaj_activacion1,F91<=final_trabaj_activacion1),imp_mensual_trabajo_activ1,0) -> 0 | G92: =IF(AND(G91>=inicio_trabaj_activacion1,G91<=final_trabaj_activacion1),imp_mensual_trabajo_activ1,0) -> 0 | H92: =IF(AND(H91>=inicio_trabaj_activacion1,H91<=final_trabaj_activacion1),imp_mensual_trabajo_activ1,0) -> 0 | I92: =IF(AND(I91>=inicio_trabaj_activacion1,I91<=final_trabaj_activacion1),imp_mensual_trabajo_activ1,0) -> 0 | J92: =IF(AND(J91>=inicio_trabaj_activacion1,J91<=final_trabaj_activacion1),imp_mensual_trabajo_activ1,0) -> 0 | ... BK92: =IF(AND(BK91>=inicio_trabaj_activacion1,BK91<=final_trabaj_activacion1),imp_mensual_trabajo_activ1,0) -> 0
B93: Proyecto de activación 2 | C93: =IF(AND(C91>=inicio_trabaj_activacion2,C91<=final_trabaj_activacion2),imp_mensual_trabajo_activ2,0) -> 0 | D93: =IF(AND(D91>=inicio_trabaj_activacion2,D91<=final_trabaj_activacion2),imp_mensual_trabajo_activ2,0) -> 0 | E93: =IF(AND(E91>=inicio_trabaj_activacion2,E91<=final_trabaj_activacion2),imp_mensual_trabajo_activ2,0) -> 0 | F93: =IF(AND(F91>=inicio_trabaj_activacion2,F91<=final_trabaj_activacion2),imp_mensual_trabajo_activ2,0) -> 0 | G93: =IF(AND(G91>=inicio_trabaj_activacion2,G91<=final_trabaj_activacion2),imp_mensual_trabajo_activ2,0) -> 0 | H93: =IF(AND(H91>=inicio_trabaj_activacion2,H91<=final_trabaj_activacion2),imp_mensual_trabajo_activ2,0) -> 0 | I93: =IF(AND(I91>=inicio_trabaj_activacion2,I91<=final_trabaj_activacion2),imp_mensual_trabajo_activ2,0) -> 0 | J93: =IF(AND(J91>=inicio_trabaj_activacion2,J91<=final_trabaj_activacion2),imp_mensual_trabajo_activ2,0) -> 0 | ... BK93: =IF(AND(BK91>=inicio_trabaj_activacion2,BK91<=final_trabaj_activacion2),imp_mensual_trabajo_activ2,0) -> 0
B95: FLUJO DE LAS OPERACIONES COMERCIALES (sin IVA) | C95: 0 | D95: 1 | E95: 2 | F95: 3 | G95: 4 | H95: 5 | I95: 6 | J95: 7 | K95: 8 | L95: 9 | M95: 10 | N95: 11 | O95: 12 | P95: 13 | Q95: 14 | R95: 15 | S95: 16 | T95: 17 | U95: 18 | V95: 19 | W95: 20 | X95: 21 | Y95: 22 | Z95: 23 | AA95: 24 | AB95: 25 | AC95: 26 | AD95: 27 | AE95: 28 | AF95: 29 | AG95: 30 | AH95: 31 | AI95: 32 | AJ95: 33 | AK95: 34 | AL95: 35 | AM95: 36 | AN95: 37 | AO95: 38 | AP95: 39 | AQ95: 40 | AR95: 41 | AS95: 42 | AT95: 43 | AU95: 44 | AV95: 45 | AW95: 46 | AX95: 47 | AY95: 48 | AZ95: 49 | BA95: 50 | BB95: 51 | BC95: 52 | BD95: 53 | BE95: 54 | BF95: 55 | BG95: 56 | BH95: 57 | BI95: 58 | BJ95: 59 | BK95: 60
B96: Cobros de clientes tipo A | C96: 0 | D96: =IF(D95>=plazo_cobroA,(IF(plazo_cobroA=0,'HIPOTESIS '!D146,0)+IF(plazo_cobroA=1,'HIPOTESIS '!C146,0)+IF(plazo_cobroA=2,'HIPOTESIS '!B146,0)+IF(plazo_cobroA=3,'HIPOTESIS '!A146,0)),0) -> 0 | E96: =IF(E95>=plazo_cobroA,(IF(plazo_cobroA=0,'HIPOTESIS '!E146,0)+IF(plazo_cobroA=1,'HIPOTESIS '!D146,0)+IF(plazo_cobroA=2,'HIPOTESIS '!C146,0)+IF(plazo_cobroA=3,'HIPOTESIS '!B146,0)),0) -> 0 | F96: =IF(F95>=plazo_cobroA,(IF(plazo_cobroA=0,'HIPOTESIS '!F146,0)+IF(plazo_cobroA=1,'HIPOTESIS '!E146,0)+IF(plazo_cobroA=2,'HIPOTESIS '!D146,0)+IF(plazo_cobroA=3,'HIPOTESIS '!C146,0)),0) -> 0 | G96: =IF(G95>=plazo_cobroA,(IF(plazo_cobroA=0,'HIPOTESIS '!G146,0)+IF(plazo_cobroA=1,'HIPOTESIS '!F146,0)+IF(plazo_cobroA=2,'HIPOTESIS '!E146,0)+IF(plazo_cobroA=3,'HIPOTESIS '!D146,0)),0) -> 0 | H96: =IF(H95>=plazo_cobroA,(IF(plazo_cobroA=0,'HIPOTESIS '!H146,0)+IF(plazo_cobroA=1,'HIPOTESIS '!G146,0)+IF(plazo_cobroA=2,'HIPOTESIS '!F146,0)+IF(plazo_cobroA=3,'HIPOTESIS '!E146,0)),0) -> 0 | I96: =IF(I95>=plazo_cobroA,(IF(plazo_cobroA=0,'HIPOTESIS '!I146,0)+IF(plazo_cobroA=1,'HIPOTESIS '!H146,0)+IF(plazo_cobroA=2,'HIPOTESIS '!G146,0)+IF(plazo_cobroA=3,'HIPOTESIS '!F146,0)),0) -> 0 | J96: =IF(J95>=plazo_cobroA,(IF(plazo_cobroA=0,'HIPOTESIS '!J146,0)+IF(plazo_cobroA=1,'HIPOTESIS '!I146,0)+IF(plazo_cobroA=2,'HIPOTESIS '!H146,0)+IF(plazo_cobroA=3,'HIPOTESIS '!G146,0)),0) -> 0 | K96: =IF(K95>=plazo_cobroA,(IF(plazo_cobroA=0,'HIPOTESIS '!K146,0)+IF(plazo_cobroA=1,'HIPOTESIS '!J146,0)+IF(plazo_cobroA=2,'HIPOTESIS '!I146,0)+IF(plazo_cobroA=3,'HIPOTESIS '!H146,0)),0) -> 0 | ... BK96: =IF(BK95>=plazo_cobroA,(IF(plazo_cobroA=0,'HIPOTESIS '!BK146,0)+IF(plazo_cobroA=1,'HIPOTESIS '!BJ146,0)+IF(plazo_cobroA=2,'HIPOTESIS '!BI146,0)+IF(plazo_cobroA=3,'HIPOTESIS '!BH146,0)),0) -> 0
B97: Saldo de clientes tipo A | C97: 0 | D97: =C97+'HIPOTESIS '!D146-D96 -> 0 | E97: =D97+'HIPOTESIS '!E146-E96 -> 0 | F97: =E97+'HIPOTESIS '!F146-F96 -> 0 | G97: =F97+'HIPOTESIS '!G146-G96 -> 0 | H97: =G97+'HIPOTESIS '!H146-H96 -> 0 | I97: =H97+'HIPOTESIS '!I146-I96 -> 0 | J97: =I97+'HIPOTESIS '!J146-J96 -> 0 | K97: =J97+'HIPOTESIS '!K146-K96 -> 0 | ... BK97: =BJ97+'HIPOTESIS '!BK146-BK96 -> 0
B98: Pagos a proveedores tipo A | C98: =IF(C95>=plazo_pagoA,(IF(plazo_pagoA=0,'HIPOTESIS '!C148,0)+IF(plazo_pagoA=1,'HIPOTESIS '!B148,0)+IF(plazo_pagoA=2,'HIPOTESIS '!A148,0)+IF(plazo_pagoA=3,#REF!,0)),0) -> 0 | D98: =IF(D95>=plazo_pagoA,(IF(plazo_pagoA=0,'HIPOTESIS '!D148,0)+IF(plazo_pagoA=1,'HIPOTESIS '!C148,0)+IF(plazo_pagoA=2,'HIPOTESIS '!B148,0)+IF(plazo_pagoA=3,'HIPOTESIS '!A148,0)),0) -> 0 | E98: =IF(E95>=plazo_pagoA,(IF(plazo_pagoA=0,'HIPOTESIS '!E148,0)+IF(plazo_pagoA=1,'HIPOTESIS '!D148,0)+IF(plazo_pagoA=2,'HIPOTESIS '!C148,0)+IF(plazo_pagoA=3,'HIPOTESIS '!B148,0)),0) -> 0 | F98: =IF(F95>=plazo_pagoA,(IF(plazo_pagoA=0,'HIPOTESIS '!F148,0)+IF(plazo_pagoA=1,'HIPOTESIS '!E148,0)+IF(plazo_pagoA=2,'HIPOTESIS '!D148,0)+IF(plazo_pagoA=3,'HIPOTESIS '!C148,0)),0) -> 0 | G98: =IF(G95>=plazo_pagoA,(IF(plazo_pagoA=0,'HIPOTESIS '!G148,0)+IF(plazo_pagoA=1,'HIPOTESIS '!F148,0)+IF(plazo_pagoA=2,'HIPOTESIS '!E148,0)+IF(plazo_pagoA=3,'HIPOTESIS '!D148,0)),0) -> 0 | H98: =IF(H95>=plazo_pagoA,(IF(plazo_pagoA=0,'HIPOTESIS '!H148,0)+IF(plazo_pagoA=1,'HIPOTESIS '!G148,0)+IF(plazo_pagoA=2,'HIPOTESIS '!F148,0)+IF(plazo_pagoA=3,'HIPOTESIS '!E148,0)),0) -> 0 | I98: =IF(I95>=plazo_pagoA,(IF(plazo_pagoA=0,'HIPOTESIS '!I148,0)+IF(plazo_pagoA=1,'HIPOTESIS '!H148,0)+IF(plazo_pagoA=2,'HIPOTESIS '!G148,0)+IF(plazo_pagoA=3,'HIPOTESIS '!F148,0)),0) -> 0 | J98: =IF(J95>=plazo_pagoA,(IF(plazo_pagoA=0,'HIPOTESIS '!J148,0)+IF(plazo_pagoA=1,'HIPOTESIS '!I148,0)+IF(plazo_pagoA=2,'HIPOTESIS '!H148,0)+IF(plazo_pagoA=3,'HIPOTESIS '!G148,0)),0) -> 0 | K98: =IF(K95>=plazo_pagoA,(IF(plazo_pagoA=0,'HIPOTESIS '!K148,0)+IF(plazo_pagoA=1,'HIPOTESIS '!J148,0)+IF(plazo_pagoA=2,'HIPOTESIS '!I148,0)+IF(plazo_pagoA=3,'HIPOTESIS '!H148,0)),0) -> 0 | ... BK98: =IF(BK95>=plazo_pagoA,(IF(plazo_pagoA=0,'HIPOTESIS '!BK148,0)+IF(plazo_pagoA=1,'HIPOTESIS '!BJ148,0)+IF(plazo_pagoA=2,'HIPOTESIS '!BI148,0)+IF(plazo_pagoA=3,'HIPOTESIS '!BH148,0)),0) -> 0
B99: Saldo de proveedores tipo A | C99: 0 | D99: =C99+'HIPOTESIS '!D148-D98 -> 0 | E99: =D99+'HIPOTESIS '!E148-E98 -> 0 | F99: =E99+'HIPOTESIS '!F148-F98 -> 0 | G99: =F99+'HIPOTESIS '!G148-G98 -> 0 | H99: =G99+'HIPOTESIS '!H148-H98 -> 0 | I99: =H99+'HIPOTESIS '!I148-I98 -> 0 | J99: =I99+'HIPOTESIS '!J148-J98 -> 0 | K99: =J99+'HIPOTESIS '!K148-K98 -> 0 | ... BK99: =BJ99+'HIPOTESIS '!BK148-BK98 -> 0
B100: Cobros de clientes tipo B | C100: =IF(C95>=plazo_cobroB,(IF(plazo_cobroB=0,'HIPOTESIS '!C153,0)+IF(plazo_cobroB=1,'HIPOTESIS '!B153,0)+IF(plazo_cobroB=2,'HIPOTESIS '!A153,0)+IF(plazo_cobroB=3,#REF!,0)),0) -> 0 | D100: =IF(D95>=plazo_cobroB,(IF(plazo_cobroB=0,'HIPOTESIS '!D153,0)+IF(plazo_cobroB=1,'HIPOTESIS '!C153,0)+IF(plazo_cobroB=2,'HIPOTESIS '!B153,0)+IF(plazo_cobroB=3,'HIPOTESIS '!A153,0)),0) -> 0 | E100: =IF(E95>=plazo_cobroB,(IF(plazo_cobroB=0,'HIPOTESIS '!E153,0)+IF(plazo_cobroB=1,'HIPOTESIS '!D153,0)+IF(plazo_cobroB=2,'HIPOTESIS '!C153,0)+IF(plazo_cobroB=3,'HIPOTESIS '!B153,0)),0) -> 0 | F100: =IF(F95>=plazo_cobroB,(IF(plazo_cobroB=0,'HIPOTESIS '!F153,0)+IF(plazo_cobroB=1,'HIPOTESIS '!E153,0)+IF(plazo_cobroB=2,'HIPOTESIS '!D153,0)+IF(plazo_cobroB=3,'HIPOTESIS '!C153,0)),0) -> 0 | G100: =IF(G95>=plazo_cobroB,(IF(plazo_cobroB=0,'HIPOTESIS '!G153,0)+IF(plazo_cobroB=1,'HIPOTESIS '!F153,0)+IF(plazo_cobroB=2,'HIPOTESIS '!E153,0)+IF(plazo_cobroB=3,'HIPOTESIS '!D153,0)),0) -> 0 | H100: =IF(H95>=plazo_cobroB,(IF(plazo_cobroB=0,'HIPOTESIS '!H153,0)+IF(plazo_cobroB=1,'HIPOTESIS '!G153,0)+IF(plazo_cobroB=2,'HIPOTESIS '!F153,0)+IF(plazo_cobroB=3,'HIPOTESIS '!E153,0)),0) -> 0 | I100: =IF(I95>=plazo_cobroB,(IF(plazo_cobroB=0,'HIPOTESIS '!I153,0)+IF(plazo_cobroB=1,'HIPOTESIS '!H153,0)+IF(plazo_cobroB=2,'HIPOTESIS '!G153,0)+IF(plazo_cobroB=3,'HIPOTESIS '!F153,0)),0) -> 0 | J100: =IF(J95>=plazo_cobroB,(IF(plazo_cobroB=0,'HIPOTESIS '!J153,0)+IF(plazo_cobroB=1,'HIPOTESIS '!I153,0)+IF(plazo_cobroB=2,'HIPOTESIS '!H153,0)+IF(plazo_cobroB=3,'HIPOTESIS '!G153,0)),0) -> 0 | K100: =IF(K95>=plazo_cobroB,(IF(plazo_cobroB=0,'HIPOTESIS '!K153,0)+IF(plazo_cobroB=1,'HIPOTESIS '!J153,0)+IF(plazo_cobroB=2,'HIPOTESIS '!I153,0)+IF(plazo_cobroB=3,'HIPOTESIS '!H153,0)),0) -> 0 | ... BK100: =IF(BK95>=plazo_cobroB,(IF(plazo_cobroB=0,'HIPOTESIS '!BK153,0)+IF(plazo_cobroB=1,'HIPOTESIS '!BJ153,0)+IF(plazo_cobroB=2,'HIPOTESIS '!BI153,0)+IF(plazo_cobroB=3,'HIPOTESIS '!BH153,0)),0) -> 0
B101: Saldo de clientes tipo B | C101: 0 | D101: =C101+'HIPOTESIS '!D153-D100 -> 0 | E101: =D101+'HIPOTESIS '!E153-E100 -> 0 | F101: =E101+'HIPOTESIS '!F153-F100 -> 0 | G101: =F101+'HIPOTESIS '!G153-G100 -> 0 | H101: =G101+'HIPOTESIS '!H153-H100 -> 0 | I101: =H101+'HIPOTESIS '!I153-I100 -> 0 | J101: =I101+'HIPOTESIS '!J153-J100 -> 0 | K101: =J101+'HIPOTESIS '!K153-K100 -> 0 | ... BK101: =BJ101+'HIPOTESIS '!BK153-BK100 -> 0
B102: Pagos a proveedores tipo B | C102: 0 | D102: =IF(D95>=plazo_pagoB,(IF(plazo_pagoB=0,'HIPOTESIS '!D155,0)+IF(plazo_pagoB=1,'HIPOTESIS '!C155,0)+IF(plazo_pagoB=2,'HIPOTESIS '!B155,0)+IF(plazo_pagoB=3,'HIPOTESIS '!A155,0)),0) -> 0 | E102: =IF(E95>=plazo_pagoB,(IF(plazo_pagoB=0,'HIPOTESIS '!E155,0)+IF(plazo_pagoB=1,'HIPOTESIS '!D155,0)+IF(plazo_pagoB=2,'HIPOTESIS '!C155,0)+IF(plazo_pagoB=3,'HIPOTESIS '!B155,0)),0) -> 0 | F102: =IF(F95>=plazo_pagoB,(IF(plazo_pagoB=0,'HIPOTESIS '!F155,0)+IF(plazo_pagoB=1,'HIPOTESIS '!E155,0)+IF(plazo_pagoB=2,'HIPOTESIS '!D155,0)+IF(plazo_pagoB=3,'HIPOTESIS '!C155,0)),0) -> 0 | G102: =IF(G95>=plazo_pagoB,(IF(plazo_pagoB=0,'HIPOTESIS '!G155,0)+IF(plazo_pagoB=1,'HIPOTESIS '!F155,0)+IF(plazo_pagoB=2,'HIPOTESIS '!E155,0)+IF(plazo_pagoB=3,'HIPOTESIS '!D155,0)),0) -> 0 | H102: =IF(H95>=plazo_pagoB,(IF(plazo_pagoB=0,'HIPOTESIS '!H155,0)+IF(plazo_pagoB=1,'HIPOTESIS '!G155,0)+IF(plazo_pagoB=2,'HIPOTESIS '!F155,0)+IF(plazo_pagoB=3,'HIPOTESIS '!E155,0)),0) -> 0 | I102: =IF(I95>=plazo_pagoB,(IF(plazo_pagoB=0,'HIPOTESIS '!I155,0)+IF(plazo_pagoB=1,'HIPOTESIS '!H155,0)+IF(plazo_pagoB=2,'HIPOTESIS '!G155,0)+IF(plazo_pagoB=3,'HIPOTESIS '!F155,0)),0) -> 0 | J102: =IF(J95>=plazo_pagoB,(IF(plazo_pagoB=0,'HIPOTESIS '!J155,0)+IF(plazo_pagoB=1,'HIPOTESIS '!I155,0)+IF(plazo_pagoB=2,'HIPOTESIS '!H155,0)+IF(plazo_pagoB=3,'HIPOTESIS '!G155,0)),0) -> 0 | K102: =IF(K95>=plazo_pagoB,(IF(plazo_pagoB=0,'HIPOTESIS '!K155,0)+IF(plazo_pagoB=1,'HIPOTESIS '!J155,0)+IF(plazo_pagoB=2,'HIPOTESIS '!I155,0)+IF(plazo_pagoB=3,'HIPOTESIS '!H155,0)),0) -> 0 | ... BK102: =IF(BK95>=plazo_pagoB,(IF(plazo_pagoB=0,'HIPOTESIS '!BK155,0)+IF(plazo_pagoB=1,'HIPOTESIS '!BJ155,0)+IF(plazo_pagoB=2,'HIPOTESIS '!BI155,0)+IF(plazo_pagoB=3,'HIPOTESIS '!BH155,0)),0) -> 0
B103: Saldo de proveedores tipo B | C103: 0 | D103: =C103+'HIPOTESIS '!D155-D102 -> 0 | E103: =D103+'HIPOTESIS '!E155-E102 -> 0 | F103: =E103+'HIPOTESIS '!F155-F102 -> 0 | G103: =F103+'HIPOTESIS '!G155-G102 -> 0 | H103: =G103+'HIPOTESIS '!H155-H102 -> 0 | I103: =H103+'HIPOTESIS '!I155-I102 -> 0 | J103: =I103+'HIPOTESIS '!J155-J102 -> 0 | K103: =J103+'HIPOTESIS '!K155-K102 -> 0 | ... BK103: =BJ103+'HIPOTESIS '!BK155-BK102 -> 0
B104: Cobros de clientes tipo C | C104: 0 | D104: =IF(D95>=plazo_cobroC,(IF(plazo_cobroC=0,'HIPOTESIS '!D160,0)+IF(plazo_cobroC=1,'HIPOTESIS '!C160,0)+IF(plazo_cobroC=2,'HIPOTESIS '!B160,0)+IF(plazo_cobroC=3,'HIPOTESIS '!A160,0)),0) -> 0 | E104: =IF(E95>=plazo_cobroC,(IF(plazo_cobroC=0,'HIPOTESIS '!E160,0)+IF(plazo_cobroC=1,'HIPOTESIS '!D160,0)+IF(plazo_cobroC=2,'HIPOTESIS '!C160,0)+IF(plazo_cobroC=3,'HIPOTESIS '!B160,0)),0) -> 0 | F104: =IF(F95>=plazo_cobroC,(IF(plazo_cobroC=0,'HIPOTESIS '!F160,0)+IF(plazo_cobroC=1,'HIPOTESIS '!E160,0)+IF(plazo_cobroC=2,'HIPOTESIS '!D160,0)+IF(plazo_cobroC=3,'HIPOTESIS '!C160,0)),0) -> 0 | G104: =IF(G95>=plazo_cobroC,(IF(plazo_cobroC=0,'HIPOTESIS '!G160,0)+IF(plazo_cobroC=1,'HIPOTESIS '!F160,0)+IF(plazo_cobroC=2,'HIPOTESIS '!E160,0)+IF(plazo_cobroC=3,'HIPOTESIS '!D160,0)),0) -> 0 | H104: =IF(H95>=plazo_cobroC,(IF(plazo_cobroC=0,'HIPOTESIS '!H160,0)+IF(plazo_cobroC=1,'HIPOTESIS '!G160,0)+IF(plazo_cobroC=2,'HIPOTESIS '!F160,0)+IF(plazo_cobroC=3,'HIPOTESIS '!E160,0)),0) -> 0 | I104: =IF(I95>=plazo_cobroC,(IF(plazo_cobroC=0,'HIPOTESIS '!I160,0)+IF(plazo_cobroC=1,'HIPOTESIS '!H160,0)+IF(plazo_cobroC=2,'HIPOTESIS '!G160,0)+IF(plazo_cobroC=3,'HIPOTESIS '!F160,0)),0) -> 0 | J104: =IF(J95>=plazo_cobroC,(IF(plazo_cobroC=0,'HIPOTESIS '!J160,0)+IF(plazo_cobroC=1,'HIPOTESIS '!I160,0)+IF(plazo_cobroC=2,'HIPOTESIS '!H160,0)+IF(plazo_cobroC=3,'HIPOTESIS '!G160,0)),0) -> 0 | K104: =IF(K95>=plazo_cobroC,(IF(plazo_cobroC=0,'HIPOTESIS '!K160,0)+IF(plazo_cobroC=1,'HIPOTESIS '!J160,0)+IF(plazo_cobroC=2,'HIPOTESIS '!I160,0)+IF(plazo_cobroC=3,'HIPOTESIS '!H160,0)),0) -> 0 | ... BK104: =IF(BK95>=plazo_cobroC,(IF(plazo_cobroC=0,'HIPOTESIS '!BK160,0)+IF(plazo_cobroC=1,'HIPOTESIS '!BJ160,0)+IF(plazo_cobroC=2,'HIPOTESIS '!BI160,0)+IF(plazo_cobroC=3,'HIPOTESIS '!BH160,0)),0) -> 0
B105: Saldo de clientes tipo C | C105: 0 | D105: =C105+'HIPOTESIS '!D160-D104 -> 0 | E105: =D105+'HIPOTESIS '!E160-E104 -> 0 | F105: =E105+'HIPOTESIS '!F160-F104 -> 0 | G105: =F105+'HIPOTESIS '!G160-G104 -> 0 | H105: =G105+'HIPOTESIS '!H160-H104 -> 0 | I105: =H105+'HIPOTESIS '!I160-I104 -> 0 | J105: =I105+'HIPOTESIS '!J160-J104 -> 0 | K105: =J105+'HIPOTESIS '!K160-K104 -> 0 | ... BK105: =BJ105+'HIPOTESIS '!BK160-BK104 -> 0
B106: Pagos a proveedores tipo C | C106: 0 | D106: =IF(D95>=plazo_pagoC,(IF(plazo_pagoC=0,'HIPOTESIS '!D162,0)+IF(plazo_pagoC=1,'HIPOTESIS '!C162,0)+IF(plazo_pagoC=2,'HIPOTESIS '!B162,0)+IF(plazo_pagoC=3,'HIPOTESIS '!A162,0)),0) -> 0 | E106: =IF(E95>=plazo_pagoC,(IF(plazo_pagoC=0,'HIPOTESIS '!E162,0)+IF(plazo_pagoC=1,'HIPOTESIS '!D162,0)+IF(plazo_pagoC=2,'HIPOTESIS '!C162,0)+IF(plazo_pagoC=3,'HIPOTESIS '!B162,0)),0) -> 0 | F106: =IF(F95>=plazo_pagoC,(IF(plazo_pagoC=0,'HIPOTESIS '!F162,0)+IF(plazo_pagoC=1,'HIPOTESIS '!E162,0)+IF(plazo_pagoC=2,'HIPOTESIS '!D162,0)+IF(plazo_pagoC=3,'HIPOTESIS '!C162,0)),0) -> 0 | G106: =IF(G95>=plazo_pagoC,(IF(plazo_pagoC=0,'HIPOTESIS '!G162,0)+IF(plazo_pagoC=1,'HIPOTESIS '!F162,0)+IF(plazo_pagoC=2,'HIPOTESIS '!E162,0)+IF(plazo_pagoC=3,'HIPOTESIS '!D162,0)),0) -> 0 | H106: =IF(H95>=plazo_pagoC,(IF(plazo_pagoC=0,'HIPOTESIS '!H162,0)+IF(plazo_pagoC=1,'HIPOTESIS '!G162,0)+IF(plazo_pagoC=2,'HIPOTESIS '!F162,0)+IF(plazo_pagoC=3,'HIPOTESIS '!E162,0)),0) -> 0 | I106: =IF(I95>=plazo_pagoC,(IF(plazo_pagoC=0,'HIPOTESIS '!I162,0)+IF(plazo_pagoC=1,'HIPOTESIS '!H162,0)+IF(plazo_pagoC=2,'HIPOTESIS '!G162,0)+IF(plazo_pagoC=3,'HIPOTESIS '!F162,0)),0) -> 0 | J106: =IF(J95>=plazo_pagoC,(IF(plazo_pagoC=0,'HIPOTESIS '!J162,0)+IF(plazo_pagoC=1,'HIPOTESIS '!I162,0)+IF(plazo_pagoC=2,'HIPOTESIS '!H162,0)+IF(plazo_pagoC=3,'HIPOTESIS '!G162,0)),0) -> 0 | K106: =IF(K95>=plazo_pagoC,(IF(plazo_pagoC=0,'HIPOTESIS '!K162,0)+IF(plazo_pagoC=1,'HIPOTESIS '!J162,0)+IF(plazo_pagoC=2,'HIPOTESIS '!I162,0)+IF(plazo_pagoC=3,'HIPOTESIS '!H162,0)),0) -> 0 | ... BK106: =IF(BK95>=plazo_pagoC,(IF(plazo_pagoC=0,'HIPOTESIS '!BK162,0)+IF(plazo_pagoC=1,'HIPOTESIS '!BJ162,0)+IF(plazo_pagoC=2,'HIPOTESIS '!BI162,0)+IF(plazo_pagoC=3,'HIPOTESIS '!BH162,0)),0) -> 0
...

Sheet RESULTADOS
B1: www.toolboardcanvas.com
A2: Parte III: RESULTADOS PREVISIONALES
AU3: =SUM(AN7:AU7) -> 0 | AW3: =AW15+AW16+AW18+AW21 -> 0 | AX3: =AW3/0.3 -> 0
C4: AÑOS | O4: MES 0 | P4: MESES AÑO 1 | AB4: MESES AÑO 2 | AN4: MESES AÑO 3 | AZ4: MESES AÑO 4 | BL4: MESES AÑO 5
A5: A | B5: CUENTA DE RESULTADOS (P&L) | C5: AÑO 0 | D5: % | E5: AÑO 1 | F5: % | G5: AÑO 2 | H5: % | I5: AÑO 3 | J5: % | K5: AÑO 4 | L5: % | M5: AÑO 5 | N5: % | O5: 0 | P5: 1 | Q5: 2 | R5: 3 | S5: 4 | T5: 5 | U5: 6 | V5: 7 | W5: 8 | X5: 9 | Y5: 10 | Z5: 11 | AA5: 12 | AB5: 13 | AC5: 14 | AD5: 15 | AE5: 16 | AF5: 17 | AG5: 18 | AH5: 19 | AI5: 20 | AJ5: 21 | AK5: 22 | AL5: 23 | AM5: 24 | AN5: 25 | AO5: 26 | AP5: 27 | AQ5: 28 | AR5: 29 | AS5: 30 | AT5: 31 | AU5: 32 | AV5: 33 | AW5: 34 | AX5: 35 | AY5: 36 | AZ5: 37 | BA5: 38 | BB5: 39 | BC5: 40 | BD5: 41 | BE5: 42 | BF5: 43 | BG5: 44 | BH5: 45 | BI5: 46 | BJ5: 47 | BK5: 48 | BL5: 49 | BM5: 50 | BN5: 51 | BO5: 52 | BP5: 53 | BQ5: 54 | BR5: 55 | BS5: 56 | BT5: 57 | BU5: 58 | BV5: 59 | BW5: 60
B6: INGRESOS | C6: =C7+C8 -> 0 | E6: =E7+E8 -> 0 | F6: =IFERROR(E6/E6,"-") -> - | G6: =G7+G8 -> 0 | H6: =IFERROR(G6/G6,"-") -> - | I6: =I7+I8 -> 0 | J6: =IFERROR(I6/I6,"-") -> - | K6: =K7+K8 -> 0 | L6: =IFERROR(K6/K6,"-") -> - | M6: =M7+M8 -> 0 | N6: =IFERROR(M6/M6,"-") -> - | O6: 0 | P6: =P7+P8 -> 0 | Q6: =Q7+Q8 -> 0 | R6: =R7+R8 -> 0 | S6: =S7+S8 -> 0 | T6: =T7+T8 -> 0 | U6: =U7+U8 -> 0 | V6: =V7+V8 -> 0 | W6: =W7+W8 -> 0 | ... BW6: =BW7+BW8 -> 0
B7: Ventas totales | C7: =O7 -> 0 | E7: =SUM(P7:AA7) -> 0 | G7: =SUM(AB7:AM7) -> 0 | I7: =SUM(AN7:AY7) -> 0 | K7: =SUM(AZ7:BK7) -> 0 | M7: =SUM(BL7:BW7) -> 0 | O7: 0 | P7: ='HIPOTESIS '!D146+'HIPOTESIS '!D153+'HIPOTESIS '!D160 -> 0 | Q7: ='HIPOTESIS '!E146+'HIPOTESIS '!E153+'HIPOTESIS '!E160 -> 0 | R7: ='HIPOTESIS '!F146+'HIPOTESIS '!F153+'HIPOTESIS '!F160 -> 0 | S7: ='HIPOTESIS '!G146+'HIPOTESIS '!G153+'HIPOTESIS '!G160 -> 0 | T7: ='HIPOTESIS '!H146+'HIPOTESIS '!H153+'HIPOTESIS '!H160 -> 0 | U7: ='HIPOTESIS '!I146+'HIPOTESIS '!I153+'HIPOTESIS '!I160 -> 0 | V7: ='HIPOTESIS '!J146+'HIPOTESIS '!J153+'HIPOTESIS '!J160 -> 0 | W7: ='HIPOTESIS '!K146+'HIPOTESIS '!K153+'HIPOTESIS '!K160 -> 0 | ... BW7: ='HIPOTESIS '!BK146+'HIPOTESIS '!BK153+'HIPOTESIS '!BK160 -> 0
B8: Subvenciones de explotación | C8: =O8 -> 0 | E8: =SUM(P8:AA8) -> 0 | G8: =SUM(AB8:AM8) -> 0 | I8: =SUM(AN8:AY8) -> 0 | K8: =SUM(AZ8:BK8) -> 0 | M8: =SUM(BL8:BW8) -> 0 | O8: 0 | P8: ='HIPOTESIS '!D164 -> 0 | Q8: ='HIPOTESIS '!E164 -> 0 | R8: ='HIPOTESIS '!F164 -> 0 | S8: ='HIPOTESIS '!G164 -> 0 | T8: ='HIPOTESIS '!H164 -> 0 | U8: ='HIPOTESIS '!I164 -> 0 | V8: ='HIPOTESIS '!J164 -> 0 | W8: ='HIPOTESIS '!K164 -> 0 | ... BW8: ='HIPOTESIS '!BK164 -> 0
B10: COSTES DE LAS VENTAS
B11: Costes variables de las ventas | C11: =O11 -> 0 | E11: =SUM(P11:AA11) -> 0 | F11: =IFERROR((E11)/E7,"-") -> - | G11: =SUM(AB11:AM11) -> 0 | H11: =IFERROR((G11)/G7,"-") -> - | I11: =SUM(AN11:AY11) -> 0 | J11: =IFERROR((I11)/I7,"-") -> - | K11: =SUM(AZ11:BK11) -> 0 | L11: =IFERROR((K11)/K7,"-") -> - | M11: =SUM(BL11:BW11) -> 0 | N11: =IFERROR((M11)/M7,"-") -> - | O11: 0 | P11: ='HIPOTESIS '!D148+'HIPOTESIS '!D155+'HIPOTESIS '!D162 -> 0 | Q11: ='HIPOTESIS '!E148+'HIPOTESIS '!E155+'HIPOTESIS '!E162 -> 0 | R11: ='HIPOTESIS '!F148+'HIPOTESIS '!F155+'HIPOTESIS '!F162 -> 0 | S11: ='HIPOTESIS '!G148+'HIPOTESIS '!G155+'HIPOTESIS '!G162 -> 0 | T11: ='HIPOTESIS '!H148+'HIPOTESIS '!H155+'HIPOTESIS '!H162 -> 0 | U11: ='HIPOTESIS '!I148+'HIPOTESIS '!I155+'HIPOTESIS '!I162 -> 0 | V11: ='HIPOTESIS '!J148+'HIPOTESIS '!J155+'HIPOTESIS '!J162 -> 0 | W11: ='HIPOTESIS '!K148+'HIPOTESIS '!K155+'HIPOTESIS '!K162 -> 0 | ... BW11: ='HIPOTESIS '!BK148+'HIPOTESIS '!BK155+'HIPOTESIS '!BK162 -> 0
B12: Margen comercial | C12: =C7+C8-C11 -> 0 | E12: =E7+E8-E11 -> 0 | F12: =IFERROR(E12/E6,"-") -> - | G12: =G7+G8-G11 -> 0 | H12: =IFERROR(G12/G6,"-") -> - | I12: =I7+I8-I11 -> 0 | J12: =IFERROR(I12/I6,"-") -> - | K12: =K7+K8-K11 -> 0 | L12: =IFERROR(K12/K6,"-") -> - | M12: =M7+M8-M11 -> 0 | N12: =IFERROR(M12/M6,"-") -> - | O12: =O7+O8-O11 -> 0 | P12: =P7+P8-P11 -> 0 | Q12: =Q7+Q8-Q11 -> 0 | R12: =R7+R8-R11 -> 0 | S12: =S7+S8-S11 -> 0 | T12: =T7+T8-T11 -> 0 | U12: =U7+U8-U11 -> 0 | V12: =V7+V8-V11 -> 0 | ... BW12: =BW7+BW8-BW11 -> 0
B13: OTROS INGRESOS Y GASTOS
B14: Ingresos por trabajos para el propio activo | C14: =O14 -> 0 | E14: =SUM(P14:AA14) -> 0 | G14: =SUM(AB14:AM14) -> 0 | I14: =SUM(AN14:AY14) -> 0 | K14: =SUM(AZ14:BK14) -> 0 | M14: =SUM(BL14:BW14) -> 0 | O14: =IF(AND(O5>=inicio_trabaj_activacion1,O5<=final_trabaj_activacion1),imp_mensual_trabajo_activ1,0)+IF(AND(O5>=inicio_trabaj_activacion2,O5<=final_trabaj_activacion2),imp_mensual_trabajo_activ2,0) -> 0 | P14: =IF(AND(P5>=inicio_trabaj_activacion1,P5<=final_trabaj_activacion1),imp_mensual_trabajo_activ1,0)+IF(AND(P5>=inicio_trabaj_activacion2,P5<=final_trabaj_activacion2),imp_mensual_trabajo_activ2,0) -> 0 | Q14: =IF(AND(Q5>=inicio_trabaj_activacion1,Q5<=final_trabaj_activacion1),imp_mensual_trabajo_activ1,0)+IF(AND(Q5>=inicio_trabaj_activacion2,Q5<=final_trabaj_activacion2),imp_mensual_trabajo_activ2,0) -> 0 | R14: =IF(AND(R5>=inicio_trabaj_activacion1,R5<=final_trabaj_activacion1),imp_mensual_trabajo_activ1,0)+IF(AND(R5>=inicio_trabaj_activacion2,R5<=final_trabaj_activacion2),imp_mensual_trabajo_activ2,0) -> 0 | S14: =IF(AND(S5>=inicio_trabaj_activacion1,S5<=final_trabaj_activacion1),imp_mensual_trabajo_activ1,0)+IF(AND(S5>=inicio_trabaj_activacion2,S5<=final_trabaj_activacion2),imp_mensual_trabajo_activ2,0) -> 0 | T14: =IF(AND(T5>=inicio_trabaj_activacion1,T5<=final_trabaj_activacion1),imp_mensual_trabajo_activ1,0)+IF(AND(T5>=inicio_trabaj_activacion2,T5<=final_trabaj_activacion2),imp_mensual_trabajo_activ2,0) -> 0 | U14: =IF(AND(U5>=inicio_trabaj_activacion1,U5<=final_trabaj_activacion1),imp_mensual_trabajo_activ1,0)+IF(AND(U5>=inicio_trabaj_activacion2,U5<=final_trabaj_activacion2),imp_mensual_trabajo_activ2,0) -> 0 | V14: =IF(AND(V5>=inicio_trabaj_activacion1,V5<=final_trabaj_activacion1),imp_mensual_trabajo_activ1,0)+IF(AND(V5>=inicio_trabaj_activacion2,V5<=final_trabaj_activacion2),imp_mensual_trabajo_activ2,0) -> 0 | ... BW14: =IF(AND(BW5>=inicio_trabaj_activacion1,BW5<=final_trabaj_activacion1),imp_mensual_trabajo_activ1,0)+IF(AND(BW5>=inicio_trabaj_activacion2,BW5<=final_trabaj_activacion2),imp_mensual_trabajo_activ2,0) -> 0
B15: Gastos fijos por servicios exteriores | C15: =O15 -> 0 | E15: =SUM(P15:AA15) -> 0 | G15: =SUM(AB15:AM15) -> 0 | I15: =SUM(AN15:AY15) -> 0 | K15: =SUM(AZ15:BK15) -> 0 | M15: =SUM(BL15:BW15) -> 0 | O15: 0 | P15: ='HIPOTESIS '!$C$86/12 -> 0 | Q15: ='HIPOTESIS '!$C$86/12 -> 0 | R15: ='HIPOTESIS '!$C$86/12 -> 0 | S15: ='HIPOTESIS '!$C$86/12 -> 0 | T15: ='HIPOTESIS '!$C$86/12 -> 0 | U15: ='HIPOTESIS '!$C$86/12 -> 0 | V15: ='HIPOTESIS '!$C$86/12 -> 0 | W15: ='HIPOTESIS '!$C$86/12 -> 0 | ... AA15: ='HIPOTESIS '!$C$86/12 -> 0 | AB15: ='HIPOTESIS '!$F$86/12 -> 0 | AC15: ='HIPOTESIS '!$F$86/12 -> 0 | AD15: ='HIPOTESIS '!$F$86/12 -> 0 | AE15: ='HIPOTESIS '!$F$86/12 -> 0 | AF15: ='HIPOTESIS '!$F$86/12 -> 0 | AG15: ='HIPOTESIS '!$F$86/12 -> 0 | AH15: ='HIPOTESIS '!$F$86/12 -> 0 | AI15: ='HIPOTESIS '!$F$86/12 -> 0 | ... AM15: ='HIPOTESIS '!$F$86/12 -> 0 | AN15: ='HIPOTESIS '!$I$86/12 -> 0 | AO15: ='HIPOTESIS '!$I$86/12 -> 0 | AP15: ='HIPOTESIS '!$I$86/12 -> 0 | AQ15: ='HIPOTESIS '!$I$86/12 -> 0 | AR15: ='HIPOTESIS '!$I$86/12 -> 0 | AS15: ='HIPOTESIS '!$I$86/12 -> 0 | AT15: ='HIPOTESIS '!$I$86/12 -> 0 | AU15: ='HIPOTESIS '!$I$86/12 -> 0 | ... AY15: ='HIPOTESIS '!$I$86/12 -> 0 | AZ15: ='HIPOTESIS '!$L$86/12 -> 0 | BA15: ='HIPOTESIS '!$L$86/12 -> 0 | BB15: ='HIPOTESIS '!$L$86/12 -> 0 | BC15: ='HIPOTESIS '!$L$86/12 -> 0 | BD15: ='HIPOTESIS '!$L$86/12 -> 0 | BE15: ='HIPOTESIS '!$L$86/12 -> 0 | BF15: ='HIPOTESIS '!$L$86/12 -> 0 | BG15: ='HIPOTESIS '!$L$86/12 -> 0 | ... BK15: ='HIPOTESIS '!$L$86/12 -> 0 | BL15: ='HIPOTESIS '!$O$86/12 -> 0 | BM15: ='HIPOTESIS '!$O$86/12 -> 0 | BN15: ='HIPOTESIS '!$O$86/12 -> 0 | BO15: ='HIPOTESIS '!$O$86/12 -> 0 | BP15: ='HIPOTESIS '!$O$86/12 -> 0 | BQ15: ='HIPOTESIS '!$O$86/12 -> 0 | BR15: ='HIPOTESIS '!$O$86/12 -> 0 | BS15: ='HIPOTESIS '!$O$86/12 -> 0 | ... BW15: ='HIPOTESIS '!$O$86/12 -> 0
B16: Gastos fijos de nómina | C16: =O16 -> 0 | E16: =SUM(P16:AA16) -> 0 | G16: =SUM(AB16:AM16) -> 0 | I16: =SUM(AN16:AY16) -> 0 | K16: =SUM(AZ16:BK16) -> 0 | M16: =SUM(BL16:BW16) -> 0 | O16: ='C'!C167 -> 0 | P16: ='C'!D167 -> 0 | Q16: ='C'!E167 -> 0 | R16: ='C'!F167 -> 0 | S16: ='C'!G167 -> 0 | T16: ='C'!H167 -> 0 | U16: ='C'!I167 -> 0 | V16: ='C'!J167 -> 0 | ... BW16: ='C'!BK167 -> 0
B17: Margen EBITDA | C17: =C12+C14-C15-C16 -> 0 | E17: =E12+E14-E15-E16 -> 0 | F17: =IFERROR(E17/E6,"-") -> - | G17: =G12+G14-G15-G16 -> 0 | H17: =IFERROR(G17/G6,"-") -> - | I17: =I12+I14-I15-I16 -> 0 | J17: =IFERROR(I17/I6,"-") -> - | K17: =K12+K14-K15-K16 -> 0 | L17: =IFERROR(K17/K6,"-") -> - | M17: =M12+M14-M15-M16 -> 0 | N17: =IFERROR(M17/M6,"-") -> - | O17: =O12+O14-O15-O16 -> 0 | P17: =P12+P14-P15-P16 -> 0 | Q17: =Q12+Q14-Q15-Q16 -> 0 | R17: =R12+R14-R15-R16 -> 0 | S17: =S12+S14-S15-S16 -> 0 | T17: =T12+T14-T15-T16 -> 0 | U17: =U12+U14-U15-U16 -> 0 | V17: =V12+V14-V15-V16 -> 0 | ... BW17: =BW12+BW14-BW15-BW16 -> 0
B18: Amortizaciones y depreciaciones | C18: =O18 -> 0 | E18: =SUM(P18:AA18) -> 0 | G18: =SUM(AB18:AM18) -> 0 | I18: =SUM(AN18:AY18) -> 0 | K18: =SUM(AZ18:BK18) -> 0 | M18: =SUM(BL18:BW18) -> 0 | O18: ='C'!C23 -> 0 | P18: ='C'!D23 -> 0 | Q18: ='C'!E23 -> 0 | R18: ='C'!F23 -> 0 | S18: ='C'!G23 -> 0 | T18: ='C'!H23 -> 0 | U18: ='C'!I23 -> 0 | V18: ='C'!J23 -> 0 | ... BW18: ='C'!BK23 -> 0
B19: Imputación de subvenciones de capital | C19: =O19 -> 0 | E19: =SUM(P19:AA19) -> 0 | G19: =SUM(AB19:AM19) -> 0 | I19: =SUM(AN19:AY19) -> 0 | K19: =SUM(AZ19:BK19) -> 0 | M19: =SUM(BL19:BW19) -> 0 | O19: ='C'!C29 -> 0 | P19: ='C'!D29 -> 0 | Q19: ='C'!E29 -> 0 | R19: ='C'!F29 -> 0 | S19: ='C'!G29 -> 0 | T19: ='C'!H29 -> 0 | U19: ='C'!I29 -> 0 | V19: ='C'!J29 -> 0 | ... BW19: ='C'!BK29 -> 0
B20: Margen EBIT | C20: =C17-C18+C19 -> 0 | E20: =E17-E18+E19 -> 0 | F20: =IFERROR(E20/E6,"-") -> - | G20: =G17-G18+G19 -> 0 | H20: =IFERROR(G20/G6,"-") -> - | I20: =I17-I18+I19 -> 0 | J20: =IFERROR(I20/I6,"-") -> - | K20: =K17-K18+K19 -> 0 | L20: =IFERROR(K20/K6,"-") -> - | M20: =M17-M18+M19 -> 0 | N20: =IFERROR(M20/M6,"-") -> - | O20: =O17-O18+O19 -> 0 | P20: =P17-P18+P19 -> 0 | Q20: =Q17-Q18+Q19 -> 0 | R20: =R17-R18+R19 -> 0 | S20: =S17-S18+S19 -> 0 | T20: =T17-T18+T19 -> 0 | U20: =U17-U18+U19 -> 0 | V20: =V17-V18+V19 -> 0 | ... BW20: =BW17-BW18+BW19 -> 0
B21: Resultado financiero (gastos menos ingresos financieros) | C21: =O21 -> 0 | E21: =SUM(P21:AA21) -> 0 | G21: =SUM(AB21:AM21) -> 0 | I21: =SUM(AN21:AY21) -> 0 | K21: =SUM(AZ21:BK21) -> 0 | M21: =SUM(BL21:BW21) -> 0 | O21: ='C'!C73+'C'!C82 -> 0 | P21: ='C'!D73+'C'!D82+'HIPOTESIS '!$D70/12*O57+'C'!D89 -> 0 | Q21: ='C'!E73+'C'!E82+'HIPOTESIS '!$D70/12*P57+'C'!E89 -> 0 | R21: ='C'!F73+'C'!F82+'HIPOTESIS '!$D70/12*Q57+'C'!F89 -> 0 | S21: ='C'!G73+'C'!G82+'HIPOTESIS '!$D70/12*R57+'C'!G89 -> 0 | T21: ='C'!H73+'C'!H82+'HIPOTESIS '!$D70/12*S57+'C'!H89 -> 0 | U21: ='C'!I73+'C'!I82+'HIPOTESIS '!$D70/12*T57+'C'!I89 -> 0 | V21: ='C'!J73+'C'!J82+'HIPOTESIS '!$D70/12*U57+'C'!J89 -> 0 | W21: ='C'!K73+'C'!K82+'HIPOTESIS '!$D70/12*V57+'C'!K89 -> 0 | ... BW21: ='C'!BK73+'C'!BK82+'HIPOTESIS '!$D70/12*BV57+'C'!BK89 -> 0
B22: Margen EBT | C22: =C20-C21 -> 0 | E22: =E20-E21 -> 0 | F22: =IFERROR(E22/E6,"-") -> - | G22: =G20-G21 -> 0 | H22: =IFERROR(G22/G6,"-") -> - | I22: =I20-I21 -> 0 | J22: =IFERROR(I22/I6,"-") -> - | K22: =K20-K21 -> 0 | L22: =IFERROR(K22/K6,"-") -> - | M22: =M20-M21 -> 0 | N22: =IFERROR(M22/M6,"-") -> - | O22: =O20-O21 -> 0 | P22: =P20-P21 -> 0 | Q22: =Q20-Q21 -> 0 | R22: =R20-R21 -> 0 | S22: =S20-S21 -> 0 | T22: =T20-T21 -> 0 | U22: =U20-U21 -> 0 | V22: =V20-V21 -> 0 | ... BW22: =BW20-BW21 -> 0
B23: Impuesto de Sociedades | C23: =O23 -> 0 | E23: =SUM(P23:AA23) -> 0 | G23: =SUM(AB23:AM23) -> 0 | I23: =SUM(AN23:AY23) -> 0 | K23: =SUM(AZ23:BK23) -> 0 | M23: =SUM(BL23:BW23) -> 0 | O23: ='C'!C267 -> 0 | P23: ='C'!D267 -> 0 | Q23: ='C'!E267 -> 0 | R23: ='C'!F267 -> 0 | S23: ='C'!G267 -> 0 | T23: ='C'!H267 -> 0 | U23: ='C'!I267 -> 0 | V23: ='C'!J267 -> 0 | ... BW23: ='C'!BK267 -> 0
B24: RESULTADO (Margen de beneficio o pérdida) | C24: =C22-C23 -> 0 | E24: =E22-E23 -> 0 | F24: =IFERROR(E24/E6,"-") -> - | G24: =G22-G23 -> 0 | H24: =IFERROR(G24/G6,"-") -> - | I24: =I22-I23 -> 0 | J24: =IFERROR(I24/I6,"-") -> - | K24: =K22-K23 -> 0 | L24: =IFERROR(K24/K6,"-") -> - | M24: =M22-M23 -> 0 | N24: =IFERROR(M24/M6,"-") -> - | O24: =O22-O23 -> 0 | P24: =P22-P23 -> 0 | Q24: =Q22-Q23 -> 0 | R24: =R22-R23 -> 0 | S24: =S22-S23 -> 0 | T24: =T22-T23 -> 0 | U24: =U22-U23 -> 0 | V24: =V22-V23 -> 0 | ... BW24: =BW22-BW23 -> 0
B25: (RESULTADO acumulado en fondos propios) | C25: =C24 -> 0 | E25: =C25+E24 -> 0 | G25: =E25+G24 -> 0 | I25: =G25+I24 -> 0 | K25: =I25+K24 -> 0 | M25: =K25+M24 -> 0 | O25: =O24 -> 0 | P25: =O25+P24 -> 0 | Q25: =P25+Q24 -> 0 | R25: =Q25+R24 -> 0 | S25: =R25+S24 -> 0 | T25: =S25+T24 -> 0 | U25: =T25+U24 -> 0 | V25: =U25+V24 -> 0 | W25: =V25+W24 -> 0 | ... BW25: =BV25+BW24 -> 0
C26: =IF(OR(E14>E16,G14>G16,I14>I16,K14>K16,M14>M16), "¡Cuidado!. Los tabajos para el propio activo en un año (ingreso por menos gasto) no pueden ser superiores a la nómina de ese año pues se deben ejecutar internamente. ¡Revisa los datos para obtener una proyección realista!", "-") -> -
C28: AÑOS | O28: MES 0 | P28: MESES AÑO 1 | AB28: MESES AÑO 2 | AN28: MESES AÑO 3 | AZ28: MESES AÑO 4 | BL28: MESES AÑO 5
A29: B | B29: FLUJO DE TESORERÍA (Cash Flow) | C29: AÑO 0 | D29: % | E29: AÑO 1 | F29: % | G29: AÑO 2 | H29: % | I29: AÑO 3 | J29: % | K29: AÑO 4 | L29: % | M29: AÑO 5 | N29: % | O29: 0 | P29: 1 | Q29: 2 | R29: 3 | S29: 4 | T29: 5 | U29: 6 | V29: 7 | W29: 8 | X29: 9 | Y29: 10 | Z29: 11 | AA29: 12 | AB29: 13 | AC29: 14 | AD29: 15 | AE29: 16 | AF29: 17 | AG29: 18 | AH29: 19 | AI29: 20 | AJ29: 21 | AK29: 22 | AL29: 23 | AM29: 24 | AN29: 25 | AO29: 26 | AP29: 27 | AQ29: 28 | AR29: 29 | AS29: 30 | AT29: 31 | AU29: 32 | AV29: 33 | AW29: 34 | AX29: 35 | AY29: 36 | AZ29: 37 | BA29: 38 | BB29: 39 | BC29: 40 | BD29: 41 | BE29: 42 | BF29: 43 | BG29: 44 | BH29: 45 | BI29: 46 | BJ29: 47 | BK29: 48 | BL29: 49 | BM29: 50 | BN29: 51 | BO29: 52 | BP29: 53 | BQ29: 54 | BR29: 55 | BS29: 56 | BT29: 57 | BU29: 58 | BV29: 59 | BW29: 60
B30: OPERACIONES
B31: Cobros de clientes | C31: =O31 -> 0 | E31: =SUM(P31:AA31) -> 0 | G31: =SUM(AB31:AM31) -> 0 | I31: =SUM(AN31:AY31) -> 0 | K31: =SUM(AZ31:BK31) -> 0 | M31: =SUM(BL31:BW31) -> 0 | O31: ='C'!C96*(1+IVA_ventas)+'C'!C100*(1+IVA_ventas)+'C'!C104*(1+IVA_ventas) -> 0 | P31: ='C'!D96*(1+IVA_ventas)+'C'!D100*(1+IVA_ventas)+'C'!D104*(1+IVA_ventas) -> 0 | Q31: ='C'!E96*(1+IVA_ventas)+'C'!E100*(1+IVA_ventas)+'C'!E104*(1+IVA_ventas) -> 0 | R31: ='C'!F96*(1+IVA_ventas)+'C'!F100*(1+IVA_ventas)+'C'!F104*(1+IVA_ventas) -> 0 | S31: ='C'!G96*(1+IVA_ventas)+'C'!G100*(1+IVA_ventas)+'C'!G104*(1+IVA_ventas) -> 0 | T31: ='C'!H96*(1+IVA_ventas)+'C'!H100*(1+IVA_ventas)+'C'!H104*(1+IVA_ventas) -> 0 | U31: ='C'!I96*(1+IVA_ventas)+'C'!I100*(1+IVA_ventas)+'C'!I104*(1+IVA_ventas) -> 0 | V31: ='C'!J96*(1+IVA_ventas)+'C'!J100*(1+IVA_ventas)+'C'!J104*(1+IVA_ventas) -> 0 | ... BW31: ='C'!BK96*(1+IVA_ventas)+'C'!BK100*(1+IVA_ventas)+'C'!BK104*(1+IVA_ventas) -> 0
B32: Cobro de subvenciones de explotación | C32: =O32 -> 0 | E32: =SUM(P32:AA32) -> 0 | G32: =SUM(AB32:AM32) -> 0 | I32: =SUM(AN32:AY32) -> 0 | K32: =SUM(AZ32:BK32) -> 0 | M32: =SUM(BL32:BW32) -> 0 | O32: =O8 -> 0 | P32: =P8 -> 0 | Q32: =Q8 -> 0 | R32: =R8 -> 0 | S32: =S8 -> 0 | T32: =T8 -> 0 | U32: =U8 -> 0 | V32: =V8 -> 0 | ... BW32: =BW8 -> 0
B33: Pagos a proveedores (coste de las ventas) | C33: =O33 -> 0 | E33: =SUM(P33:AA33) -> 0 | G33: =SUM(AB33:AM33) -> 0 | I33: =SUM(AN33:AY33) -> 0 | K33: =SUM(AZ33:BK33) -> 0 | M33: =SUM(BL33:BW33) -> 0 | O33: =-'C'!C98*(1+IVA_compras)-'C'!C102*(1+IVA_compras)-'C'!C106*(1+IVA_compras) -> 0 | P33: =-'C'!D98*(1+IVA_compras)-'C'!D102*(1+IVA_compras)-'C'!D106*(1+IVA_compras) -> 0 | Q33: =-'C'!E98*(1+IVA_compras)-'C'!E102*(1+IVA_compras)-'C'!E106*(1+IVA_compras) -> 0 | R33: =-'C'!F98*(1+IVA_compras)-'C'!F102*(1+IVA_compras)-'C'!F106*(1+IVA_compras) -> 0 | S33: =-'C'!G98*(1+IVA_compras)-'C'!G102*(1+IVA_compras)-'C'!G106*(1+IVA_compras) -> 0 | T33: =-'C'!H98*(1+IVA_compras)-'C'!H102*(1+IVA_compras)-'C'!H106*(1+IVA_compras) -> 0 | U33: =-'C'!I98*(1+IVA_compras)-'C'!I102*(1+IVA_compras)-'C'!I106*(1+IVA_compras) -> 0 | V33: =-'C'!J98*(1+IVA_compras)-'C'!J102*(1+IVA_compras)-'C'!J106*(1+IVA_compras) -> 0 | ... BW33: =-'C'!BK98*(1+IVA_compras)-'C'!BK102*(1+IVA_compras)-'C'!BK106*(1+IVA_compras) -> 0
B34: Pagos gastos fijos por servicios exteriores (al contado) | C34: =O34 -> 0 | E34: =SUM(P34:AA34) -> 0 | G34: =SUM(AB34:AM34) -> 0 | I34: =SUM(AN34:AY34) -> 0 | K34: =SUM(AZ34:BK34) -> 0 | M34: =SUM(BL34:BW34) -> 0 | O34: =-O15*(1+IVA_compras) -> 0 | P34: =-P15*(1+IVA_compras) -> 0 | Q34: =-Q15*(1+IVA_compras) -> 0 | R34: =-R15*(1+IVA_compras) -> 0 | S34: =-S15*(1+IVA_compras) -> 0 | T34: =-T15*(1+IVA_compras) -> 0 | U34: =-U15*(1+IVA_compras) -> 0 | V34: =-V15*(1+IVA_compras) -> 0 | ... BW34: =-BW15*(1+IVA_compras) -> 0
B35: Pago al contado de la nómina | C35: =O35 -> 0 | E35: =SUM(P35:AA35) -> 0 | G35: =SUM(AB35:AM35) -> 0 | I35: =SUM(AN35:AY35) -> 0 | K35: =SUM(AZ35:BK35) -> 0 | M35: =SUM(BL35:BW35) -> 0 | O35: =-'C'!C203 -> 0 | P35: =-'C'!D203 -> 0 | Q35: =-'C'!E203 -> 0 | R35: =-'C'!F203 -> 0 | S35: =-'C'!G203 -> 0 | T35: =-'C'!H203 -> 0 | U35: =-'C'!I203 -> 0 | V35: =-'C'!J203 -> 0 | ... BW35: =-'C'!BK203 -> 0
B36: Pago del seguro social a TGSS | C36: =O36 -> 0 | E36: =SUM(P36:AA36) -> 0 | G36: =SUM(AB36:AM36) -> 0 | I36: =SUM(AN36:AY36) -> 0 | K36: =SUM(AZ36:BK36) -> 0 | M36: =SUM(BL36:BW36) -> 0 | O36: =-'C'!C252 -> 0 | P36: =-'C'!D252 -> 0 | Q36: =-'C'!E252 -> 0 | R36: =-'C'!F252 -> 0 | S36: =-'C'!G252 -> 0 | T36: =-'C'!H252 -> 0 | U36: =-'C'!I252 -> 0 | V36: =-'C'!J252 -> 0 | ... BW36: =-'C'!BK252 -> 0
B37: Pago intereses préstamos (al contado) + póliza | C37: =O37 -> 0 | E37: =SUM(P37:AA37) -> 0 | G37: =SUM(AB37:AM37) -> 0 | I37: =SUM(AN37:AY37) -> 0 | K37: =SUM(AZ37:BK37) -> 0 | M37: =SUM(BL37:BW37) -> 0 | O37: =-O21 -> 0 | P37: =-P21 -> 0 | Q37: =-Q21 -> 0 | R37: =-R21 -> 0 | S37: =-S21 -> 0 | T37: =-T21 -> 0 | U37: =-U21 -> 0 | V37: =-V21 -> 0 | ... BW37: =-BW21 -> 0
B38: Pago de las retenciones a hacienda (IRPF) | C38: =O38 -> 0 | E38: =SUM(P38:AA38) -> 0 | G38: =SUM(AB38:AM38) -> 0 | I38: =SUM(AN38:AY38) -> 0 | K38: =SUM(AZ38:BK38) -> 0 | M38: =SUM(BL38:BW38) -> 0 | O38: =-'C'!C247 -> 0 | P38: =-'C'!D247 -> 0 | Q38: =-'C'!E247 -> 0 | R38: =-'C'!F247 -> 0 | S38: =-'C'!G247 -> 0 | T38: =-'C'!H247 -> 0 | U38: =-'C'!I247 -> 0 | V38: =-'C'!J247 -> 0 | ... BW38: =-'C'!BK247 -> 0
B39: Pago del IVA a hacienda | C39: =O39 -> 0 | E39: =SUM(P39:AA39) -> 0 | G39: =SUM(AB39:AM39) -> 0 | I39: =SUM(AN39:AY39) -> 0 | K39: =SUM(AZ39:BK39) -> 0 | M39: =SUM(BL39:BW39) -> 0 | O39: =-'C'!C259 -> 0 | P39: =-'C'!D259 -> 0 | Q39: =-'C'!E259 -> 0 | R39: =-'C'!F259 -> 0 | S39: =-'C'!G259 -> 0 | T39: =-'C'!H259 -> 0 | U39: =-'C'!I259 -> 0 | V39: =-'C'!J259 -> 0 | ... BW39: =-'C'!BK259 -> 0
B40: Pago del IS a hacienda (del mes anterior) | C40: =O40 -> 0 | E40: =SUM(P40:AA40) -> 0 | G40: =SUM(AB40:AM40) -> 0 | I40: =SUM(AN40:AY40) -> 0 | K40: =SUM(AZ40:BK40) -> 0 | M40: =SUM(BL40:BW40) -> 0 | O40: 0 | P40: =-O23 -> 0 | Q40: =-P23 -> 0 | R40: =-Q23 -> 0 | S40: =-R23 -> 0 | T40: =-S23 -> 0 | U40: =-T23 -> 0 | V40: =-U23 -> 0 | W40: =-V23 -> 0 | ... BW40: =-BV23 -> 0
B41: CF operaciones | C41: =C31+C32-C33-C34-C35-C37-C40-C39 -> 0 | E41: =SUM(E31:E40) -> 0 | F41: =IFERROR(E41/E56,"-") -> 0 | G41: =SUM(G31:G40) -> 0 | H41: =IFERROR(G41/G56,"-") -> 0 | I41: =SUM(I31:I40) -> 0 | J41: =IFERROR(I41/I56,"-") -> 0 | K41: =SUM(K31:K40) -> 0 | L41: =IFERROR(K41/K56,"-") -> 0 | M41: =SUM(M31:M40) -> 0 | N41: =IFERROR(M41/M56,"-") -> 0 | O41: =SUM(O31:O40) -> 0 | P41: =SUM(P31:P40) -> 0 | Q41: =SUM(Q31:Q40) -> 0 | R41: =SUM(R31:R40) -> 0 | S41: =SUM(S31:S40) -> 0 | T41: =SUM(T31:T40) -> 0 | U41: =SUM(U31:U40) -> 0 | V41: =SUM(V31:V40) -> 0 | ... BW41: =SUM(BW31:BW40) -> 0
B42: INVERSIONES
B43: Pago de inversiones | C43: =O43 -> 0 | E43: =SUM(P43:AA43) -> 0 | G43: =SUM(AB43:AM43) -> 0 | I43: =SUM(AN43:AY43) -> 0 | K43: =SUM(AZ43:BK43) -> 0 | M43: =SUM(BL43:BW43) -> 0 | O43: =-(IF(O29=inicio_inv1,imp_inv1*(1+IVA_inversiones),0)+IF(O29=inicio_inv2,imp_inv2*(1+IVA_inversiones),0)+IF(O29=0,('HIPOTESIS '!$C$38+'HIPOTESIS '!$E$38),0)) -> 0 | P43: =-(IF(P29=inicio_inv1,imp_inv1*(1+IVA_inversiones),0)+IF(P29=inicio_inv2,imp_inv2*(1+IVA_inversiones),0)+IF(P29=0,('HIPOTESIS '!$C$38+'HIPOTESIS '!$E$38),0)) -> 0 | Q43: =-(IF(Q29=inicio_inv1,imp_inv1*(1+IVA_inversiones),0)+IF(Q29=inicio_inv2,imp_inv2*(1+IVA_inversiones),0)+IF(Q29=0,('HIPOTESIS '!$C$38+'HIPOTESIS '!$E$38),0)) -> 0 | R43: =-(IF(R29=inicio_inv1,imp_inv1*(1+IVA_inversiones),0)+IF(R29=inicio_inv2,imp_inv2*(1+IVA_inversiones),0)+IF(R29=0,('HIPOTESIS '!$C$38+'HIPOTESIS '!$E$38),0)) -> 0 | S43: =-(IF(S29=inicio_inv1,imp_inv1*(1+IVA_inversiones),0)+IF(S29=inicio_inv2,imp_inv2*(1+IVA_inversiones),0)+IF(S29=0,('HIPOTESIS '!$C$38+'HIPOTESIS '!$E$38),0)) -> 0 | T43: =-(IF(T29=inicio_inv1,imp_inv1*(1+IVA_inversiones),0)+IF(T29=inicio_inv2,imp_inv2*(1+IVA_inversiones),0)+IF(T29=0,('HIPOTESIS '!$C$38+'HIPOTESIS '!$E$38),0)) -> 0 | U43: =-(IF(U29=inicio_inv1,imp_inv1*(1+IVA_inversiones),0)+IF(U29=inicio_inv2,imp_inv2*(1+IVA_inversiones),0)+IF(U29=0,('HIPOTESIS '!$C$38+'HIPOTESIS '!$E$38),0)) -> 0 | V43: =-(IF(V29=inicio_inv1,imp_inv1*(1+IVA_inversiones),0)+IF(V29=inicio_inv2,imp_inv2*(1+IVA_inversiones),0)+IF(V29=0,('HIPOTESIS '!$C$38+'HIPOTESIS '!$E$38),0)) -> 0 | ... BW43: =-(IF(BW29=inicio_inv1,imp_inv1*(1+IVA_inversiones),0)+IF(BW29=inicio_inv2,imp_inv2*(1+IVA_inversiones),0)+IF(BW29=0,('HIPOTESIS '!$C$38+'HIPOTESIS '!$E$38),0)) -> 0
B44: Pago por variación de existencias | C44: =O44 -> 0 | E44: =SUM(P44:AA44) -> 0 | G44: =SUM(AB44:AM44) -> 0 | I44: =SUM(AN44:AY44) -> 0 | K44: =SUM(AZ44:BK44) -> 0 | M44: =SUM(BL44:BW44) -> 0 | O44: =-('C'!C111*(1+IVA_compras)+'C'!C114*(1+IVA_compras)+'C'!C117*(1+IVA_compras)) -> 0 | P44: =-('C'!D111*(1+IVA_compras)+'C'!D114*(1+IVA_compras)+'C'!D117*(1+IVA_compras)) -> 0 | Q44: =-('C'!E111*(1+IVA_compras)+'C'!E114*(1+IVA_compras)+'C'!E117*(1+IVA_compras)) -> 0 | R44: =-('C'!F111*(1+IVA_compras)+'C'!F114*(1+IVA_compras)+'C'!F117*(1+IVA_compras)) -> 0 | S44: =-('C'!G111*(1+IVA_compras)+'C'!G114*(1+IVA_compras)+'C'!G117*(1+IVA_compras)) -> 0 | T44: =-('C'!H111*(1+IVA_compras)+'C'!H114*(1+IVA_compras)+'C'!H117*(1+IVA_compras)) -> 0 | U44: =-('C'!I111*(1+IVA_compras)+'C'!I114*(1+IVA_compras)+'C'!I117*(1+IVA_compras)) -> 0 | V44: =-('C'!J111*(1+IVA_compras)+'C'!J114*(1+IVA_compras)+'C'!J117*(1+IVA_compras)) -> 0 | ... BW44: =-('C'!BK111*(1+IVA_compras)+'C'!BK114*(1+IVA_compras)+'C'!BK117*(1+IVA_compras)) -> 0
B45: Cobro de desinversiones | C45: =-O45 -> 0 | E45: =SUM(P45:AA45) -> 0 | G45: =SUM(AB45:AM45) -> 0 | I45: =SUM(AN45:AY45) -> 0 | K45: =SUM(AZ45:BK45) -> 0 | M45: =SUM(BL45:BW45) -> 0 | O45: 0 | P45: 0 | Q45: 0 | R45: 0 | S45: 0 | T45: 0 | U45: 0 | V45: 0 | W45: 0 | X45: 0 | Y45: 0 | Z45: 0 | AA45: 0 | AB45: 0 | AC45: 0 | AD45: 0 | AE45: 0 | AF45: 0 | AG45: 0 | AH45: 0 | AI45: 0 | AJ45: 0 | AK45: 0 | AL45: 0 | AM45: 0 | AN45: 0 | AO45: 0 | AP45: 0 | AQ45: 0 | AR45: 0 | AS45: 0 | AT45: 0 | AU45: 0 | AV45: 0 | AW45: 0 | AX45: 0 | AY45: 0 | AZ45: 0 | BA45: 0 | BB45: 0 | BC45: 0 | BD45: 0 | BE45: 0 | BF45: 0 | BG45: 0 | BH45: 0 | BI45: 0 | BJ45: 0 | BK45: 0 | BL45: 0 | BM45: 0 | BN45: 0 | BO45: 0 | BP45: 0 | BQ45: 0 | BR45: 0 | BS45: 0 | BT45: 0 | BU45: 0 | BV45: 0 | BW45: 0
B46: Pago/Cobro de fianzas y depósito a largo plazo | C46: =O46 -> 0 | E46: =SUM(P46:AA46) -> 0 | G46: =SUM(AB46:AM46) -> 0 | I46: =SUM(AN46:AY46) -> 0 | K46: =SUM(AZ46:BK46) -> 0 | M46: =SUM(BL46:BW46) -> 0 | O46: =-(IF(O29=mes_fianza,importe_fianza,0)+IF(O29=(mes_fianza+12*año_fin_fianza),-importe_fianza,0)) -> 0 | P46: =-(IF(P29=mes_fianza,importe_fianza,0)+IF(P29=(mes_fianza+12*año_fin_fianza),-importe_fianza,0)) -> 0 | Q46: =-(IF(Q29=mes_fianza,importe_fianza,0)+IF(Q29=(mes_fianza+12*año_fin_fianza),-importe_fianza,0)) -> 0 | R46: =-(IF(R29=mes_fianza,importe_fianza,0)+IF(R29=(mes_fianza+12*año_fin_fianza),-importe_fianza,0)) -> 0 | S46: =-(IF(S29=mes_fianza,importe_fianza,0)+IF(S29=(mes_fianza+12*año_fin_fianza),-importe_fianza,0)) -> 0 | T46: =-(IF(T29=mes_fianza,importe_fianza,0)+IF(T29=(mes_fianza+12*año_fin_fianza),-importe_fianza,0)) -> 0 | U46: =-(IF(U29=mes_fianza,importe_fianza,0)+IF(U29=(mes_fianza+12*año_fin_fianza),-importe_fianza,0)) -> 0 | V46: =-(IF(V29=mes_fianza,importe_fianza,0)+IF(V29=(mes_fianza+12*año_fin_fianza),-importe_fianza,0)) -> 0 | ... BW46: =-(IF(BW29=mes_fianza,importe_fianza,0)+IF(BW29=(mes_fianza+12*año_fin_fianza),-importe_fianza,0)) -> 0
B47: CF inversiones | C47: =SUM(C43:C46) -> 0 | E47: =SUM(E43:E46) -> 0 | F47: =IFERROR(E47/E56,"-") -> 0 | G47: =SUM(G43:G46) -> 0 | H47: =IFERROR(G47/G56,"-") -> 0 | I47: =SUM(I43:I46) -> 0 | J47: =IFERROR(I47/I56,"-") -> 0 | K47: =SUM(K43:K46) -> 0 | L47: =IFERROR(K47/K56,"-") -> 0 | M47: =SUM(M43:M46) -> 0 | N47: =IFERROR(M47/M56,"-") -> 0 | O47: =SUM(O43:O46) -> 0 | P47: =SUM(P43:P46) -> 0 | Q47: =SUM(Q43:Q46) -> 0 | R47: =SUM(R43:R46) -> 0 | S47: =SUM(S43:S46) -> 0 | T47: =SUM(T43:T46) -> 0 | U47: =SUM(U43:U46) -> 0 | V47: =SUM(V43:V46) -> 0 | ... BW47: =SUM(BW43:BW46) -> 0
B48: FINANCIACIÓN
B49: Abono de capital social (inicial + ampliaciones de capital) | C49: =O49 -> 1000 | E49: =SUM(P49:AA49) -> 0 | G49: =SUM(AB49:AM49) -> 0 | I49: =SUM(AN49:AY49) -> 0 | K49: =SUM(AZ49:BK49) -> 0 | M49: =SUM(BL49:BW49) -> 0 | O49: ='C'!C63 -> 1000 | P49: ='C'!D63 -> 0 | Q49: ='C'!E63 -> 0 | R49: ='C'!F63 -> 0 | S49: ='C'!G63 -> 0 | T49: ='C'!H63 -> 0 | U49: ='C'!I63 -> 0 | V49: ='C'!J63 -> 0 | ... BW49: ='C'!BK63 -> 0
B50: Abono nuevos préstamos | C50: =O50 -> 0 | E50: =SUM(P50:AA50) -> 0 | G50: =SUM(AB50:AM50) -> 0 | I50: =SUM(AN50:AY50) -> 0 | K50: =SUM(AZ50:BK50) -> 0 | M50: =SUM(BL50:BW50) -> 0 | O50: =IF(O29=inicio_p1,imp_p1,0)+IF(RESULTADOS!O29=inicio_p2,imp_p2,0)+IF(O29=inicio_prest_participa,importe_prest_participa,0) -> 0 | P50: =IF(P29=inicio_p1,imp_p1,0)+IF(RESULTADOS!P29=inicio_p2,imp_p2,0)+IF(P29=inicio_prest_participa,importe_prest_participa,0) -> 0 | Q50: =IF(Q29=inicio_p1,imp_p1,0)+IF(RESULTADOS!Q29=inicio_p2,imp_p2,0)+IF(Q29=inicio_prest_participa,importe_prest_participa,0) -> 0 | R50: =IF(R29=inicio_p1,imp_p1,0)+IF(RESULTADOS!R29=inicio_p2,imp_p2,0)+IF(R29=inicio_prest_participa,importe_prest_participa,0) -> 0 | S50: =IF(S29=inicio_p1,imp_p1,0)+IF(RESULTADOS!S29=inicio_p2,imp_p2,0)+IF(S29=inicio_prest_participa,importe_prest_participa,0) -> 0 | T50: =IF(T29=inicio_p1,imp_p1,0)+IF(RESULTADOS!T29=inicio_p2,imp_p2,0)+IF(T29=inicio_prest_participa,importe_prest_participa,0) -> 0 | U50: =IF(U29=inicio_p1,imp_p1,0)+IF(RESULTADOS!U29=inicio_p2,imp_p2,0)+IF(U29=inicio_prest_participa,importe_prest_participa,0) -> 0 | V50: =IF(V29=inicio_p1,imp_p1,0)+IF(RESULTADOS!V29=inicio_p2,imp_p2,0)+IF(V29=inicio_prest_participa,importe_prest_participa,0) -> 0 | ... BW50: =IF(BW29=inicio_p1,imp_p1,0)+IF(RESULTADOS!BW29=inicio_p2,imp_p2,0)+IF(BW29=inicio_prest_participa,importe_prest_participa,0) -> 0
B51: Abono subvenciones de capital | C51: =O51 -> 0 | E51: =SUM(P51:AA51) -> 0 | G51: =SUM(AB51:AM51) -> 0 | I51: =SUM(AN51:AY51) -> 0 | K51: =SUM(AZ51:BK51) -> 0 | M51: =SUM(BL51:BW51) -> 0 | O51: =IF(O29=inicio_subv_inv1,imp_subv_inv1,0)+IF(RESULTADOS!O29=inicio_subv_inv2,imp_subv_inv2,0)+IF(RESULTADOS!O29=inicio_subv_activ1,imp_subv_activ1,0)+IF(RESULTADOS!O29=inicio_subv_activ2,imp_subv_activ2,0) -> 0 | P51: =IF(P29=inicio_subv_inv1,imp_subv_inv1,0)+IF(RESULTADOS!P29=inicio_subv_inv2,imp_subv_inv2,0)+IF(RESULTADOS!P29=inicio_subv_activ1,imp_subv_activ1,0)+IF(RESULTADOS!P29=inicio_subv_activ2,imp_subv_activ2,0) -> 0 | Q51: =IF(Q29=inicio_subv_inv1,imp_subv_inv1,0)+IF(RESULTADOS!Q29=inicio_subv_inv2,imp_subv_inv2,0)+IF(RESULTADOS!Q29=inicio_subv_activ1,imp_subv_activ1,0)+IF(RESULTADOS!Q29=inicio_subv_activ2,imp_subv_activ2,0) -> 0 | R51: =IF(R29=inicio_subv_inv1,imp_subv_inv1,0)+IF(RESULTADOS!R29=inicio_subv_inv2,imp_subv_inv2,0)+IF(RESULTADOS!R29=inicio_subv_activ1,imp_subv_activ1,0)+IF(RESULTADOS!R29=inicio_subv_activ2,imp_subv_activ2,0) -> 0 | S51: =IF(S29=inicio_subv_inv1,imp_subv_inv1,0)+IF(RESULTADOS!S29=inicio_subv_inv2,imp_subv_inv2,0)+IF(RESULTADOS!S29=inicio_subv_activ1,imp_subv_activ1,0)+IF(RESULTADOS!S29=inicio_subv_activ2,imp_subv_activ2,0) -> 0 | T51: =IF(T29=inicio_subv_inv1,imp_subv_inv1,0)+IF(RESULTADOS!T29=inicio_subv_inv2,imp_subv_inv2,0)+IF(RESULTADOS!T29=inicio_subv_activ1,imp_subv_activ1,0)+IF(RESULTADOS!T29=inicio_subv_activ2,imp_subv_activ2,0) -> 0 | U51: =IF(U29=inicio_subv_inv1,imp_subv_inv1,0)+IF(RESULTADOS!U29=inicio_subv_inv2,imp_subv_inv2,0)+IF(RESULTADOS!U29=inicio_subv_activ1,imp_subv_activ1,0)+IF(RESULTADOS!U29=inicio_subv_activ2,imp_subv_activ2,0) -> 0 | V51: =IF(V29=inicio_subv_inv1,imp_subv_inv1,0)+IF(RESULTADOS!V29=inicio_subv_inv2,imp_subv_inv2,0)+IF(RESULTADOS!V29=inicio_subv_activ1,imp_subv_activ1,0)+IF(RESULTADOS!V29=inicio_subv_activ2,imp_subv_activ2,0) -> 0 | ... BW51: =IF(BW29=inicio_subv_inv1,imp_subv_inv1,0)+IF(RESULTADOS!BW29=inicio_subv_inv2,imp_subv_inv2,0)+IF(RESULTADOS!BW29=inicio_subv_activ1,imp_subv_activ1,0)+IF(RESULTADOS!BW29=inicio_subv_activ2,imp_subv_activ2,0) -> 0
B52: Pago préstamos existentes (parte de amortiz. de capital) | C52: =O52 -> 0 | E52: =SUM(P52:AA52) -> 0 | G52: =SUM(AB52:AM52) -> 0 | I52: =SUM(AN52:AY52) -> 0 | K52: =SUM(AZ52:BK52) -> 0 | M52: =SUM(BL52:BW52) -> 0 | O52: =-'C'!C72-'C'!C81-'C'!C88 -> 0 | P52: =-'C'!D72-'C'!D81-'C'!D88 -> 0 | Q52: =-'C'!E72-'C'!E81-'C'!E88 -> 0 | R52: =-'C'!F72-'C'!F81-'C'!F88 -> 0 | S52: =-'C'!G72-'C'!G81-'C'!G88 -> 0 | T52: =-'C'!H72-'C'!H81-'C'!H88 -> 0 | U52: =-'C'!I72-'C'!I81-'C'!I88 -> 0 | V52: =-'C'!J72-'C'!J81-'C'!J88 -> 0 | ... BW52: =-'C'!BK72-'C'!BK81-'C'!BK88 -> 0
B53: Pago de dividendos | C53: =O53 -> 0 | E53: =SUM(P53:AA53) -> 0 | G53: =SUM(AB53:AM53) -> 0 | I53: =SUM(AN53:AY53) -> 0 | K53: =SUM(AZ53:BK53) -> 0 | M53: =SUM(BL53:BW53) -> 0 | O53: 0 | P53: 0 | Q53: 0 | R53: 0 | S53: 0 | T53: 0 | U53: 0 | V53: 0 | W53: 0 | X53: 0 | Y53: 0 | Z53: 0 | AA53: 0 | AB53: 0 | AC53: 0 | AD53: 0 | AE53: 0 | AF53: 0 | AG53: 0 | AH53: 0 | AI53: 0 | AJ53: 0 | AK53: 0 | AL53: 0 | AM53: 0 | AN53: 0 | AO53: 0 | AP53: 0 | AQ53: 0 | AR53: 0 | AS53: 0 | AT53: 0 | AU53: 0 | AV53: 0 | AW53: 0 | AX53: 0 | AY53: 0 | AZ53: 0 | BA53: 0 | BB53: 0 | BC53: 0 | BD53: 0 | BE53: 0 | BF53: 0 | BG53: 0 | BH53: 0 | BI53: 0 | BJ53: 0 | BK53: 0 | BL53: 0 | BM53: 0 | BN53: 0 | BO53: 0 | BP53: 0 | BQ53: 0 | BR53: 0 | BS53: 0 | BT53: 0 | BU53: 0 | BV53: 0 | BW53: 0
B54: CF Financiación | C54: =SUM(C49:C53) -> 1000 | E54: =SUM(E49:E53) -> 0 | F54: =IFERROR(E54/E55,"-") -> - | G54: =SUM(G49:G53) -> 0 | H54: =IFERROR(G54/G56,"-") -> 0 | I54: =SUM(I49:I53) -> 0 | J54: =IFERROR(I54/I56,"-") -> 0 | K54: =SUM(K49:K53) -> 0 | L54: =IFERROR(K54/K56,"-") -> 0 | M54: =SUM(M49:M53) -> 0 | N54: =IFERROR(M54/M56,"-") -> 0 | O54: =SUM(O49:O53) -> 1000 | P54: =SUM(P49:P53) -> 0 | Q54: =SUM(Q49:Q53) -> 0 | R54: =SUM(R49:R53) -> 0 | S54: =SUM(S49:S53) -> 0 | T54: =SUM(T49:T53) -> 0 | U54: =SUM(U49:U53) -> 0 | V54: =SUM(V49:V53) -> 0 | ... BW54: =SUM(BW49:BW53) -> 0
B55: CF NETO | C55: =C41+C47+C54 -> 1000 | E55: =E41+E47+E54 -> 0 | G55: =G41+G47+G54 -> 0 | I55: =I41+I47+I54 -> 0 | K55: =K41+K47+K54 -> 0 | M55: =M41+M47+M54 -> 0 | O55: =O41+O47+O54 -> 1000 | P55: =P41+P47+P54 -> 0 | Q55: =Q41+Q47+Q54 -> 0 | R55: =R41+R47+R54 -> 0 | S55: =S41+S47+S54 -> 0 | T55: =T41+T47+T54 -> 0 | U55: =U41+U47+U54 -> 0 | V55: =V41+V47+V54 -> 0 | ... BW55: =BW41+BW47+BW54 -> 0
B56: CF ACUMULADO AL CIERRE (Tesorería disponible) | C56: =C55 -> 1000 | E56: =C56+E55 -> 1000 | F56: =IFERROR(E56/E56,"-") -> 1 | G56: =E56+G55 -> 1000 | H56: =IFERROR(G56/G56,"-") -> 1 | I56: =G56+I55 -> 1000 | J56: =IFERROR(I56/I56,"-") -> 1 | K56: =I56+K55 -> 1000 | L56: =IFERROR(K56/K56,"-") -> 1 | M56: =K56+M55 -> 1000 | N56: =IFERROR(M56/M56,"-") -> 1 | O56: =O55 -> 1000 | P56: =O56+P55 -> 1000 | Q56: =P56+Q55 -> 1000 | R56: =Q56+R55 -> 1000 | S56: =R56+S55 -> 1000 | T56: =S56+T55 -> 1000 | U56: =T56+U55 -> 1000 | V56: =U56+V55 -> 1000 | W56: =V56+W55 -> 1000 | ... BW56: =BV56+BW55 -> 1000
B57: Si <0 entonces : Póliza de crédito (saldo vivo) o Refinanciación (nuevas hipótesis) | C57: =IF(C56<0,C56*-1,0) -> 0 | E57: =IF(E56<0,E56*-1,0) -> 0 | G57: =IF(G56<0,G56*-1,0) -> 0 | I57: =IF(I56<0,I56*-1,0) -> 0 | K57: =IF(K56<0,K56*-1,0) -> 0 | M57: =IF(M56<0,M56*-1,0) -> 0 | O57: =IF(O56<0,O56*-1,0) -> 0 | P57: =IF(P56<0,P56*-1,0) -> 0 | Q57: =IF(Q56<0,Q56*-1,0) -> 0 | R57: =IF(R56<0,R56*-1,0) -> 0 | S57: =IF(S56<0,S56*-1,0) -> 0 | T57: =IF(T56<0,T56*-1,0) -> 0 | U57: =IF(U56<0,U56*-1,0) -> 0 | V57: =IF(V56<0,V56*-1,0) -> 0 | ... BW57: =IF(BW56<0,BW56*-1,0) -> 0
B58: TESORERÍA DISPONIBLE (incluye póliza) (Póliza Activada o Refinanciación si <0) | C58: =C56+C57 -> 1000 | E58: =E56+E57 -> 1000 | G58: =G56+G57 -> 1000 | I58: =I56+I57 -> 1000 | K58: =K56+K57 -> 1000 | M58: =M56+M57 -> 1000 | O58: =O56+O57 -> 1000 | P58: =P56+P57 -> 1000 | Q58: =Q56+Q57 -> 1000 | R58: =R56+R57 -> 1000 | S58: =S56+S57 -> 1000 | T58: =T56+T57 -> 1000 | U58: =U56+U57 -> 1000 | V58: =V56+V57 -> 1000 | ... BW58: =BW56+BW57 -> 1000
C61: AÑOS | O61: MES 0 | P61: MESES AÑO 1 | AB61: MESES AÑO 2 | AN61: MESES AÑO 3 | AZ61: MESES AÑO 4 | BL61: MESES AÑO 5
A62: C | B62: BALANCE DE SITUACIÓN (Balance Sheet) | C62: AÑO 0 | D62: % | E62: AÑO 1 | F62: % | G62: AÑO 2 | H62: % | I62: AÑO 3 | J62: % | K62: AÑO 4 | L62: % | M62: AÑO 5 | N62: % | O62: 0 | P62: 1 | Q62: 2 | R62: 3 | S62: 4 | T62: 5 | U62: 6 | V62: 7 | W62: 8 | X62: 9 | Y62: 10 | Z62: 11 | AA62: 12 | AB62: 13 | AC62: 14 | AD62: 15 | AE62: 16 | AF62: 17 | AG62: 18 | AH62: 19 | AI62: 20 | AJ62: 21 | AK62: 22 | AL62: 23 | AM62: 24 | AN62: 25 | AO62: 26 | AP62: 27 | AQ62: 28 | AR62: 29 | AS62: 30 | AT62: 31 | AU62: 32 | AV62: 33 | AW62: 34 | AX62: 35 | AY62: 36 | AZ62: 37 | BA62: 38 | BB62: 39 | BC62: 40 | BD62: 41 | BE62: 42 | BF62: 43 | BG62: 44 | BH62: 45 | BI62: 46 | BJ62: 47 | BK62: 48 | BL62: 49 | BM62: 50 | BN62: 51 | BO62: 52 | BP62: 53 | BQ62: 54 | BR62: 55 | BS62: 56 | BT62: 57 | BU62: 58 | BV62: 59 | BW62: 60
B63: PATRIMONIO NETO + PASIVO
B64: PATRIMONIO NETO (PN)
B65: Capital (inicial + ampliaciones) | C65: =O65 -> 1000 | E65: =AA65 -> 1000 | G65: =AM65 -> 1000 | I65: =AY65 -> 1000 | K65: =BK65 -> 1000 | M65: =BW65 -> 1000 | O65: ='C'!C64 -> 1000 | P65: ='C'!D64 -> 1000 | Q65: ='C'!E64 -> 1000 | R65: ='C'!F64 -> 1000 | S65: ='C'!G64 -> 1000 | T65: ='C'!H64 -> 1000 | U65: ='C'!I64 -> 1000 | V65: ='C'!J64 -> 1000 | ... BW65: ='C'!BK64 -> 1000
B66: Resultado acumulado años anteriores (reservas) | C66: 0 | E66: =C66+C67 -> 0 | G66: =E67+E66 -> 0 | I66: =G66+G67 -> 0 | K66: =I66+I67 -> 0 | M66: =K66+K67 -> 0 | O66: 0 | P66: =O25 -> 0 | Q66: =P25 -> 0 | R66: =Q25 -> 0 | S66: =R25 -> 0 | T66: =S25 -> 0 | U66: =T25 -> 0 | V66: =U25 -> 0 | W66: =V25 -> 0 | ... BW66: =BV25 -> 0
B67: Resultado año en curso | C67: =SUM(O67) -> 0 | E67: =SUM(P67:AA67) -> 0 | G67: =SUM(AB67:AM67) -> 0 | I67: =SUM(AN67:AY67) -> 0 | K67: =SUM(AZ67:BK67) -> 0 | M67: =SUM(BL67:BW67) -> 0 | O67: =O24 -> 0 | P67: =P24 -> 0 | Q67: =Q24 -> 0 | R67: =R24 -> 0 | S67: =S24 -> 0 | T67: =T24 -> 0 | U67: =U24 -> 0 | V67: =V24 -> 0 | ... BW67: =BW24 -> 0
B68: Préstamo participativo | C68: =O68 -> 0 | E68: =AA68 -> 0 | G68: =AM68 -> 0 | I68: =AY68 -> 0 | K68: =BK68 -> 0 | M68: =BW68 -> 0 | O68: ='C'!C86 -> 0 | P68: ='C'!D86 -> 0 | Q68: ='C'!E86 -> 0 | R68: ='C'!F86 -> 0 | S68: ='C'!G86 -> 0 | T68: ='C'!H86 -> 0 | U68: ='C'!I86 -> 0 | V68: ='C'!J86 -> 0 | ... BW68: ='C'!BK86 -> 0
B69: Fondos propios | C69: =C65+C66+C67+C68 -> 1000 | E69: =E65+E66+E67+E68 -> 1000 | G69: =G65+G66+G67+G68 -> 1000 | I69: =I65+I66+I67+I68 -> 1000 | K69: =K65+K66+K67+K68 -> 1000 | M69: =M65+M66+M67+M68 -> 1000 | O69: =O65+O66+O67+O68 -> 1000 | P69: =P65+P66+P67+P68 -> 1000 | Q69: =Q65+Q66+Q67+Q68 -> 1000 | R69: =R65+R66+R67+R68 -> 1000 | S69: =S65+S66+S67+S68 -> 1000 | T69: =T65+T66+T67+T68 -> 1000 | U69: =U65+U66+U67+U68 -> 1000 | V69: =V65+V66+V67+V68 -> 1000 | ... BW69: =BW65+BW66+BW67+BW68 -> 1000
B70: Valor de las subvenciones de capital | C70: =O70 -> 0 | E70: =AA70 -> 0 | G70: =AM70 -> 0 | I70: =AY70 -> 0 | K70: =BK70 -> 0 | M70: =BW70 -> 0 | O70: ='C'!C59 -> 0 | P70: ='C'!D59 -> 0 | Q70: ='C'!E59 -> 0 | R70: ='C'!F59 -> 0 | S70: ='C'!G59 -> 0 | T70: ='C'!H59 -> 0 | U70: ='C'!I59 -> 0 | V70: ='C'!J59 -> 0 | ... BW70: ='C'!BK59 -> 0
B71: Total Patrimonio Neto | C71: =C69+C70 -> 1000 | D71: =IFERROR(C71/C85,"-") -> 1 | E71: =E69+E70 -> 1000 | F71: =IFERROR(E71/E85,"-") -> 1 | G71: =G69+G70 -> 1000 | H71: =IFERROR(G71/G85,"-") -> 1 | I71: =I69+I70 -> 1000 | J71: =IFERROR(I71/I85,"-") -> 1 | K71: =K69+K70 -> 1000 | L71: =IFERROR(K71/K85,"-") -> 1 | M71: =M69+M70 -> 1000 | N71: =IFERROR(M71/M85,"-") -> 1 | O71: =O69+O70 -> 1000 | P71: =P69+P70 -> 1000 | Q71: =Q69+Q70 -> 1000 | R71: =R69+R70 -> 1000 | S71: =S69+S70 -> 1000 | T71: =T69+T70 -> 1000 | U71: =U69+U70 -> 1000 | V71: =V69+V70 -> 1000 | ... BW71: =BW69+BW70 -> 1000
B72: PASIVO NO CORRIENTE
B73: Deudas a largo plazo (parte préstamos >12 meses) | C73: =O73 -> 0 | E73: =AA73 -> 0 | G73: =AM73 -> 0 | I73: =AY73 -> 0 | K73: =BK73 -> 0 | M73: =BW73 -> 0 | O73: ='C'!C70+'C'!C79 -> 0 | P73: ='C'!D70+'C'!D79 -> 0 | Q73: ='C'!E70+'C'!E79 -> 0 | R73: ='C'!F70+'C'!F79 -> 0 | S73: ='C'!G70+'C'!G79 -> 0 | T73: ='C'!H70+'C'!H79 -> 0 | U73: ='C'!I70+'C'!I79 -> 0 | V73: ='C'!J70+'C'!J79 -> 0 | ... BW73: ='C'!BK70+'C'!BK79 -> 0
B74: Total pasivo no corriente | C74: =C73 -> 0 | D74: =IFERROR(C74/C85,"-") -> 0 | E74: =E73 -> 0 | F74: =IFERROR(E74/E85,"-") -> 0 | G74: =G73 -> 0 | H74: =IFERROR(G74/G85,"-") -> 0 | I74: =I73 -> 0 | J74: =IFERROR(I74/I85,"-") -> 0 | K74: =K73 -> 0 | L74: =IFERROR(K74/K85,"-") -> 0 | M74: =M73 -> 0 | N74: =IFERROR(M74/M85,"-") -> 0 | O74: =O73 -> 0 | P74: =P73 -> 0 | Q74: =Q73 -> 0 | R74: =R73 -> 0 | S74: =S73 -> 0 | T74: =T73 -> 0 | U74: =U73 -> 0 | V74: =V73 -> 0 | ... BW74: =BW73 -> 0
B75: PASIVO CORRIENTE
B76: Deudas a corto (parte préstamos <= 12 meses) | C76: =O76 -> 0 | E76: =AA76 -> 0 | G76: =AM76 -> 0 | I76: =AY76 -> 0 | K76: =BK76 -> 0 | M76: =BW76 -> 0 | O76: ='C'!C69+'C'!C78 -> 0 | P76: ='C'!D69+'C'!D78 -> 0 | Q76: ='C'!E69+'C'!E78 -> 0 | R76: ='C'!F69+'C'!F78 -> 0 | S76: ='C'!G69+'C'!G78 -> 0 | T76: ='C'!H69+'C'!H78 -> 0 | U76: ='C'!I69+'C'!I78 -> 0 | V76: ='C'!J69+'C'!J78 -> 0 | ... BW76: ='C'!BK69+'C'!BK78 -> 0
B77: Saldo vivo de la póliza (coste refinanciación) | C77: =O77 -> 0 | E77: =AA77 -> 0 | G77: =AM77 -> 0 | I77: =AY77 -> 0 | K77: =BK77 -> 0 | M77: =BW77 -> 0 | O77: =O57 -> 0 | P77: =P57 -> 0 | Q77: =Q57 -> 0 | R77: =R57 -> 0 | S77: =S57 -> 0 | T77: =T57 -> 0 | U77: =U57 -> 0 | V77: =V57 -> 0 | ... BW77: =BW57 -> 0
B78: Deudas a corto por proveedores | C78: =O78 -> 0 | E78: =AA78 -> 0 | G78: =AM78 -> 0 | I78: =AY78 -> 0 | K78: =BK78 -> 0 | M78: =BW78 -> 0 | O78: ='C'!C99*(1+IVA_compras)+'C'!C103*(1+IVA_compras)+'C'!C107*(1+IVA_compras)+'C'!C112*(1+IVA_compras)+'C'!C115*(1+IVA_compras)+'C'!C118*(1+IVA_compras) -> 0 | P78: ='C'!D99*(1+IVA_compras)+'C'!D103*(1+IVA_compras)+'C'!D107*(1+IVA_compras)+'C'!D112*(1+IVA_compras)+'C'!D115*(1+IVA_compras)+'C'!D118*(1+IVA_compras) -> 0 | Q78: ='C'!E99*(1+IVA_compras)+'C'!E103*(1+IVA_compras)+'C'!E107*(1+IVA_compras)+'C'!E112*(1+IVA_compras)+'C'!E115*(1+IVA_compras)+'C'!E118*(1+IVA_compras) -> 0 | R78: ='C'!F99*(1+IVA_compras)+'C'!F103*(1+IVA_compras)+'C'!F107*(1+IVA_compras)+'C'!F112*(1+IVA_compras)+'C'!F115*(1+IVA_compras)+'C'!F118*(1+IVA_compras) -> 0 | S78: ='C'!G99*(1+IVA_compras)+'C'!G103*(1+IVA_compras)+'C'!G107*(1+IVA_compras)+'C'!G112*(1+IVA_compras)+'C'!G115*(1+IVA_compras)+'C'!G118*(1+IVA_compras) -> 0 | T78: ='C'!H99*(1+IVA_compras)+'C'!H103*(1+IVA_compras)+'C'!H107*(1+IVA_compras)+'C'!H112*(1+IVA_compras)+'C'!H115*(1+IVA_compras)+'C'!H118*(1+IVA_compras) -> 0 | U78: ='C'!I99*(1+IVA_compras)+'C'!I103*(1+IVA_compras)+'C'!I107*(1+IVA_compras)+'C'!I112*(1+IVA_compras)+'C'!I115*(1+IVA_compras)+'C'!I118*(1+IVA_compras) -> 0 | V78: ='C'!J99*(1+IVA_compras)+'C'!J103*(1+IVA_compras)+'C'!J107*(1+IVA_compras)+'C'!J112*(1+IVA_compras)+'C'!J115*(1+IVA_compras)+'C'!J118*(1+IVA_compras) -> 0 | ... BW78: ='C'!BK99*(1+IVA_compras)+'C'!BK103*(1+IVA_compras)+'C'!BK107*(1+IVA_compras)+'C'!BK112*(1+IVA_compras)+'C'!BK115*(1+IVA_compras)+'C'!BK118*(1+IVA_compras) -> 0
B79: Seg. Social acreedora | E79: =AA79 -> 0 | G79: =AM79 -> 0 | I79: =AY79 -> 0 | K79: =BK79 -> 0 | M79: =BW79 -> 0 | O79: ='C'!C253 -> 0 | P79: ='C'!D253 -> 0 | Q79: ='C'!E253 -> 0 | R79: ='C'!F253 -> 0 | S79: ='C'!G253 -> 0 | T79: ='C'!H253 -> 0 | U79: ='C'!I253 -> 0 | V79: ='C'!J253 -> 0 | ... BW79: ='C'!BK253 -> 0
B80: Hacienda pública acreedora por IS | C80: =O80 -> 0 | E80: =AA80 -> 0 | G80: =AM80 -> 0 | I80: =AY80 -> 0 | K80: =BK80 -> 0 | M80: =BW80 -> 0 | O80: ='C'!C268 -> 0 | P80: ='C'!D268 -> 0 | Q80: ='C'!E268 -> 0 | R80: ='C'!F268 -> 0 | S80: ='C'!G268 -> 0 | T80: ='C'!H268 -> 0 | U80: ='C'!I268 -> 0 | V80: ='C'!J268 -> 0 | ... BW80: ='C'!BK268 -> 0
B81: Hacienda pública acreedora por IVA | C81: =O81 -> 0 | E81: =AA81 -> 0 | G81: =AM81 -> 0 | I81: =AY81 -> 0 | K81: =BK81 -> 0 | M81: =BW81 -> 0 | O81: ='C'!C260 -> 0 | P81: ='C'!D260 -> 0 | Q81: ='C'!E260 -> 0 | R81: ='C'!F260 -> 0 | S81: ='C'!G260 -> 0 | T81: ='C'!H260 -> 0 | U81: ='C'!I260 -> 0 | V81: ='C'!J260 -> 0 | ... BW81: ='C'!BK260 -> 0
B82: Hacienda pública acreedora por Retenciones Renta (IRPF) | E82: =AA82 -> 0 | G82: =AM82 -> 0 | I82: =AY82 -> 0 | K82: =BK82 -> 0 | M82: =BW82 -> 0 | P82: ='C'!D248 -> 0 | Q82: ='C'!E248 -> 0 | R82: ='C'!F248 -> 0 | S82: ='C'!G248 -> 0 | T82: ='C'!H248 -> 0 | U82: ='C'!I248 -> 0 | V82: ='C'!J248 -> 0 | W82: ='C'!K248 -> 0 | ... BW82: ='C'!BK248 -> 0
B83: Total pasivo Corriente | C83: =C76+C78+C80+C77+C81+C82+C79 -> 0 | D83: =IFERROR(C83/C85,"-") -> 0 | E83: =E76+E78+E80+E77+E81+E82+E79 -> 0 | F83: =IFERROR(E83/E85,"-") -> 0 | G83: =G76+G78+G80+G77+G81+G82+G79 -> 0 | H83: =IFERROR(G83/G85,"-") -> 0 | I83: =I76+I78+I80+I77+I81+I82+I79 -> 0 | J83: =IFERROR(I83/I85,"-") -> 0 | K83: =K76+K78+K80+K77+K81+K82+K79 -> 0 | L83: =IFERROR(K83/K85,"-") -> 0 | M83: =M76+M78+M80+M77+M81+M82+M79 -> 0 | N83: =IFERROR(M83/M85,"-") -> 0 | O83: =O76+O78+O80+O77+O81+O79+O82 -> 0 | P83: =P76+P78+P80+P77+P81+P79+P82 -> 0 | Q83: =Q76+Q78+Q80+Q77+Q81+Q79+Q82 -> 0 | R83: =R76+R78+R80+R77+R81+R79+R82 -> 0 | S83: =S76+S78+S80+S77+S81+S79+S82 -> 0 | T83: =T76+T78+T80+T77+T81+T79+T82 -> 0 | U83: =U76+U78+U80+U77+U81+U79+U82 -> 0 | V83: =V76+V78+V80+V77+V81+V79+V82 -> 0 | ... BW83: =BW76+BW78+BW80+BW77+BW81+BW79+BW82 -> 0
B84: Total Pasivo | C84: =C74+C83 -> 0 | E84: =E74+E83 -> 0 | G84: =G74+G83 -> 0 | I84: =I74+I83 -> 0 | K84: =K74+K83 -> 0 | M84: =M74+M83 -> 0 | O84: =O74+O83 -> 0 | P84: =P74+P83 -> 0 | Q84: =Q74+Q83 -> 0 | R84: =R74+R83 -> 0 | S84: =S74+S83 -> 0 | T84: =T74+T83 -> 0 | U84: =U74+U83 -> 0 | V84: =V74+V83 -> 0 | ... BW84: =BW74+BW83 -> 0
B85: TOTAL PN+ PASIVO | C85: =C71+C84 -> 1000 | D85: =IFERROR(C85/C85,"-") -> 1 | E85: =E71+E84 -> 1000 | F85: =IFERROR(E85/E85,"-") -> 1 | G85: =G71+G84 -> 1000 | H85: =IFERROR(G85/G85,"-") -> 1 | I85: =I71+I84 -> 1000 | J85: =IFERROR(I85/I85,"-") -> 1 | K85: =K71+K84 -> 1000 | L85: =IFERROR(K85/K85,"-") -> 1 | M85: =M71+M84 -> 1000 | N85: =IFERROR(M85/M85,"-") -> 1 | O85: =O84+O71 -> 1000 | P85: =P84+P71 -> 1000 | Q85: =Q84+Q71 -> 1000 | R85: =R84+R71 -> 1000 | S85: =S84+S71 -> 1000 | T85: =T84+T71 -> 1000 | U85: =U84+U71 -> 1000 | V85: =V84+V71 -> 1000 | ... BW85: =BW84+BW71 -> 1000
B86: ACTIVO
B87: ACTIVO NO CORRIENTE
B88: Inmovilizado | C88: =O88 -> 0 | E88: =AA88 -> 0 | G88: =AM88 -> 0 | I88: =AY88 -> 0 | K88: =BK88 -> 0 | M88: =BW88 -> 0 | O88: ='C'!C51 -> 0 | P88: ='C'!D51 -> 0 | Q88: ='C'!E51 -> 0 | R88: ='C'!F51 -> 0 | S88: ='C'!G51 -> 0 | T88: ='C'!H51 -> 0 | U88: ='C'!I51 -> 0 | V88: ='C'!J51 -> 0 | ... BW88: ='C'!BK51 -> 0
B89: Fianzas y depósitos | C89: =O89 -> 0 | E89: =AA89 -> 0 | G89: =AM89 -> 0 | I89: =AY89 -> 0 | K89: =BK89 -> 0 | M89: =BW89 -> 0 | O89: ='C'!C53 -> 0 | P89: ='C'!D53 -> 0 | Q89: ='C'!E53 -> 0 | R89: ='C'!F53 -> 0 | S89: ='C'!G53 -> 0 | T89: ='C'!H53 -> 0 | U89: ='C'!I53 -> 0 | V89: ='C'!J53 -> 0 | ... BW89: ='C'!BK53 -> 0
B90: Total activo no corriente | C90: =C88+C89 -> 0 | D90: =IFERROR(C90/C97,"-") -> 0 | E90: =E88+E89 -> 0 | F90: =IFERROR(E90/E97,"-") -> 0 | G90: =G88+G89 -> 0 | H90: =IFERROR(G90/G97,"-") -> 0 | I90: =I88+I89 -> 0 | J90: =IFERROR(I90/I97,"-") -> 0 | K90: =K88+K89 -> 0 | L90: =IFERROR(K90/K97,"-") -> 0 | M90: =M88+M89 -> 0 | N90: =IFERROR(M90/M97,"-") -> 0 | O90: =O88+O89 -> 0 | P90: =P88+P89 -> 0 | Q90: =Q88+Q89 -> 0 | R90: =R88+R89 -> 0 | S90: =S88+S89 -> 0 | T90: =T88+T89 -> 0 | U90: =U88+U89 -> 0 | V90: =V88+V89 -> 0 | ... BW90: =BW88+BW89 -> 0
B91: ACTIVO CORRIENTE
B92: Existencias | C92: =O92 -> 0 | E92: =AA92 -> 0 | G92: =AM92 -> 0 | I92: =AY92 -> 0 | K92: =BK92 -> 0 | M92: =BW92 -> 0 | O92: ='HIPOTESIS '!C149+'HIPOTESIS '!C156+'HIPOTESIS '!C163 -> 0 | P92: ='HIPOTESIS '!D149+'HIPOTESIS '!D156+'HIPOTESIS '!D163 -> 0 | Q92: ='HIPOTESIS '!E149+'HIPOTESIS '!E156+'HIPOTESIS '!E163 -> 0 | R92: ='HIPOTESIS '!F149+'HIPOTESIS '!F156+'HIPOTESIS '!F163 -> 0 | S92: ='HIPOTESIS '!G149+'HIPOTESIS '!G156+'HIPOTESIS '!G163 -> 0 | T92: ='HIPOTESIS '!H149+'HIPOTESIS '!H156+'HIPOTESIS '!H163 -> 0 | U92: ='HIPOTESIS '!I149+'HIPOTESIS '!I156+'HIPOTESIS '!I163 -> 0 | V92: ='HIPOTESIS '!J149+'HIPOTESIS '!J156+'HIPOTESIS '!J163 -> 0 | ... BW92: ='HIPOTESIS '!BK149+'HIPOTESIS '!BK156+'HIPOTESIS '!BK163 -> 0
B93: Realizable comercial (por clientes) | C93: =O93 -> 0 | E93: =AA93 -> 0 | G93: =AM93 -> 0 | I93: =AY93 -> 0 | K93: =BK93 -> 0 | M93: =BW93 -> 0 | O93: ='C'!C97*(1+IVA_ventas)+'C'!C101*(1+IVA_ventas)+'C'!C105*(1+IVA_ventas) -> 0 | P93: ='C'!D97*(1+IVA_ventas)+'C'!D101*(1+IVA_ventas)+'C'!D105*(1+IVA_ventas) -> 0 | Q93: ='C'!E97*(1+IVA_ventas)+'C'!E101*(1+IVA_ventas)+'C'!E105*(1+IVA_ventas) -> 0 | R93: ='C'!F97*(1+IVA_ventas)+'C'!F101*(1+IVA_ventas)+'C'!F105*(1+IVA_ventas) -> 0 | S93: ='C'!G97*(1+IVA_ventas)+'C'!G101*(1+IVA_ventas)+'C'!G105*(1+IVA_ventas) -> 0 | T93: ='C'!H97*(1+IVA_ventas)+'C'!H101*(1+IVA_ventas)+'C'!H105*(1+IVA_ventas) -> 0 | U93: ='C'!I97*(1+IVA_ventas)+'C'!I101*(1+IVA_ventas)+'C'!I105*(1+IVA_ventas) -> 0 | V93: ='C'!J97*(1+IVA_ventas)+'C'!J101*(1+IVA_ventas)+'C'!J105*(1+IVA_ventas) -> 0 | ... BW93: ='C'!BK97*(1+IVA_ventas)+'C'!BK101*(1+IVA_ventas)+'C'!BK105*(1+IVA_ventas) -> 0
B94: Realizable de IS (por crédito fiscal activado y no utilizado) | C94: =O94 -> 0 | E94: =AA94 -> 0 | G94: =AM94 -> 0 | I94: =AY94 -> 0 | K94: =BK94 -> 0 | M94: =BW94 -> 0 | O94: =-'C'!C265 -> 0 | P94: =-'C'!D265 -> 0 | Q94: =-'C'!E265 -> 0 | R94: =-'C'!F265 -> 0 | S94: =-'C'!G265 -> 0 | T94: =-'C'!H265 -> 0 | U94: =-'C'!I265 -> 0 | V94: =-'C'!J265 -> 0 | ... BW94: =-'C'!BK265 -> 0
B95: Tesorería Disponible (incluye póliza) | C95: =O95 -> 1000 | E95: =AA95 -> 1000 | G95: =AM95 -> 1000 | I95: =AY95 -> 1000 | K95: =BK95 -> 1000 | M95: =BW95 -> 1000 | O95: =O58 -> 1000 | P95: =P58 -> 1000 | Q95: =Q58 -> 1000 | R95: =R58 -> 1000 | S95: =S58 -> 1000 | T95: =T58 -> 1000 | U95: =U58 -> 1000 | V95: =V58 -> 1000 | ... BW95: =BW58 -> 1000
B96: Total activo corriente | C96: =C92+C93+C95+C94 -> 1000 | D96: =IFERROR(C96/C97,"-") -> 1 | E96: =E92+E93+E95+E94 -> 1000 | F96: =IFERROR(E96/E97,"-") -> 1 | G96: =G92+G93+G95+G94 -> 1000 | H96: =IFERROR(G96/G97,"-") -> 1 | I96: =I92+I93+I95+I94 -> 1000 | J96: =IFERROR(I96/I97,"-") -> 1 | K96: =K92+K93+K95+K94 -> 1000 | M96: =M92+M93+M95+M94 -> 1000 | N96: =IFERROR(M96/M97,"-") -> 1 | O96: =O92+O93+O95+O94 -> 1000 | P96: =P92+P93+P95+P94 -> 1000 | Q96: =Q92+Q93+Q95+Q94 -> 1000 | R96: =R92+R93+R95+R94 -> 1000 | S96: =S92+S93+S95+S94 -> 1000 | T96: =T92+T93+T95+T94 -> 1000 | U96: =U92+U93+U95+U94 -> 1000 | V96: =V92+V93+V95+V94 -> 1000 | ... BW96: =BW92+BW93+BW95+BW94 -> 1000
B97: TOTAL. ACTIVO | C97: =C90+C96 -> 1000 | D97: =IFERROR(C97/C97,"-") -> 1 | E97: =E90+E96 -> 1000 | F97: =IFERROR(E97/E97,"-") -> 1 | G97: =G90+G96 -> 1000 | H97: =IFERROR(G97/G97,"-") -> 1 | I97: =I90+I96 -> 1000 | J97: =IFERROR(I97/I97,"-") -> 1 | K97: =K90+K96 -> 1000 | L97: =IFERROR(K97/K97,"-") -> 1 | M97: =M90+M96 -> 1000 | N97: =IFERROR(M97/M97,"-") -> 1 | O97: =O90+O96 -> 1000 | P97: =P90+P96 -> 1000 | Q97: =Q90+Q96 -> 1000 | R97: =R90+R96 -> 1000 | S97: =S90+S96 -> 1000 | T97: =T90+T96 -> 1000 | U97: =U90+U96 -> 1000 | V97: =V90+V96 -> 1000 | ... BW97: =BW90+BW96 -> 1000
B98: Check 1: (A-PN-P)=0? | C98: =C97-C85 -> 0 | E98: =E97-E85 -> 0 | G98: =G97-G85 -> 0 | I98: =I97-I85 -> 0 | K98: =K97-K85 -> 0 | M98: =M97-M85 -> 0 | O98: =O97-O85 -> 0 | P98: =P97-P85 -> 0 | Q98: =Q97-Q85 -> 0 | R98: =R97-R85 -> 0 | S98: =S97-S85 -> 0 | T98: =T97-T85 -> 0 | U98: =U97-U85 -> 0 | V98: =V97-V85 -> 0 | ... BW98: =BW97-BW85 -> 0
B99: Check 2: (cash_anual=cash_último_mes_año) | C99: =C58-C95 -> 0 | E99: =E58-E95 -> 0 | G99: =G58-G95 -> 0 | I99: =I58-I95 -> 0 | K99: =K58-K95 -> 0 | M99: =M58-M95 -> 0

Sheet ANALISIS 
A2: Parte IV: ANÁLISIS
A4: A | B4: ANÁLISIS FINANCIERO (re-funding)
B6: DISPONIBLE DE TESORERÍA | C6: AÑO 0 | D6: AÑO 1 | E6: AÑO 2 | F6: AÑO 3 | G6: AÑO 4 | H6: AÑO 5 | I6: DATO | J6: ¿REFINANCIACIÓN CON CAPITAL ? | K6: MES DE ENTRADA | L6: IMPORTE | M6: VALORACIÓN EMPRESA (PRE-MONEY) | N6: ACCIONES TOTALES EN CIRCULACIÓN | O6: VALOR MONETARIO POR ACCIÓN | P6: % SOCIEDAD PARA LOS NUEVOS SOCIOS | Q6: VALOR PARA LOS FUNDADORES | R6: OBSERVACIONES
B7: Déficit en el disponible de tesorería | C7: =IF(RESULTADOS!C56>0,0,RESULTADOS!C56) -> 0 | D7: =IF(RESULTADOS!E56>0,0,RESULTADOS!E56) -> 0 | E7: =IF(RESULTADOS!G56>0,0,RESULTADOS!G56) -> 0 | F7: =IF(RESULTADOS!I56>0,0,RESULTADOS!I56) -> 0 | G7: =IF(RESULTADOS!K56>0,0,RESULTADOS!K56) -> 0 | H7: =IF(RESULTADOS!M56>0,0,RESULTADOS!M56) -> 0 | J7: Capital inicial desembolsado por los fundadores | K7: ='HIPOTESIS '!C63 -> 0 | L7: ='HIPOTESIS '!D63 -> 1000 | M7: =L7 -> 1000 | N7: ='HIPOTESIS '!F63 -> 1000 | O7: =L7/N7 -> 1 | P7: 0 | Q7: =O7*N7 -> 1000 | R7: La valoración de empresa en el mes "n" es el valor que las partes acuerdan libremente. Es común que responda a una métrica comercial sobre la que se aplica un múltiplo (por ejemplo un múltiplo de ventas, clientes activos, margen EBITDA, ...). En futuras ampliaciones de capital se genera una prima de emisión como diferencia entre valor nominal y valor real acordado en la valoración. En función de la valoración empresa (pre-money, es decir justo antes de la ampliación) el porcentaje de empresa que toman los socios se calcula por la diferencia entre valor acciones antes y después. Es opcional realizar este cálculo, simplemente para observar el % que se cede en función de comos se "crea" valor. Esta cuestión responde al "dilema de la dilución del emprendedor" del libro "El Viaje del Emprendedor".
B8: Mes en que se produce el pico de déficit anual | C8: =IF(C7>=0,"-",_xlfn.XLOOKUP(C7,RESULTADOS!O56:BW56,RESULTADOS!O29:BW29,-1,-1)) -> - | D8: =IF(D7>=0,"-",_xlfn.XLOOKUP(D7,RESULTADOS!P56:BX56,RESULTADOS!P29:BX29,-1,-1)) -> - | E8: =IF(E7>=0,"-",_xlfn.XLOOKUP(E7,RESULTADOS!Q56:BY56,RESULTADOS!Q29:BY29,-1,-1)) -> - | F8: =IF(F7>=0,"-",_xlfn.XLOOKUP(F7,RESULTADOS!R56:BZ56,RESULTADOS!R29:BZ29,-1,-1)) -> - | G8: =IF(G7>=0,"-",_xlfn.XLOOKUP(G7,RESULTADOS!S56:CA56,RESULTADOS!S29:CA29,-1,-1)) -> - | H8: =IF(H7>=0,"-",_xlfn.XLOOKUP(H7,RESULTADOS!T56:CB56,RESULTADOS!T29:CB29,-1,-1)) -> - | J8: Ampliación de capital 1 (prevista en el mes a indicar) | K8: 21 | L8: 0 | M8: 5000000 | N8: =Ampliación_de_capital_1/(M8/'HIPOTESIS '!F63)+'HIPOTESIS '!F63 -> 1000 | O8: =(Ampliación_de_capital_1+M8)/N8 -> 5000 | P8: =Ampliación_de_capital_1/(Ampliación_de_capital_1+M8) -> 0 | Q8: =O8*N7 -> 5000000
B9: IMPORTE A REFINANCIAR | C9: =IF(H9>0,"Dado que existe déficit de caja se debe refinanciar aumentando capital o con deuda, mediante préstamo participativo (en tal caso usar el cuadro de la derecha para plantear refinanciación)","Dado que no hay déficit financiero las hipótesis financieras se pueden dar por válidas") -> Dado que no hay déficit financiero las hipótesis financieras se pueden dar por válidas | H9: =-IF(MIN(C7:H7)<0,MIN(C7:H7),0) -> 0
B10: MES DE INICIO DE LA REFINANCIACIÓN | H10: =IF(H9>0,_xlfn.XLOOKUP(0.00001,RESULTADOS!P57:BW57,RESULTADOS!P29:BW29,-1,-1),"-") -> - | J10: ¿REFINANCIACIÓN CON DEUDA? | K10: MES DE ENTRADA | L10: IMPORTE | M10: MESES CARENCIA | N10: MESES AMORTIZ. | O10: MES FINAL | P10: % INTERÉS ANUAL | Q10: % INTERÉS PARTICIPATIVO | R10: OBSERVACIONES
J11: Préstamo participativo | K11: 0 | L11: 0 | M11: 24 | N11: 36 | O11: =inicio_prest_participa+carencia_prest_participa+meses_amortiz_prest_participa -> 60 | P11: 0.1 | Q11: 0 | R11: Un préstamo participativo es una forma de inversión con deuda en la empresa. Los inversores puedan optar por inversión en capital (equity), en deuda o formas mixtas. El préstamo participativo se importa como fondos propios. El interés es variable existiendo un interés de inicio muy ventajoso y un interés participativo cuando la empresa ya funciona y que se indexa a beneficios o otros ratios de crecimiento. Amortización con el método alemán (amortización fija).
B12: ANÁLISIS DEL CASH FLOW | C12: AÑO 0 | D12: AÑO 1 | E12: AÑO 2 | F12: AÑO 3 | G12: AÑO 4 | H12: AÑO 5
B13: CF operaciones | C13: =RESULTADOS!C41 -> 0 | D13: =RESULTADOS!E41 -> 0 | E13: =RESULTADOS!G41 -> 0 | F13: =RESULTADOS!I41 -> 0 | G13: =RESULTADOS!K41 -> 0 | H13: =RESULTADOS!M41 -> 0
B14: CF inversiones | C14: =RESULTADOS!C47 -> 0 | D14: =RESULTADOS!E47 -> 0 | E14: =RESULTADOS!G47 -> 0 | F14: =RESULTADOS!I47 -> 0 | G14: =RESULTADOS!K47 -> 0 | H14: =RESULTADOS!M47 -> 0
B15: CF financiación | C15: =RESULTADOS!C54 -> 1000 | D15: =RESULTADOS!E54 -> 0 | E15: =RESULTADOS!G54 -> 0 | F15: =RESULTADOS!I54 -> 0 | G15: =RESULTADOS!K54 -> 0 | H15: =RESULTADOS!M54 -> 0
B16: CF NETO | C16: =RESULTADOS!C55 -> 1000 | D16: =RESULTADOS!E55 -> 0 | E16: =RESULTADOS!G55 -> 0 | F16: =RESULTADOS!I55 -> 0 | G16: =RESULTADOS!K55 -> 0 | H16: =RESULTADOS!M55 -> 0
B17: CF ACUMULADO | C17: =RESULTADOS!C56 -> 1000 | D17: =RESULTADOS!E56 -> 1000 | E17: =RESULTADOS!G56 -> 1000 | F17: =RESULTADOS!I56 -> 1000 | G17: =RESULTADOS!K56 -> 1000 | H17: =RESULTADOS!M56 -> 1000
B18: Burn Rate = CF medio mensual | C18: =C16/12 -> 83.333333 | D18: =D16/12 -> 0 | E18: =E16/12 -> 0 | F18: =F16/12 -> 0 | G18: =G16/12 -> 0 | H18: =H16/12 -> 0
B20: VALORACIÓN DEL PROYECTO POR FLUJOS DE CAJA | C20: AÑO 0 | D20: AÑO 1 | E20: AÑO 2 | F20: AÑO 3 | G20: AÑO 4 | H20: AÑO 5
B21: Desembolso inicial (inversión en año 0) | C21: =RESULTADOS!C47 -> 0
B22: CF neto | D22: =RESULTADOS!E55 -> 0 | E22: =RESULTADOS!G55 -> 0 | F22: =RESULTADOS!I55 -> 0 | G22: =RESULTADOS!K55 -> 0 | H22: =RESULTADOS!M55 -> 0
C23: =C21+C22 -> 0 | D23: =D21+D22 -> 0 | E23: =E21+E22 -> 0 | F23: =F21+F22 -> 0 | G23: =G21+G22 -> 0 | H23: =H21+H22 -> 0
B24: TIR | C24: =IFERROR(IRR(C23:H23),0) -> 0 | I24: Tasa descuento:
B25: Valoración por flujos de caja ( descuento VAN) | C25: =NPV($I$25,D23,E23,F23,G23,H23)+C23 -> 0 | D25: =NPV($I$25,E23,F23,G23,H23)+D23 -> 0 | E25: =NPV($I$25,F23,G23,H23)+E23 -> 0 | F25: =NPV($I$25,G23,H23)+F23 -> 0 | G25: =NPV($I$25,H23)+G23 -> 0 | H25: =NPV($I$25,0)+H23 -> 0 | I25: 0.1
B27: VALORACIÓN POR MÚLTIPLOS | C27: AÑO 0 | D27: AÑO 1 | E27: AÑO 2 | F27: AÑO 3 | G27: AÑO 4 | H27: AÑO 5 | I27: Múltiplo:
B28: Resultado (margen de beneficio o pérdida) | C28: =RESULTADOS!C24 -> 0 | D28: =RESULTADOS!E24 -> 0 | E28: =RESULTADOS!G24 -> 0 | F28: =RESULTADOS!I24 -> 0 | G28: =RESULTADOS!K24 -> 0 | H28: =RESULTADOS!M24 -> 0 | I28: 10
B29: Valoración por múltiplos del resultado (descuento PER) | C29: =IF(C28>0,C28*$I$28,0) -> 0 | D29: =IF(D28>0,D28*$I$28,0) -> 0 | E29: =IF(E28>0,E28*$I$28,0) -> 0 | F29: =IF(F28>0,F28*$I$28,0) -> 0 | G29: =IF(G28>0,G28*$I$28,0) -> 0 | H29: =IF(H28>0,H28*$I$28,0) -> 0
A31: B | B31: ANÁLISIS ECONÓMICO (economics) | I31: =IFERROR(RESULTADOS!O17/I2,"-") -> -
J32: TOOL 8: HOJA DE RUTA DEL PLAN ECONÓMICO FINANCIERO
B33: MÁRGENES | C33: AÑO 1 | D33: AÑO 2 | E33: AÑO 3 | F33: AÑO 4 | G33: AÑO 5
B34: Ingresos | C34: =RESULTADOS!E6 -> 0 | D34: =RESULTADOS!G6 -> 0 | E34: =RESULTADOS!I6 -> 0 | F34: =RESULTADOS!K6 -> 0 | G34: =RESULTADOS!M6 -> 0 | Q34: =IDEA!C11 -> Nombre_Proyecto
B35: Incremento de ingresos | C35: =IFERROR((C34-B34)/B34,"-") -> - | D35: =IFERROR((D34-C34)/C34,"-") -> - | E35: =IFERROR((E34-D34)/D34,"-") -> - | F35: =IFERROR((F34-E34)/E34,"-") -> - | G35: =IFERROR((G34-F34)/F34,"-") -> -
B36: Margen comercial | C36: =IFERROR(RESULTADOS!E12/C34,"-") -> - | D36: =IFERROR(RESULTADOS!G12/D34,"-") -> - | E36: =IFERROR(RESULTADOS!I12/E34,"-") -> - | F36: =IFERROR(RESULTADOS!K12/F34,"-") -> - | G36: =IFERROR(RESULTADOS!M12/G34,"-") -> -
B37: Margen de EBITDA | C37: =IFERROR(RESULTADOS!E17/C34,"-") -> - | D37: =IFERROR(RESULTADOS!G17/D34,"-") -> - | E37: =IFERROR(RESULTADOS!I17/E34,"-") -> - | F37: =IFERROR(RESULTADOS!K17/F34,"-") -> - | G37: =IFERROR(RESULTADOS!M17/G34,"-") -> -
B38: Margen de EBT | C38: =IFERROR(RESULTADOS!E22/C34,"-") -> - | D38: =IFERROR(RESULTADOS!G22/D34,"-") -> - | E38: =IFERROR(RESULTADOS!I22/E34,"-") -> - | F38: =IFERROR(RESULTADOS!K22/F34,"-") -> - | G38: =IFERROR(RESULTADOS!M22/G34,"-") -> -
B39: Margen de BENEFICIO | C39: =IFERROR(RESULTADOS!E24/C34,"-") -> - | D39: =IFERROR(RESULTADOS!G24/D34,"-") -> - | E39: =IFERROR(RESULTADOS!I24/E34,"-") -> - | F39: =IFERROR(RESULTADOS!K24/F34,"-") -> - | G39: =IFERROR(RESULTADOS!M24/G34,"-") -> -
H41: =IFERROR((G41/C41)^(1/5)-1,"-") -> -
B42: PUNTO MUERTO | C42: AÑO 1 | D42: AÑO 2 | E42: AÑO 3 | F42: AÑO 4 | G42: AÑO 5 | H42: CAGR
B43: # tipo A | C43: =SUM('HIPOTESIS '!D143:O143) -> 0 | D43: =SUM('HIPOTESIS '!P143:AA143) -> 0 | E43: =SUM('HIPOTESIS '!AB143:AM143) -> 0 | F43: =SUM('HIPOTESIS '!AN143:AY143) -> 0 | G43: =SUM('HIPOTESIS '!AZ143:BK143) -> 0 | H43: =IFERROR((G43/C43)^(1/5)-1,"-") -> -
B44: # tipo B | C44: =SUM('HIPOTESIS '!D150:O150) -> 0 | D44: =SUM('HIPOTESIS '!P150:AA150) -> 0 | E44: =SUM('HIPOTESIS '!AB150:AM150) -> 0 | F44: =SUM('HIPOTESIS '!AN150:AY150) -> 0 | G44: =SUM('HIPOTESIS '!AZ150:BK150) -> 0 | H44: =IFERROR((G44/C44)^(1/5)-1,"-") -> -
B45: # tipo C | C45: =SUM('HIPOTESIS '!D157:O157) -> 0 | D45: =SUM('HIPOTESIS '!P157:AA157) -> 0 | E45: =SUM('HIPOTESIS '!AB157:AM157) -> 0 | F45: =SUM('HIPOTESIS '!AN157:AY157) -> 0 | G45: =SUM('HIPOTESIS '!AZ157:BK157) -> 0 | H45: =IFERROR((G45/C45)^(1/5)-1,"-") -> -
B46: # A+B+C | C46: =C43+C44+C45 -> 0 | D46: =D43+D44+D45 -> 0 | E46: =E43+E44+E45 -> 0 | F46: =F43+F44+F45 -> 0 | G46: =G43+G44+G45 -> 0 | H46: =IFERROR((G46/C46)^(1/5)-1,"-") -> -
B47: Ventas | C47: =RESULTADOS!E7 -> 0 | D47: =RESULTADOS!G7 -> 0 | E47: =RESULTADOS!I7 -> 0 | F47: =RESULTADOS!K7 -> 0 | G47: =RESULTADOS!M7 -> 0 | H47: =IFERROR((G47/C47)^(1/5)-1,"-") -> -
B48: Costes variables de las ventas | C48: =RESULTADOS!E11 -> 0 | D48: =RESULTADOS!G11 -> 0 | E48: =RESULTADOS!I11 -> 0 | F48: =RESULTADOS!K11 -> 0 | G48: =RESULTADOS!M11 -> 0 | H48: =IFERROR((G48/C48)^(1/5)-1,"-") -> -
B49: Gastos fijos | C49: =(RESULTADOS!E16+RESULTADOS!E15-RESULTADOS!E14+RESULTADOS!E18-RESULTADOS!E19+RESULTADOS!E21)-RESULTADOS!E8 -> 0 | D49: =(RESULTADOS!G16+RESULTADOS!G15-RESULTADOS!G14+RESULTADOS!G18-RESULTADOS!G19+RESULTADOS!G21)-RESULTADOS!G8 -> 0 | E49: =(RESULTADOS!I16+RESULTADOS!I15-RESULTADOS!I14+RESULTADOS!I18-RESULTADOS!I19+RESULTADOS!I21)-RESULTADOS!I8 -> 0 | F49: =(RESULTADOS!K16+RESULTADOS!K15-RESULTADOS!K14+RESULTADOS!K18-RESULTADOS!K19+RESULTADOS!K21)-RESULTADOS!K8 -> 0 | G49: =(RESULTADOS!M16+RESULTADOS!M15-RESULTADOS!M14+RESULTADOS!M18-RESULTADOS!M19+RESULTADOS!M21)-RESULTADOS!M8 -> 0 | H49: =IFERROR((G49/C49)^(1/5)-1,"-") -> -
B50: Gastos fijos + costes variables de las ventas | C50: =C49+C48 -> 0 | D50: =D49+D48 -> 0 | E50: =E49+E48 -> 0 | F50: =F49+F48 -> 0 | G50: =G49+G48 -> 0 | H50: =IFERROR((G50/C50)^(1/5)-1,"-") -> -
B51: Precio venta medio unitario | C51: =IFERROR(C47/C46,0) -> 0 | D51: =IFERROR(D47/D46,0) -> 0 | E51: =IFERROR(E47/E46,0) -> 0 | F51: =IFERROR(F47/F46,0) -> 0 | G51: =IFERROR(G47/G46,0) -> 0 | H51: =IFERROR((G51/C51)^(1/5)-1,"-") -> -
B52: Margen comercial (sin subvenciones) | C52: =RESULTADOS!E12-RESULTADOS!E8 -> 0 | D52: =RESULTADOS!G12-RESULTADOS!G8 -> 0 | E52: =RESULTADOS!I12-RESULTADOS!I8 -> 0 | F52: =RESULTADOS!K12-RESULTADOS!K8 -> 0 | G52: =RESULTADOS!M12-RESULTADOS!M8 -> 0 | H52: =IFERROR((G52/C52)^(1/5)-1,"-") -> -
B53: Margen comercial medio unitario | C53: =IFERROR(C52/C46,0) -> 0 | D53: =IFERROR(D52/D46,0) -> 0 | E53: =IFERROR(E52/E46,0) -> 0 | F53: =IFERROR(F52/F46,0) -> 0 | G53: =IFERROR(G52/G46,0) -> 0 | H53: =IFERROR((G53/C53)^(1/5)-1,"-") -> -
B54: Punto muerto anual (# unidades totales para EBT=0) | C54: =IFERROR(C49/C53,"-") -> - | D54: =IFERROR(D49/D53,"-") -> - | E54: =IFERROR(E49/E53,"-") -> - | F54: =IFERROR(F49/F53,"-") -> - | G54: =IFERROR(G49/G53,"-") -> -
B55: Mes en que se produce el punto muerto | C55: =_xlfn.XLOOKUP(C54,'C'!C129:BK129,'C'!C121:BK121,1,-1) -> 0 | D55: =_xlfn.XLOOKUP(D54,'C'!C129:BK129,'C'!C121:BK121,-1,-1) -> 0 | E55: =_xlfn.XLOOKUP(E54,'C'!C129:BK129,'C'!C121:BK121,-1,-1) -> 0 | F55: =_xlfn.XLOOKUP(F54,'C'!C129:BK129,'C'!C121:BK121,-1,-1) -> 0 | G55: =_xlfn.XLOOKUP(G54,'C'!C129:BK129,'C'!C121:BK121,-1,-1) -> 0
B56: Punto muerto absoluto (mes en que EBT=0) | C56: =IFERROR(_xlfn.XLOOKUP(1,'C'!D149:BK149,'C'!D121:BK121),"Inexistente") -> Inexistente
B57: Punto muerto absoluto (# unidades totales Q para EBT=0) | C57: =IF(C56<>"Inexistente",_xlfn.XLOOKUP(C56,'C'!D121:BK121,'C'!D129:BK129,-1,-1),"Inexistente") -> Inexistente
A60: C | B60: ANÁLISIS PATRIMONIAL (finantial position)
B62: ANÁLISIS DE BALANCE | C62: AÑO 1 | D62: AÑO 2 | E62: AÑO 3 | F62: AÑO 4 | G62: AÑO 5
B63: Patrimonio neto | C63: =RESULTADOS!E71 -> 1000 | D63: =RESULTADOS!G71 -> 1000 | E63: =RESULTADOS!I71 -> 1000 | F63: =RESULTADOS!K71 -> 1000 | G63: =RESULTADOS!M71 -> 1000
B64: Pasivo no corriente | C64: =RESULTADOS!E74 -> 0 | D64: =RESULTADOS!G74 -> 0 | E64: =RESULTADOS!I74 -> 0 | F64: =RESULTADOS!K74 -> 0 | G64: =RESULTADOS!M74 -> 0
B65: Pasivo corriente | C65: =RESULTADOS!E83 -> 0 | D65: =RESULTADOS!G83 -> 0 | E65: =RESULTADOS!I83 -> 0 | F65: =RESULTADOS!K83 -> 0 | G65: =RESULTADOS!M83 -> 0
B66: Activo no corriente | C66: =RESULTADOS!E90 -> 0 | D66: =RESULTADOS!G90 -> 0 | E66: =RESULTADOS!I90 -> 0 | F66: =RESULTADOS!K90 -> 0 | G66: =RESULTADOS!M90 -> 0
B67: Activo corriente | C67: =RESULTADOS!E96 -> 1000 | D67: =RESULTADOS!G96 -> 1000 | E67: =RESULTADOS!I96 -> 1000 | F67: =RESULTADOS!K96 -> 1000 | G67: =RESULTADOS!M96 -> 1000
B68: Fondo de Maniobra | C68: =C67-C65 -> 1000 | D68: =D67-D65 -> 1000 | E68: =E67-E65 -> 1000 | F68: =F67-F65 -> 1000 | G68: =G67-G65 -> 1000
B71: APALANCAMIENTO | C71: AÑO 1 | D71: AÑO 2 | E71: AÑO 3 | F71: AÑO 4 | G71: AÑO 5
B72: Pasivo | C72: =RESULTADOS!E84 -> 0 | D72: =RESULTADOS!G84 -> 0 | E72: =RESULTADOS!I84 -> 0 | F72: =RESULTADOS!K84 -> 0 | G72: =RESULTADOS!M84 -> 0
B73: Patrimonio Neto + Pasivo | C73: =RESULTADOS!E85 -> 1000 | D73: =RESULTADOS!G85 -> 1000 | E73: =RESULTADOS!I85 -> 1000 | F73: =RESULTADOS!K85 -> 1000 | G73: =RESULTADOS!M85 -> 1000
B74: Apalancamiento | C74: =IFERROR(C72/C73,"-") -> 0 | D74: =IFERROR(D72/D73,"-") -> 0 | E74: =IFERROR(E72/E73,"-") -> 0 | F74: =IFERROR(F72/F73,"-") -> 0 | G74: =IFERROR(G72/G73,"-") -> 0
B75: LIQUIDEZ
B76: Pasivo corriente | C76: =RESULTADOS!E83 -> 0 | D76: =RESULTADOS!G83 -> 0 | E76: =RESULTADOS!I83 -> 0 | F76: =RESULTADOS!K83 -> 0 | G76: =RESULTADOS!M83 -> 0 | L76: ¿Qué inversión se requiere? | U76: ¿Qué resultados se consiguen?
B77: Activo corriente | C77: =RESULTADOS!E96 -> 1000 | D77: =RESULTADOS!G96 -> 1000 | E77: =RESULTADOS!I96 -> 1000 | F77: =RESULTADOS!K96 -> 1000 | G77: =RESULTADOS!M96 -> 1000
B78: Liquidez | C78: =IFERROR(C77/C76,"-") -> - | D78: =IFERROR(D77/D76,"-") -> - | E78: =IFERROR(E77/E76,"-") -> - | F78: =IFERROR(F77/F76,"-") -> - | G78: =IFERROR(G77/G76,"-") -> - | L78: INVERSIÓN INICIAL: | N78: =-RESULTADOS!C47 -> 0 | U78: VENTAS AÑO 5: | W78: =G47 -> 0
L79: CAPITAL INICIAL: | N79: =L7 -> 1000 | U79: CAGR Vventas de 1 a 5): | W79: =H47 -> -
B80: RENTABILIDAD | C80: AÑO 1 | D80: AÑO 2 | E80: AÑO 3 | F80: AÑO 4 | G80: AÑO 5 | L80: AMPLIACIÓN DE CAPITAL: | N80: =Ampliación_de_capital_1 -> 0 | U80: RESULTADO AÑO 5: | W80: =RESULTADOS!M24 -> 0
B81: Activo | C81: =RESULTADOS!E97 -> 1000 | D81: =RESULTADOS!G97 -> 1000 | E81: =RESULTADOS!I97 -> 1000 | F81: =RESULTADOS!K97 -> 1000 | G81: =RESULTADOS!M97 -> 1000 | L81: MES DE AMPLIACIÓN: | N81: =IF(N80>0,mes_ampliacion_capital_1,"-") -> - | U81: MARGEN EBT AÑO 5: | W81: =G38 -> -
B82: EBIT | C82: =RESULTADOS!E22 -> 0 | D82: =RESULTADOS!G22 -> 0 | E82: =RESULTADOS!I22 -> 0 | F82: =RESULTADOS!K22 -> 0 | G82: =RESULTADOS!M22 -> 0 | L82: PRÉSTAMO PARTICIPATIVO: | N82: =importe_prest_participa -> 0 | U82: TIR: | W82: =C24 -> 0
B83: ROA | C83: =IFERROR(C82/C81,"-") -> 0 | D83: =IFERROR(D82/D81,"-") -> 0 | E83: =IFERROR(E82/E81,"-") -> 0 | F83: =IFERROR(F82/F81,"-") -> 0 | G83: =IFERROR(G82/G81,"-") -> 0 | L83: MES DE PRÉSTAMO PARTICIPATIVO: | N83: =IF(N82>0,inicio_prest_participa,"-") -> - | U83: PUNTO MUERTO (Q): | W83: =C57 -> Inexistente
B84: Beneficio | C84: =RESULTADOS!E24 -> 0 | D84: =RESULTADOS!G24 -> 0 | E84: =RESULTADOS!I24 -> 0 | F84: =RESULTADOS!K24 -> 0 | G84: =RESULTADOS!M24 -> 0 | L84: % PROPIEDAD DE LOS FUNDADORES | N84: =100%-P8 -> 1 | U84: PUNTO MUERTO (MES): | W84: =C56 -> Inexistente
B85: Patrimonio neto (neto) | C85: =RESULTADOS!E71 -> 1000 | D85: =RESULTADOS!G71 -> 1000 | E85: =RESULTADOS!I71 -> 1000 | F85: =RESULTADOS!K71 -> 1000 | G85: =RESULTADOS!M71 -> 1000 | U85: ROE Máx. | W85: =MAX(C86:G86) -> 0
B86: ROE | C86: =IFERROR(C84/C85,"-") -> 0 | D86: =IFERROR(D84/D85,"-") -> 0 | E86: =IFERROR(E84/E85,"-") -> 0 | F86: =IFERROR(F84/F85,"-") -> 0 | G86: =IFERROR(G84/G85,"-") -> 0 | U86: FONDO DE MANIOBRA AÑO 5: | W86: =G68 -> 1000
B89: PERSONAL EN PLATILLA | C89: AÑO 1 | D89: AÑO 2 | E89: AÑO 3 | F89: AÑO 4 | G89: AÑO 5
B90: Trabajadores en nómina | C90: ='C'!O240 -> 0 | D90: ='C'!AA240 -> 0 | E90: ='C'!AM240 -> 0 | F90: ='C'!AY240 -> 0 | G90: ='C'!BK240 -> 0
B91: Fundadores en nómina | C91: ='C'!O241 -> 0 | D91: ='C'!AA241 -> 0 | E91: ='C'!AM241 -> 0 | F91: ='C'!AY241 -> 0 | G91: ='C'!BK241 -> 0
B92: Ingresos mensual por nómina | C92: ='C'!O242 -> 0 | D92: ='C'!AA242 -> 0 | E92: ='C'!AM242 -> 0 | F92: ='C'!AY242 -> 0 | G92: ='C'!BK242 -> 0
B93: Coste salarial mensual medio | C93: ='C'!O243 -> 0 | D93: ='C'!AA243 -> 0 | E93: ='C'!AM243 -> 0 | F93: ='C'!AY243 -> 0 | G93: ='C'!BK243 -> 0
A99: D | B99: SENSIBILIDAD POR ESCENARIOS (scenarios)
A101: 12 | B101: CUENTA DE RESULTADOS ESCENARIO A | C101: ESCENARIO DE VARIACIONES A | F101: AÑO 1 | G101: % | H101: AÑO 2 | I101: % | J101: AÑO 3 | K101: % | L101: AÑO 4 | M101: % | N101: AÑO 5 | O101: % | V101: EBITDA | Y101: EBT | AB101: ROA
B102: INGRESOS | C102: Modificación de ventas | F102: =F103+F104 -> 0 | G102: =IFERROR(F102/F102,"-") -> - | H102: =H103+H104 -> 0 | I102: =IFERROR(H102/H102,"-") -> - | J102: =J103+J104 -> 0 | K102: =IFERROR(J102/J102,"-") -> - | L102: =L103+L104 -> 0 | M102: =IFERROR(L102/L102,"-") -> - | N102: =N103+N104 -> 0 | O102: =IFERROR(N102/N102,"-") -> - | V102: A | W102: B | X102: C | Y102: A | Z102: B | AA102: C | AB102: A | AC102: B | AD102: C
B103: Ventas | C103: 0 | F103: =RESULTADOS!E7*(1+C103) -> 0 | H103: =RESULTADOS!G7*(1+C103) -> 0 | J103: =RESULTADOS!I7*(1+C103) -> 0 | L103: =RESULTADOS!K7*(1+C103) -> 0 | N103: =RESULTADOS!M7*(1+C103) -> 0
F104: =RESULTADOS!E8 -> 0 | H104: =RESULTADOS!G8 -> 0 | J104: =RESULTADOS!I8 -> 0 | L104: =RESULTADOS!K8 -> 0 | N104: =RESULTADOS!M8 -> 0 | U104: AÑO 1 | V104: =G114 -> - | W104: =G132 -> - | X104: =G150 -> - | Y104: =G116 -> - | Z104: =I116 -> - | AA104: =I152 -> - | AB104: =F117 -> 0 | AC104: =F135 -> 0 | AD104: =F153 -> 0
B106: COSTES DE LAS VENTAS | C106: Modificación de márgenes
B107: Costes de las ventas | C107: 0 | F107: =RESULTADOS!E11*(1-C107) -> 0 | G107: =IFERROR((F103-F107)/F103,"-") -> - | H107: =RESULTADOS!G11*(1-C107) -> 0 | I107: =IFERROR((H103-H107)/H107,"-") -> - | J107: =RESULTADOS!I11*(1-C107) -> 0 | K107: =IFERROR((J103-J107)/J103,"-") -> - | L107: =RESULTADOS!K11*(1-C107) -> 0 | M107: =IFERROR((L103-L107)/L107,"-") -> - | N107: =RESULTADOS!M11*(1-C107) -> 0 | O107: =IFERROR((N103-N107)/N107,"-") -> -
B108: Margen comercial | F108: =F103+F104-F107 -> 0 | G108: =IFERROR(F108/F102,"-") -> - | H108: =H103+H104-H107 -> 0 | I108: =IFERROR(H108/H102,"-") -> - | J108: =J103+J104-J107 -> 0 | K108: =IFERROR(J108/J102,"-") -> - | L108: =L103+L104-L107 -> 0 | M108: =IFERROR(L108/L102,"-") -> - | N108: =N103+N104-N107 -> 0 | O108: =IFERROR(N108/N102,"-") -> -
C109: Modificación de gastos
C110: 0 | U110: AÑO 2 | V110: =I114 -> - | W110: =I132 -> - | X110: =I150 -> - | Y110: =I116 -> - | Z110: =I134 -> - | AA110: =I152 -> - | AB110: =H117 -> 0 | AC110: =H135 -> 0 | AD110: =H153 -> 0
B112: Gastos | F112: =(RESULTADOS!E16+RESULTADOS!E15-RESULTADOS!E14)*(1+C110) -> 0 | H112: =(RESULTADOS!G16+RESULTADOS!G15-RESULTADOS!G14)*(1+C110) -> 0 | J112: =(RESULTADOS!I16+RESULTADOS!I15-RESULTADOS!I14)*(1+C110) -> 0 | L112: =(RESULTADOS!K16+RESULTADOS!K15-RESULTADOS!K14)*(1+C110) -> 0 | N112: =(RESULTADOS!M16+RESULTADOS!M15-RESULTADOS!M14)*(1+C110) -> 0
B113: MÁRGENES
B114: Margen EBITDA | F114: =F108-F112 -> 0 | G114: =IFERROR(F114/F102,"-") -> - | H114: =H108-H112 -> 0 | I114: =IFERROR(H114/H102,"-") -> - | J114: =J108-J112 -> 0 | K114: =IFERROR(J114/J102,"-") -> - | L114: =L108-L112 -> 0 | M114: =IFERROR(L114/L102,"-") -> - | N114: =N108-N112 -> 0 | O114: =IFERROR(N114/N102,"-") -> -
B115: Margen EBIT | F115: =F114-RESULTADOS!E18+RESULTADOS!E19 -> 0 | G115: =IFERROR(F115/F102,"-") -> - | H115: =H114-RESULTADOS!G18+RESULTADOS!G19 -> 0 | I115: =IFERROR(H115/H102,"-") -> - | J115: =J114-RESULTADOS!I18+RESULTADOS!I19 -> 0 | K115: =IFERROR(J115/J102,"-") -> - | L115: =L114-RESULTADOS!K18+RESULTADOS!K19 -> 0 | M115: =IFERROR(L115/L102,"-") -> - | N115: =N114-RESULTADOS!M18+RESULTADOS!M19 -> 0 | O115: =IFERROR(N115/N102,"-") -> -
B116: Margen EBT | F116: =F115-RESULTADOS!E21 -> 0 | G116: =IFERROR(F116/F102,"-") -> - | H116: =H115-RESULTADOS!G21 -> 0 | I116: =IFERROR(H116/H102,"-") -> - | J116: =J115-RESULTADOS!I21 -> 0 | K116: =IFERROR(J116/J102,"-") -> - | L116: =L115-RESULTADOS!K21 -> 0 | M116: =IFERROR(L116/L102,"-") -> - | N116: =N115-RESULTADOS!M21 -> 0 | O116: =IFERROR(N116/N102,"-") -> - | U116: AÑO 3 | V116: =K114 -> - | W116: =K132 -> - | X116: =K150 -> - | Y116: =M116 -> - | Z116: =K134 -> - | AA116: =K152 -> - | AB116: =J117 -> 0 | AC116: =J135 -> 0 | AD116: =J153 -> 0
B117: ROA | F117: =IFERROR(F115/C$81,"-") -> 0 | H117: =IFERROR(H115/D$81,"-") -> 0 | J117: =IFERROR(J115/E$81,"-") -> 0 | L117: =IFERROR(L115/F$81,"-") -> 0 | N117: =IFERROR(N115/G$81,"-") -> 0
B119: CUENTA DE RESULTADOS ESCENARIO B | C119: ESCENARIO DE VARIACIONES B | F119: AÑO 1 | G119: % | H119: AÑO 2 | I119: % | J119: AÑO 3 | K119: % | L119: AÑO 4 | M119: % | N119: AÑO 5 | O119: %
B120: INGRESOS | C120: Modificación de ventas | F120: =F121+F122 -> 0 | G120: =IFERROR(F120/F120,"-") -> - | H120: =H121+H122 -> 0 | I120: =IFERROR(H120/H120,"-") -> - | J120: =J121+J122 -> 0 | K120: =IFERROR(J120/J120,"-") -> - | L120: =L121+L122 -> 0 | M120: =IFERROR(L120/L120,"-") -> - | N120: =N121+N122 -> 0 | O120: =IFERROR(N120/N120,"-") -> -
B121: Ventas | C121: 0.3 | F121: =RESULTADOS!E7*(1+C121) -> 0 | H121: =RESULTADOS!G7*(1+C121) -> 0 | J121: =RESULTADOS!I7*(1+C121) -> 0 | L121: =RESULTADOS!K7*(1+C121) -> 0 | N121: =RESULTADOS!M7*(1+C121) -> 0
F122: =RESULTADOS!E8 -> 0 | H122: =RESULTADOS!G8 -> 0 | J122: =RESULTADOS!I8 -> 0 | L122: =RESULTADOS!K8 -> 0 | N122: =RESULTADOS!M8 -> 0 | U122: AÑO 4 | V122: =M114 -> - | W122: =M132 -> - | X122: =M150 -> - | Y122: =O116 -> - | Z122: =M134 -> - | AA122: =M152 -> - | AB122: =L117 -> 0 | AC122: =L135 -> 0 | AD122: =L153 -> 0
B124: COSTES DE LAS VENTAS | C124: Modificación de márgenes
...

Sheet Sheet2
C6: RATIO | D6: FÓRMULA | E6: EXPLICACIÓN | F6: LÍMITES
B7: RATIOS DE LIQUIDEZ | C7: LIQUIDEZ | D7: ACTIVO CORRIENTE | E7: Capacidad para hacer frente a las obligaciones a corto. Si es muy baja existe peligro de insolvencia. Si es muy alta es que tenemos activos improductivos | F7: Valores razonables entre 1 y 2 aunque difiere según el sector y en sectores donde se cobra al contado y se pago aplazado puede ser menor a 0.
D8: PASIVO CORRIENTE
C9: TESORERÍA | D9: DISPONIBLE | E9: Capacidad para pagar deudas a corto con el dinero efectivo (depende del sector) | F9: Valores razonables entre 0,1 y 0, 5, aunque difiere según el sector
D10: PASIVO CORRIENTE
B11: RATIOS DE SOLVENCIA | C11: AUTONOMÍA FINANCIERA | D11: PATRIMONIO NETO | E11: Da idea de la independencia financiera de la empresa | F11: Cuanto mayor más autonomía
D12: PASIVO
C13: APALANCAMIENTO | D13: PATRIMONIO NETO | E13: Indica como de endeudada está la empresa | F13: Si el coste de la deuda es bajo (muy inferior a la rentabilidad) es una forma de dar eficiencia del patrimonio neto.
D14: ACTIVO
C16: RATIO | D16: FÓRMULA | E16: EXPLICACIÓN | F16: LÍMITES
B17: RATIOS ECONÓMICOS | C17: RENTABILIDAD DEL CAPITAL (ROE) | D17: BENEFICIO NETO | E17: Indica la rentabilidad que está teniendo la inversión de los socios | F17: Cuanto más alto mejor (lo cual se consigue tanto con beneficio como también con alto apalancamiento, es decir poco patrimonio neto)
D18: PATRIMONIO NETO
C19: RENTABILIDAD DEL ACTICO (ROA o ROI) | D19: EBIT | E19: Indica la capacidad de los activos de la empresa para dar beneficios (con independencia del resultado financiero) | F19: Cuanto más alto mejor
D20: ACTIVO
C21: RENTABILIDAD COMERCIAL (MARGEN) | D21: BENEFICIO NETO | E21: Indica el margen sobre ventas con que la empresa trabaja | F21: Cuanto más alto mejor
D22: VENTAS
C23: ROTACIÓN DE ACTIVOS | D23: VENTAS | E23: Indica si los activos rinden a máxima capacidad o están siendo infrautilizados (depende del sector de actividad) | F23: Cuanto mayor más eficiente es la empresa. Si es muy alto puede significar poca capacidad de respuesta a incrementos de ventas
D24: ACTIVO
C26: MÉTRICA | D26: FÓRMULA HOJA CÁLCULO | E26: EXPLICACIÓN | F26: LIMITES
B27: INDICADORES DE GESTIÓN | C27: FONDO DE MANIOBRA (FP) | D27: AC-PC | E27: Es la diferencia de activo circulante con pasivo circulante. Indica el déficit teórico de la empresa para hacer frente a necesidades financieras | F27: El valor depende del sector/modelo de negocio. En general debe ser positivo.
C28: PUNTO MUERTO | D28: Ingresos-Gastos=0 | E28: Es el punto (medido en cantidad de unidades vendidas o el mes concreto) en que las ventas son mayores a la suma de gastos fijos y variables | F28: Cuanto antes mejor
C29: REFINANCIACIÓN | D29: Cashf flow <0 | E29: Es valor de pico de déficit de caja. Si es negativo indica el momento y importe de la refinanciación preceptiva en hipótesis financieras. | F29: En función del punto muerto y otros pagos
C30: VAN | D30: VNA | E30: Mide la rentabilidad acumulada de la inversión en términos de capa generada partir de la diferencia entre el desembolso inicial y los flujos de tesorería previstos a lo largo de los años llevados a valor presente con una tasa de descuento r. | F30: Mayor a 0 para recuperar el desembolso inicial (inversión)
C31: TIR | D31: TIR | E31: Indica la tasa r tal que el VAN es de 0. Es decir a que porcentaje se deben descontar los flujos de caja futuros y el valor residual, para recuperar el desembolso. | F31: Cuanto mayor mejor pues indica más rentabilidad (al menos debe ser mayor a la rentabilidad que ofrece la renta fija asegurada)
